Workbook

Sheet Historical Data
A1: Bharti Airtel Limited
A2: Historical Data | L2: ( Rs. In Cr )
C4: Income | H4: 2022 | I4: =H4+1 -> 2023 | J4: =I4+1 -> 2024 | K4: =J4+1 -> 2025 | L4: =K4+1 -> 2026
D5: Revenue from operations | H5: 1165469 | I5: 1391448 | J5: 1499824 | K5: 1729852 | L5: 2109728
D6: Other income | H6: 5343 | I6: 9366 | J6: 14354 | K6: 15737 | L6: 28173
D7: Total income | H7: 1170812 | I7: 1400814 | J7: 1514178 | K7: 1745589 | L7: 2137901
C9: Expenses
D10: Network operating expenses | H10: 250205 | I10: 285433 | J10: 300188 | K10: 335043 | L10: 397500
D11: Access charges | H11: 67611 | I11: 76207 | J11: 75185 | K11: 71713 | L11: 55416
D12: License fee / Spectrum charges | H12: 110636 | I12: 117517 | J12: 120358 | K12: 138290 | L12: 153729
D13: Employee benefits expense | H13: 44333 | I13: 48308 | J13: 53231 | K13: 63089 | L13: 75813
D14: Sales and marketing expenses | H14: 53035 | I14: 72454 | J14: 81326 | K14: 114601 | L14: 131073
D15: Other expenses | H15: 64310 | I15: 78794 | J15: 86618 | K15: 75524 | L15: 99452
D16: Total expenses | H16: 590130 | I16: 678713 | J16: 716906 | K16: 798260 | L16: 912983
C18: EBITDA* (Profit before D&A, finance costs, share of associates'/JVs' profit or loss, exceptional items and tax) | H18: 580682 | I18: 722101 | J18: 797272 | K18: 947329 | L18: 1224918
D19: Depreciation and amortisation expenses | H19: 330907 | I19: 364318 | J19: 395376 | K19: 455703 | L19: 527108
D20: Finance costs | H20: 166162 | I20: 192999 | J20: 226477 | K20: 217539 | L20: 215553
D21: Share of profit / (loss) of associates and joint ventures (net) | H21: 24232 | I21: 7521 | J21: 27094 | K21: 37030 | L21: 3645
C22: Profit before exceptional items and tax | H22: 107845 | I22: 172305 | J22: 202513 | K22: 311117 | L22: 485902
D23: Exceptional items (net) | H23: 16986 | I23: -6698 | J23: -75723 | K23: 72868 | L23: -34175
C24: Profit before tax | H24: 124831 | I24: 165607 | J24: 126790 | K24: 383985 | L24: 451727
D26: Tax expense / (credit)
D27: Current tax | H27: 30331 | I27: 34831 | J27: 41498 | K27: 41121 | L27: 78812
D28: Deferred tax | H28: 11448 | I28: 7902 | J28: -288 | K28: -31949 | L28: 34687
D29: Total tax expense | H29: 41779 | I29: 42733 | J29: 41210 | K29: 9172 | L29: 113499
C30: Profit for the year | H30: 83052 | I30: 122874 | J30: 85580 | K30: 374813 | L30: 338228
A32: Balance Sheet
B33: ASSETS
C34: Non-current assets
D35: Property, plant and equipment | H35: 905725 | I35: 952241 | J35: 1066121 | K35: 1432724 | L35: 1570659
D36: Capital work-in-progress | H36: 42386 | I36: 110293 | J36: 89077 | K36: 105962 | L36: 126131
D37: Right-of-use assets | H37: 322286 | I37: 546466 | J37: 559367 | K37: 602415 | L37: 673244
D38: Goodwill | H38: 338313 | I38: 337741 | J38: 265017 | K38: 516974 | L38: 566859
D39: Other intangible assets | H39: 874509 | I39: 937490 | J39: 1142526 | K39: 1332569 | L39: 1252604
D40: Intangible assets under development | H40: 17161 | I40: 383961 | J40: 79964 | K40: 4027 | L40: 3250
D41: Investment in joint ventures and associates | H41: 284268 | I41: 281838 | J41: 312404 | K41: 36416 | L41: 40622
D42: Financial assets - Investments | H42: 609 | I42: 656 | J42: 924 | K42: 5435 | L42: 11385
D43: Financial assets - Derivative instruments | H43: 218 | I43: 854 | J43: 65
D44: Financial assets - Trade receivables | J44: 1805 | K44: 2131 | L44: 2544
D45: Financial assets - Loans | K45: 865
D46: Financial assets - Other financial assets | H46: 22515 | I46: 25963 | J46: 26557 | K46: 37471 | L46: 35700
D47: Income tax assets (net) | H47: 17479 | I47: 20399 | J47: 14135 | K47: 24978 | L47: 20181
D48: Deferred tax assets (net) | H48: 199250 | I48: 189519 | J48: 192428 | K48: 249111 | L48: 191413
D49: Other non-current assets | H49: 91562 | I49: 103898 | J49: 112159 | K49: 116638 | L49: 124770
C50: Total non-current assets | H50: 3116281 | I50: 3891319 | J50: 3862549 | K50: 4467716 | L50: 4619362
C52: Current assets
D53: Inventories | H53: 3750 | I53: 2576 | J53: 3639 | K53: 4517 | L53: 6009
D54: Financial assets - Investments | H54: 8614 | I54: 47045 | J54: 2695 | K54: 16532 | L54: 137006
D55: Financial assets - Derivative instruments | H55: 561 | I55: 1283 | J55: 1168 | K55: 813 | L55: 5040
D56: Financial assets - Trade receivables | H56: 40562 | I56: 39815 | J56: 47277 | K56: 74557 | L56: 79776
D57: Financial assets - Cash and cash equivalents | H57: 60959 | I57: 71794 | J57: 69155 | K57: 61056 | L57: 137222
D58: Financial assets - Other bank balances | H58: 73984 | I58: 62392 | J58: 94244 | K58: 106143 | L58: 166546
D59: Financial assets - Other financial assets | H59: 214697 | I59: 220865 | J59: 249544 | K59: 267662 | L59: 244264
D60: Other current assets | H60: 117152 | I60: 129243 | J60: 115039 | K60: 144608 | L60: 125718
D61: Assets held for sale | L61: 573
C62: Total current assets | H62: 520279 | I62: 575013 | J62: 582761 | K62: 675888 | L62: 902154
C63: TOTAL ASSETS | H63: 3636560 | I63: 4466332 | J63: 4445310 | K63: 5143604 | L63: 5521516
C65: EQUITY AND LIABILITIES
D66: Equity
D67: Share capital | H67: 27950 | I67: 28366 | J67: 28766 | K67: 29001 | L67: 30468
D68: Other equity | H68: 637593 | I68: 747263 | J68: 791422 | K68: 1107718 | L68: 1460098
C69: Equity attributable to owners of the Parent | H69: 665543 | I69: 775629 | J69: 820188 | K69: 1136719 | L69: 1490566
D70: Non-controlling interests (NCI) | H70: 253807 | I70: 288814 | J70: 235451 | K70: 397958 | L70: 469068
C71: Total equity | H71: 919350 | I71: 1064443 | J71: 1055639 | K71: 1534677 | L71: 1959634
C73: Non-current liabilities
D74: Financial liabilities - Borrowings | H74: 1135350 | I74: 1515686 | J74: 1309626 | K74: 1048638 | L74: 1000849
D75: Financial liabilities - Lease liabilities | H75: 290562 | I75: 508295 | J75: 539271 | K75: 556701 | L75: 644996
D76: Financial liabilities - Derivative instruments | H76: 174 | I76: 3523 | J76: 2890
D77: Financial liabilities - Other financial liabilities | H77: 90116 | I77: 97311 | J77: 85036 | K77: 38642 | L77: 26320
D78: Deferred revenue | H78: 30258 | I78: 30901 | J78: 34139 | K78: 35185 | L78: 40185
D79: Provisions | H79: 4639 | I79: 4744 | J79: 5443 | K79: 30396 | L79: 35189
D80: Deferred tax liabilities (net) | H80: 24488 | I80: 20762 | J80: 25118 | K80: 93549 | L80: 67789
D81: Other non-current liabilities | H81: 1363 | I81: 1029 | J81: 1470 | K81: 1414 | L81: 1497
D82: Total non-current liabilities | H82: 1576950 | I82: 2182251 | J82: 2002993 | K82: 1804525 | L82: 1816825
C84: Current liabilities
D85: Financial liabilities - Borrowings | H85: 193795 | I85: 139762 | J85: 209539 | K85: 434485 | L85: 215865
D86: Financial liabilities - Lease liabilities | H86: 77072 | I86: 96460 | J86: 97487 | K86: 96597 | L86: 92407
D87: Financial liabilities - Derivative instruments | H87: 995 | I87: 1117 | J87: 12207 | K87: 1921 | L87: 1918
D88: Financial liabilities - Trade payables | H88: 292741 | I88: 328946 | J88: 351325 | K88: 381537 | L88: 450152
D89: Financial liabilities - Other financial liabilities | H89: 194415 | I89: 241951 | J89: 253456 | K89: 333024 | L89: 408659
D90: Deferred revenue | H90: 75929 | I90: 84995 | J90: 87262 | K90: 97729 | L90: 109487
D91: Provisions | H91: 243449 | I91: 257292 | J91: 283282 | K91: 361552 | L91: 357828
D92: Current tax liabilities (net) | H92: 20725 | I92: 17972 | J92: 33031 | K92: 20035 | L92: 31400
D93: Other current liabilities | H93: 41139 | I93: 51143 | J93: 59089 | K93: 77522 | L93: 77341
D94: Total current liabilities | H94: 1140260 | I94: 1219638 | J94: 1386678 | K94: 1804402 | L94: 1745057
D95: Total liabilities | H95: 2717210 | I95: 3401889 | J95: 3389671 | K95: 3608927 | L95: 3561882
C96: TOTAL EQUITY AND LIABILITIES | H96: 3636560 | I96: 4466332 | J96: 4445310 | K96: 5143604 | L96: 5521516
A98: Cash Flow
C99: Cash flows from operating activities
D100: Profit before tax | H100: 124831 | I100: 165607 | J100: 126790 | K100: 383985 | L100: 451727
D101: Adjustments for:
D102: Depreciation and amortisation expenses | H102: 330907 | I102: 364318 | J102: 395376 | K102: 455703 | L102: 527108
D103: Finance costs | H103: 165241 | I103: 188434 | J103: 219337 | K103: 216258 | L103: 214485
D104: Dividend income | L104: -272
D105: Net gain on fair value through profit or loss (FVTPL) instruments | H105: -1067 | I105: -2474 | J105: -2645 | K105: -2048 | L105: -3369
D106: Gain on deemed disposal of subsidiary
D107: Interest income | H107: -2206 | I107: -3080 | J107: -6493 | K107: -5306 | L107: -11158
D108: Net loss / (gain) on derivative financial instruments | H108: 947 | I108: 3013 | J108: 6319 | K108: 420 | L108: -2017
D109: Share of profit of associates and joint ventures (net) | H109: -24232 | I109: -7521 | J109: -27094 | K109: -37030 | L109: -3645
D110: Exceptional items (net) | H110: -11705 | I110: 6698 | J110: 75723 | K110: -72868 | L110: 34175
...

Sheet Model
A1: Bharti Airtel Limited | H1: Historical Period | M1: Forecasted Period
A2: Financial Statement Analysis & Valuation | H2: 2022 | I2: =H2+1 -> 2023 | J2: =I2+1 -> 2024 | K2: =J2+1 -> 2025 | L2: =K2+1 -> 2026 | M2: =L2+1 -> 2027 | N2: =M2+1 -> 2028 | O2: =N2+1 -> 2029 | P2: =O2+1 -> 2030 | Q2: =P2+1 -> 2031
G3: =IF(E4=Scenario!D6,1,IF(E4=Scenario!D7,2,3)) -> 2
B4: LIVE SCENARIO | E4: Bull Case
C5: Revenue Growth as % | I5: =(I20-H20)/H20 -> 0.19389533 | J5: =(J20-I20)/I20 -> 0.077887208 | K5: =(K20-J20)/J20 -> 0.15337 | L5: =(L20-K20)/K20 -> 0.21960029 | M5: {=CHOOSE(G3,Scenario!H6:L6,Scenario!H7:L7,Scenario!H8:L8)} -> 0.2230534 | N5: 0.20089907 | O5: 0.18094517 | P5: 0.16297315 | Q5: 0.14678617
C6: COGS as % of Revenue | H6: =H21/-H20 -> 0.36762196 | I6: =I21/-I20 -> 0.34435854 | J6: =J21/-J20 -> 0.33052612 | K6: =K21/-K20 -> 0.31508245 | L6: =L21/-L20 -> 0.28754655 | M6: =AVERAGE(H6:L6) -> 0.32902712 | N6: =M6 -> 0.32902712 | O6: =N6 -> 0.32902712 | P6: =O6 -> 0.32902712 | Q6: =P6 -> 0.32902712
C7: Operating Expense as % of Revenue | H7: =H23/-H20 -> 0.13872355 | I7: =I23/-I20 -> 0.14341607 | J7: =J23/-J20 -> 0.1474673 | K7: =K23/-K20 -> 0.146379 | L7: =L23/-L20 -> 0.1452026 | M7: =AVERAGE(H7:L7) -> 0.1442377 | N7: =M7 -> 0.1442377 | O7: =N7 -> 0.1442377 | P7: =O7 -> 0.1442377 | Q7: =P7 -> 0.1442377
C8: Depreciation & Amortization as % of PP&E | H8: =H25/-H42 -> 0.34901715 | I8: =I25/-I42 -> 0.34287656 | J8: =J25/-J42 -> 0.34225821 | K8: =K25/-K42 -> 0.29616374 | L8: =L25/-L42 -> 0.31065011 | M8: =AVERAGE(H8:L8) -> 0.32819315 | N8: =M8 -> 0.32819315 | O8: =N8 -> 0.32819315 | P8: =O8 -> 0.32819315 | Q8: =P8 -> 0.32819315
C9: Interest as % of Debt | H9: =H27/-H54 -> 0.097927898 | I9: =I27/-I54 -> 0.085390118 | J9: =J27/-J54 -> 0.10504874 | K9: =K27/-K54 -> 0.10182403 | L9: =L27/-L54 -> 0.11030711 | M9: =AVERAGE(H9:L9) -> 0.10009958 | N9: =M9 -> 0.10009958 | O9: =N9 -> 0.10009958 | P9: =O9 -> 0.10009958 | Q9: =P9 -> 0.10009958
C10: Tax as % of Pre-Tax Income | H10: =H30/-H29 -> 0.33468449 | I10: =I30/-I29 -> 0.25803861 | J10: =J30/-J29 -> 0.32502563 | K10: =K30/-K29 -> 0.02388635 | L10: =L30/-L29 -> 0.25125574 | M10: =AVERAGE(H10:L10) -> 0.23857816 | N10: =M10 -> 0.23857816 | O10: =N10 -> 0.23857816 | P10: =O10 -> 0.23857816 | Q10: =P10 -> 0.23857816
C11: Other Income as % of Revenue | H11: =H28/H20 -> 0.039950441 | I11: =I28/I20 -> 0.0073225877 | J11: =J28/J20 -> -0.022852681 | K11: =K28/K20 -> 0.072627601 | L11: =L28/L20 -> -0.0011172056 | M11: =AVERAGE(H11:L11) -> 0.019186148 | N11: =M11 -> 0.019186148 | O11: =N11 -> 0.019186148 | P11: =O11 -> 0.019186148 | Q11: =P11 -> 0.019186148
C12: Dividend Payout Ratio | H12: =H86/-H31 -> 0.17384289 | I12: =I86/-I31 -> 0.29215294 | J12: =J86/-J31 -> 0.4889577 | K12: =K86/-K31 -> 0.18502293 | L12: =L86/-L31 -> 0.33491314 | M12: =AVERAGE(H12:L12) -> 0.29497792 | N12: =M12 -> 0.29497792 | O12: =N12 -> 0.29497792 | P12: =O12 -> 0.29497792 | Q12: =P12 -> 0.29497792
C13: Day's Sales Outstanding | H13: =H38/H20*365 -> 12.703152 | I13: =I38/I20*365 -> 10.444138 | J13: =J38/J20*365 -> 11.50542 | K13: =K38/K20*365 -> 15.73158 | L13: =L38/L20*365 -> 13.801893 | M13: =AVERAGE(H13:L13) -> 12.837237 | N13: =M13 -> 12.837237 | O13: =N13 -> 12.837237 | P13: =O13 -> 12.837237 | Q13: =P13 -> 12.837237
C14: Day's Inventory Outstanding | H14: =H37/-H21*365 -> 3.1946402 | I14: =I37/-I21*365 -> 1.9622796 | J14: =J37/-J21*365 -> 2.6793463 | K14: =K37/-K21*365 -> 3.0248915 | L14: =L37/-L21*365 -> 3.6154341 | M14: =AVERAGE(H14:L14) -> 2.8953183 | N14: =M14 -> 2.8953183 | O14: =N14 -> 2.8953183 | P14: =O14 -> 2.8953183 | Q14: =P14 -> 2.8953183
C15: Days's Payable Outstanding | H15: =H50/-H21*365 -> 249.38725 | I15: =I50/-I21*365 -> 250.5761 | J15: =J50/-J21*365 -> 258.67582 | K15: =K50/-K21*365 -> 255.50321 | L15: =L50/-L21*365 -> 270.84288 | M15: =AVERAGE(H15:L15) -> 256.99705 | N15: =M15 -> 256.99705 | O15: =N15 -> 256.99705 | P15: =O15 -> 256.99705 | Q15: =P15 -> 256.99705
C16: Capital Asset Turnover Ratio | H16: =H20/(H42+H43) -> 0.63348246 | I16: =I20/(I42+I43) -> 0.58366475 | J16: =J20/(J42+J43) -> 0.63079092 | K16: =K20/(K42+K43) -> 0.60162864 | L16: =L20/(L42+L43) -> 0.71452163 | M16: =AVERAGE(H16:L16) -> 0.63281768 | N16: =M16 -> 0.63281768 | O16: =N16 -> 0.63281768 | P16: =O16 -> 0.63281768 | Q16: =P16 -> 0.63281768
A18: INCOME STATEMENT
C20: Revenue | H20: ='Historical Data'!H5 -> 1165469 | I20: ='Historical Data'!I5 -> 1391448 | J20: ='Historical Data'!J5 -> 1499824 | K20: ='Historical Data'!K5 -> 1729852 | L20: ='Historical Data'!L5 -> 2109728 | M20: =L20*(1+M5) -> 2580310 | N20: =M20*(1+N5) -> 3098691.9 | O20: =N20*(1+O5) -> 3659385.2 | P20: =O20*(1+P5) -> 4255766.8 | Q20: =P20*(1+Q5) -> 4880454.5
C21: Less: Cost of Good Sold | H21: =-SUM('Historical Data'!H10:H12) -> -428452 | I21: =-SUM('Historical Data'!I10:I12) -> -479157 | J21: =-SUM('Historical Data'!J10:J12) -> -495731 | K21: =-SUM('Historical Data'!K10:K12) -> -545046 | L21: =-SUM('Historical Data'!L10:L12) -> -606645 | M21: =M20*-M6 -> -848991.98 | N21: =N20*-N6 -> -1019553.7 | O21: =O20*-O6 -> -1204037 | P21: =P20*-P6 -> -1400262.7 | Q21: =Q20*-Q6 -> -1605801.9
C22: Gross Profit | H22: =SUM(H20:H21) -> 737017 | I22: =SUM(I20:I21) -> 912291 | J22: =SUM(J20:J21) -> 1004093 | K22: =SUM(K20:K21) -> 1184806 | L22: =SUM(L20:L21) -> 1503083 | M22: =SUM(M20:M21) -> 1731318 | N22: =SUM(N20:N21) -> 2079138.2 | O22: =SUM(O20:O21) -> 2455348.2 | ... Q22: =SUM(Q20:Q21) -> 3274652.6
C23: Less: Operating Expense | H23: =-SUM('Historical Data'!H13:H15) -> -161678 | I23: =-SUM('Historical Data'!I13:I15) -> -199556 | J23: =-SUM('Historical Data'!J13:J15) -> -221175 | K23: =-SUM('Historical Data'!K13:K15) -> -253214 | L23: =-SUM('Historical Data'!L13:L15) -> -306338 | M23: =M20*-M7 -> -372177.99 | N23: =N20*-N7 -> -446948.21 | O23: =O20*-O7 -> -527821.33 | P23: =P20*-P7 -> -613842.03 | Q23: =Q20*-Q7 -> -703945.55
C24: EBITDA | H24: =SUM(H22:H23) -> 575339 | I24: =SUM(I22:I23) -> 712735 | J24: =SUM(J22:J23) -> 782918 | K24: =SUM(K22:K23) -> 931592 | L24: =SUM(L22:L23) -> 1196745 | M24: =SUM(M22:M23) -> 1359140 | N24: =SUM(N22:N23) -> 1632190 | O24: =SUM(O22:O23) -> 1927526.9 | ... Q24: =SUM(Q22:Q23) -> 2570707
C25: Less: Depreciation & Amortization | H25: =-'Historical Data'!H19 -> -330907 | I25: =-'Historical Data'!I19 -> -364318 | J25: =-'Historical Data'!J19 -> -395376 | K25: =-'Historical Data'!K19 -> -455703 | L25: =-'Historical Data'!L19 -> -527108 | M25: =M106 -> -969037.55 | N25: =N106 -> -895060.23 | O25: =O106 -> -870151.82 | P25: =P106 -> -875361.84 | Q25: =Q106 -> -897370.65
C26: EBIT | H26: =SUM(H24:H25) -> 244432 | I26: =SUM(I24:I25) -> 348417 | J26: =SUM(J24:J25) -> 387542 | K26: =SUM(K24:K25) -> 475889 | L26: =SUM(L24:L25) -> 669637 | M26: =SUM(M24:M25) -> 390102.5 | N26: =SUM(N24:N25) -> 737129.78 | O26: =SUM(O24:O25) -> 1057375.1 | ... Q26: =SUM(Q24:Q25) -> 1673336.4
C27: Less: Interest | H27: =-'Historical Data'!H20 -> -166162 | I27: =-'Historical Data'!I20 -> -192999 | J27: =-'Historical Data'!J20 -> -226477 | K27: =-'Historical Data'!K20 -> -217539 | L27: =-'Historical Data'!L20 -> -215553 | M27: =M113 -> -195606.29 | N27: =N113 -> -175291.01 | O27: =O113 -> -154975.74 | P27: =P113 -> -134660.46 | Q27: =Q113 -> -114345.19
C28: Other Income | H28: =SUM('Historical Data'!H6,'Historical Data'!H21,'Historical Data'!H23) -> 46561 | I28: =SUM('Historical Data'!I6,'Historical Data'!I21,'Historical Data'!I23) -> 10189 | J28: =SUM('Historical Data'!J6,'Historical Data'!J21,'Historical Data'!J23) -> -34275 | K28: =SUM('Historical Data'!K6,'Historical Data'!K21,'Historical Data'!K23) -> 125635 | L28: =SUM('Historical Data'!L6,'Historical Data'!L21,'Historical Data'!L23) -> -2357 | M28: =M20*M11 -> 49506.211 | N28: =N20*N11 -> 59451.962 | O28: =O20*O11 -> 70209.508 | P28: =P20*P11 -> 81651.773 | Q28: =Q20*Q11 -> 93637.123
C29: Profit Before Tax | H29: =SUM(H26:H28) -> 124831 | I29: =SUM(I26:I28) -> 165607 | J29: =SUM(J26:J28) -> 126790 | K29: =SUM(K26:K28) -> 383985 | L29: =SUM(L26:L28) -> 451727 | M29: =SUM(M26:M28) -> 244002.42 | N29: =SUM(N26:N28) -> 621290.73 | O29: =SUM(O26:O28) -> 972608.86 | ... Q29: =SUM(Q26:Q28) -> 1652628.3
C30: Less: Tax | H30: =-SUM('Historical Data'!H27:H28) -> -41779 | I30: =-SUM('Historical Data'!I27:I28) -> -42733 | J30: =-SUM('Historical Data'!J27:J28) -> -41210 | K30: =-SUM('Historical Data'!K27:K28) -> -9172 | L30: =-SUM('Historical Data'!L27:L28) -> -113499 | M30: =M29*-M10 -> -58213.649 | N30: =N29*-N10 -> -148226.4 | O30: =O29*-O10 -> -232043.24 | P30: =P29*-P10 -> -313322.68 | Q30: =Q29*-Q10 -> -394281.03
C31: Profit After Tax | H31: =SUM(H29:H30) -> 83052 | I31: =SUM(I29:I30) -> 122874 | J31: =SUM(J29:J30) -> 85580 | K31: =SUM(K29:K30) -> 374813 | L31: =SUM(L29:L30) -> 338228 | M31: =SUM(M29:M30) -> 185788.77 | N31: =SUM(N29:N30) -> 473064.33 | O31: =SUM(O29:O30) -> 740565.62 | ... Q31: =SUM(Q29:Q30) -> 1258347.3
A33: BALANCE SHEET
A35: Current Assets
B36: Cash & Bank | H36: ='Historical Data'!H58+'Historical Data'!H57 -> 134943 | I36: ='Historical Data'!I58+'Historical Data'!I57 -> 134186 | J36: ='Historical Data'!J58+'Historical Data'!J57 -> 163399 | K36: ='Historical Data'!K58+'Historical Data'!K57 -> 167199 | L36: ='Historical Data'!L58+'Historical Data'!L57 -> 303768 | M36: =M92 -> 593134.56 | N36: =N92 -> 900108.29 | O36: =O92 -> 1312109.6 | P36: =P92 -> 1862729.8 | Q36: =Q92 -> 2578279.1
B37: Inventories | H37: ='Historical Data'!H53 -> 3750 | I37: ='Historical Data'!I53 -> 2576 | J37: ='Historical Data'!J53 -> 3639 | K37: ='Historical Data'!K53 -> 4517 | L37: ='Historical Data'!L53 -> 6009 | M37: =M21/-365*M14 -> 6734.5261 | N37: =N21/-365*N14 -> 8087.4861 | O37: =O21/-365*O14 -> 9550.8777 | P37: =P21/-365*P14 -> 11107.414 | Q37: =Q21/-365*Q14 -> 12737.829
B38: Trade Recevivable | H38: ='Historical Data'!H56 -> 40562 | I38: ='Historical Data'!I56 -> 39815 | J38: ='Historical Data'!J56 -> 47277 | K38: ='Historical Data'!K56 -> 74557 | L38: ='Historical Data'!L56 -> 79776 | M38: =M20/365*M13 -> 90750.822 | N38: =N13/365*N20 -> 108982.58 | O38: =O13/365*O20 -> 128702.45 | P38: =P13/365*P20 -> 149677.49 | Q38: =Q13/365*Q20 -> 171648.08
B39: Other Current Assets | H39: =SUM('Historical Data'!H59:H61,'Historical Data'!H54:H55) -> 341024 | I39: =SUM('Historical Data'!I59:I61,'Historical Data'!I54:I55) -> 398436 | J39: =SUM('Historical Data'!J59:J61,'Historical Data'!J54:J55) -> 368446 | K39: =SUM('Historical Data'!K59:K61,'Historical Data'!K54:K55) -> 429615 | L39: =SUM('Historical Data'!L59:L61,'Historical Data'!L54:L55) -> 512601 | M39: =L39 -> 512601 | N39: =M39 -> 512601 | O39: =N39 -> 512601 | P39: =O39 -> 512601 | Q39: =P39 -> 512601
A41: Non Current Assets
B42: Plant, Property & Equipment | H42: ='Historical Data'!H35+'Historical Data'!H36 -> 948111 | I42: ='Historical Data'!I35+'Historical Data'!I36 -> 1062534 | J42: ='Historical Data'!J35+'Historical Data'!J36 -> 1155198 | K42: ='Historical Data'!K35+'Historical Data'!K36 -> 1538686 | L42: ='Historical Data'!L35+'Historical Data'!L36 -> 1696790 | M42: =M107-M43 -> 1471382.1 | N42: =N107-N43 -> 1395486.6 | O42: =O107-O43 -> 1411361.4 | P42: =P107-P43 -> 1478421.9 | Q42: =Q107-Q43 -> 1568204
B43: Intangible Assets | H43: ='Historical Data'!H39+'Historical Data'!H40 -> 891670 | I43: ='Historical Data'!I39+'Historical Data'!I40 -> 1321451 | J43: ='Historical Data'!J39+'Historical Data'!J40 -> 1222490 | K43: ='Historical Data'!K39+'Historical Data'!K40 -> 1336596 | L43: ='Historical Data'!L39+'Historical Data'!L40 -> 1255854 | M43: =L43 -> 1255854 | N43: =M43 -> 1255854 | O43: =N43 -> 1255854 | P43: =O43 -> 1255854 | Q43: =P43 -> 1255854
B44: Goodwill | H44: ='Historical Data'!H38 -> 338313 | I44: ='Historical Data'!I38 -> 337741 | J44: ='Historical Data'!J38 -> 265017 | K44: ='Historical Data'!K38 -> 516974 | L44: ='Historical Data'!L38 -> 566859 | M44: =L44 -> 566859 | N44: =M44 -> 566859 | O44: =N44 -> 566859 | P44: =O44 -> 566859 | Q44: =P44 -> 566859
B45: Financial Asset | H45: =SUM('Historical Data'!H42:H46) -> 23342 | I45: =SUM('Historical Data'!I42:I46) -> 27473 | J45: =SUM('Historical Data'!J42:J46) -> 29351 | K45: =SUM('Historical Data'!K42:K46) -> 45902 | L45: =SUM('Historical Data'!L42:L46) -> 49629 | M45: =L45 -> 49629 | N45: =M45 -> 49629 | O45: =N45 -> 49629 | P45: =O45 -> 49629 | Q45: =P45 -> 49629
B46: Other Non Current Assets | H46: =SUM('Historical Data'!H47:H49,'Historical Data'!H37,'Historical Data'!H41) -> 914845 | I46: =SUM('Historical Data'!I47:I49,'Historical Data'!I37,'Historical Data'!I41) -> 1142120 | J46: =SUM('Historical Data'!J47:J49,'Historical Data'!J37,'Historical Data'!J41) -> 1190493 | K46: =SUM('Historical Data'!K47:K49,'Historical Data'!K37,'Historical Data'!K41) -> 1029558 | L46: =SUM('Historical Data'!L47:L49,'Historical Data'!L37,'Historical Data'!L41) -> 1050230 | M46: =L46 -> 1050230 | N46: =M46 -> 1050230 | O46: =N46 -> 1050230 | P46: =O46 -> 1050230 | Q46: =P46 -> 1050230
B47: TOTAL ASSETS | H47: =SUM(H36:H39,H42:H46) -> 3636560 | I47: =SUM(I36:I39,I42:I46) -> 4466332 | J47: =SUM(J36:J39,J42:J46) -> 4445310 | K47: =SUM(K36:K39,K42:K46) -> 5143604 | L47: =SUM(L36:L39,L42:L46) -> 5521516 | M47: =SUM(M42:M46,M36:M39) -> 5597175.1 | N47: =SUM(N42:N46,N36:N39) -> 5847837.9 | O47: =SUM(O42:O46,O36:O39) -> 6296897.4 | P47: =SUM(P42:P46,P36:P39) -> 6937109.6 | Q47: =SUM(Q42:Q46,Q36:Q39) -> 7766042
A49: Current Liabilities
B50: Trade Payable | H50: ='Historical Data'!H88 -> 292741 | I50: ='Historical Data'!I88 -> 328946 | J50: ='Historical Data'!J88 -> 351325 | K50: ='Historical Data'!K88 -> 381537 | L50: ='Historical Data'!L88 -> 450152 | M50: =M21/365*-M15 -> 597776.54 | N50: =N21/365*-N15 -> 717869.29 | O50: =O21/365*-O15 -> 847764.27 | P50: =P21/365*-P15 -> 985927.08 | Q50: =Q21/365*-Q15 -> 1130647.5
B51: Other Current Liabilities | H51: =SUM('Historical Data'!H87,'Historical Data'!H89:H93) -> 576652 | I51: =SUM('Historical Data'!I87,'Historical Data'!I89:I93) -> 654470 | J51: =SUM('Historical Data'!J87,'Historical Data'!J89:J93) -> 728327 | K51: =SUM('Historical Data'!K87,'Historical Data'!K89:K93) -> 891783 | L51: =SUM('Historical Data'!L87,'Historical Data'!L89:L93) -> 986633 | M51: =L51 -> 986633 | N51: =M51 -> 986633 | O51: =N51 -> 986633 | P51: =O51 -> 986633 | Q51: =P51 -> 986633
A53: Non Current Assets
B54: Borrowing | H54: ='Historical Data'!H74+'Historical Data'!H85+'Historical Data'!H86+'Historical Data'!H75 -> 1696779 | I54: ='Historical Data'!I74+'Historical Data'!I85+'Historical Data'!I86+'Historical Data'!I75 -> 2260203 | J54: ='Historical Data'!J74+'Historical Data'!J85+'Historical Data'!J86+'Historical Data'!J75 -> 2155923 | K54: ='Historical Data'!K74+'Historical Data'!K85+'Historical Data'!K86+'Historical Data'!K75 -> 2136421 | L54: ='Historical Data'!L74+'Historical Data'!L85+'Historical Data'!L86+'Historical Data'!L75 -> 1954117 | M54: =M112 -> 1751166.3 | N54: =N112 -> 1548215.7 | O54: =O112 -> 1345265 | P54: =P112 -> 1142314.3 | Q54: =Q112 -> 939363.67
B55: Other Non Current Liabilities | H55: =SUM('Historical Data'!H76:H81) -> 151038 | I55: =SUM('Historical Data'!I76:I81) -> 158270 | J55: =SUM('Historical Data'!J76:J81) -> 154096 | K55: =SUM('Historical Data'!K76:K81) -> 199186 | L55: =SUM('Historical Data'!L76:L81) -> 170980 | M55: =L55 -> 170980 | N55: =M55 -> 170980 | O55: =N55 -> 170980 | P55: =O55 -> 170980 | Q55: =P55 -> 170980
B56: TOTAL LAIBILITIES | H56: =SUM(H54:H55,H50:H51) -> 2717210 | I56: =SUM(I54:I55,I50:I51) -> 3401889 | J56: =SUM(J54:J55,J50:J51) -> 3389671 | K56: =SUM(K54:K55,K50:K51) -> 3608927 | L56: =SUM(L54:L55,L50:L51) -> 3561882 | M56: =SUM(M54:M55,M50:M51) -> 3506555.9 | N56: =SUM(N54:N55,N50:N51) -> 3423698 | O56: =SUM(O54:O55,O50:O51) -> 3350642.3 | ... Q56: =SUM(Q54:Q55,Q50:Q51) -> 3227624.2
B58: Equity | H58: ='Historical Data'!H67 -> 27950 | I58: ='Historical Data'!I67 -> 28366 | J58: ='Historical Data'!J67 -> 28766 | K58: ='Historical Data'!K67 -> 29001 | L58: ='Historical Data'!L67 -> 30468 | M58: =L58 -> 30468 | N58: =M58 -> 30468 | O58: =N58 -> 30468 | P58: =O58 -> 30468 | Q58: =P58 -> 30468
B59: Other Equity | H59: ='Historical Data'!H68 -> 637593 | I59: ='Historical Data'!I68 -> 747263 | J59: ='Historical Data'!J68 -> 791422 | K59: ='Historical Data'!K68 -> 1107718 | L59: ='Historical Data'!L68 -> 1460098 | M59: =L59+M31+M86 -> 1591083.2 | N59: =M59+N31+N86 -> 1924604 | O59: =N59+O31+O86 -> 2446719.1 | P59: =O59+P31+P86 -> 3151719.2 | Q59: =P59+Q31+Q86 -> 4038881.8
B60: Total Shareholder Fund | H60: =SUM(H58:H59) -> 665543 | I60: =SUM(I58:I59) -> 775629 | J60: =SUM(J58:J59) -> 820188 | K60: =SUM(K58:K59) -> 1136719 | L60: =SUM(L58:L59) -> 1490566 | M60: =SUM(M58:M59) -> 1621551.2 | N60: =SUM(N58:N59) -> 1955072 | O60: =SUM(O58:O59) -> 2477187.1 | ... Q60: =SUM(Q58:Q59) -> 4069349.8
B61: Non-Controlling Interest | H61: ='Historical Data'!H70 -> 253807 | I61: ='Historical Data'!I70 -> 288814 | J61: ='Historical Data'!J70 -> 235451 | K61: ='Historical Data'!K70 -> 397958 | L61: ='Historical Data'!L70 -> 469068 | M61: =L61 -> 469068 | N61: =M61 -> 469068 | O61: =N61 -> 469068 | P61: =O61 -> 469068 | Q61: =P61 -> 469068
B62: TOTAL EQUITY & LIABILITIES | H62: =SUM(H60:H61,H56) -> 3636560 | I62: =SUM(I60:I61,I56) -> 4466332 | J62: =SUM(J60:J61,J56) -> 4445310 | K62: =SUM(K60:K61,K56) -> 5143604 | L62: =SUM(L60:L61,L56) -> 5521516 | M62: =SUM(M60:M61,M56) -> 5597175.1 | N62: =SUM(N60:N61,N56) -> 5847837.9 | O62: =SUM(O60:O61,O56) -> 6296897.4 | ... Q62: =SUM(Q60:Q61,Q56) -> 7766042
D64: CHECK | H64: =IF(H62=H47,"TALLIED","ERROR") -> TALLIED | I64: =IF(I62=I47,"TALLIED","ERROR") -> TALLIED | J64: =IF(J62=J47,"TALLIED","ERROR") -> TALLIED | K64: =IF(K62=K47,"TALLIED","ERROR") -> TALLIED | L64: =IF(L62=L47,"TALLIED","ERROR") -> TALLIED | M64: =IF(M62=M47,"TALLIED","ERROR") -> TALLIED | N64: =IF(N62=N47,"TALLIED","ERROR") -> TALLIED | O64: =IF(O62=O47,"TALLIED","ERROR") -> TALLIED | ... Q64: =IF(Q62=Q47,"TALLIED","ERROR") -> TALLIED
A66: CASH FLOW
B68: Cash Flow from Operations
C69: Profit after Tax | H69: ='Historical Data'!H100+'Historical Data'!H124 -> 103077 | I69: ='Historical Data'!I100+'Historical Data'!I124 -> 127692 | J69: ='Historical Data'!J100+'Historical Data'!J124 -> 97984 | K69: ='Historical Data'!K100+'Historical Data'!K124 -> 339605 | L69: ='Historical Data'!L100+'Historical Data'!L124 -> 388888 | M69: =M31 -> 185788.77 | N69: =N31 -> 473064.33 | O69: =O31 -> 740565.62 | P69: =P31 -> 999968.84 | Q69: =Q31 -> 1258347.3
C70: Add: Depreciation & Amortization | H70: ='Historical Data'!H102 -> 330907 | I70: ='Historical Data'!I102 -> 364318 | J70: ='Historical Data'!J102 -> 395376 | K70: ='Historical Data'!K102 -> 455703 | L70: ='Historical Data'!L102 -> 527108 | M70: =-M25 -> 969037.55 | N70: =-N25 -> 895060.23 | O70: =-O25 -> 870151.82 | P70: =-P25 -> 875361.84 | Q70: =-Q25 -> 897370.65
C71: Add/Less: Other Adjustments | H71: =SUM('Historical Data'!H103:H114) -> 130654 | I71: =SUM('Historical Data'!I103:I114) -> 192356 | J71: =SUM('Historical Data'!J103:J114) -> 271486 | K71: =SUM('Historical Data'!K103:K114) -> 104201 | L71: =SUM('Historical Data'!L103:L114) -> 234258 | M71: =-SUM(M27:M28) -> 146100.08 | N71: =-SUM(N27:N28) -> 115839.05 | O71: =-SUM(O27:O28) -> 84766.23 | P71: =-SUM(P27:P28) -> 53008.689 | Q71: =-SUM(Q27:Q28) -> 20708.062
C72: Add/Less: Working Capital Adjustments | H72: =H101 -> -14472 | I72: =I101 -> -31120 | J72: =J101 -> 24136 | K72: =K101 -> 83813 | L72: =L101 -> 72042 | M72: =M101 -> 135924.19 | N72: =N101 -> 100508.03 | O72: =O101 -> 108711.72 | ... Q72: =Q101 -> 121119.46
C73: Operating Cash Flow | H73: =SUM(H69:H72) -> 550166 | I73: =SUM(I69:I72) -> 653246 | J73: =SUM(J69:J72) -> 788982 | K73: =SUM(K69:K72) -> 983322 | L73: =SUM(L69:L72) -> 1222296 | M73: =SUM(M69:M72) -> 1436850.6 | N73: =SUM(N69:N72) -> 1584471.6 | O73: =SUM(O69:O72) -> 1804195.4 | ... Q73: =SUM(Q69:Q72) -> 2297545.5
B75: Cash Flow from Investing Activities
C76: Investment in PP&E | H76: ='Historical Data'!H128 -> -265406 | I76: ='Historical Data'!I128 -> -260566 | J76: ='Historical Data'!J128 -> -381915 | K76: ='Historical Data'!K128 -> -379077 | L76: ='Historical Data'!L128 -> -451756 | M76: =-M105 -> -743629.69 | N76: =-N105 -> -819164.66 | O76: =-O105 -> -886026.65 | P76: =-P105 -> -942422.38 | Q76: =-Q105 -> -987152.72
C77: Sale proceeds from sale of PP&E | H77: ='Historical Data'!H129 -> 13791 | I77: ='Historical Data'!I129 -> 885 | J77: ='Historical Data'!J129 -> 1228 | K77: ='Historical Data'!K129 -> 3382 | L77: ='Historical Data'!L129 -> 11680 | M77: 0 | N77: =M77 -> 0 | O77: =N77 -> 0 | P77: =O77 -> 0 | Q77: =P77 -> 0
C78: Purchase/sale of investments | H78: =SUM('Historical Data'!H130:H143) -> -171133 | I78: =SUM('Historical Data'!I130:I143) -> -148621 | J78: =SUM('Historical Data'!J130:J143) -> -128095 | K78: =SUM('Historical Data'!K130:K143) -> -232332 | L78: =SUM('Historical Data'!L130:L143) -> -151170 | M78: 0 | N78: =M78 -> 0 | O78: =N78 -> 0 | P78: =O78 -> 0 | Q78: =P78 -> 0
C79: Dividend Income | H79: ='Historical Data'!H144 -> 0 | I79: ='Historical Data'!I144 -> 13992 | J79: ='Historical Data'!J144 -> 1072 | K79: ='Historical Data'!K144 -> 1090 | L79: ='Historical Data'!L144 -> 1813 | M79: 0 | N79: =M79 -> 0 | O79: =N79 -> 0 | P79: =O79 -> 0 | Q79: =P79 -> 0
C80: Interest income | H80: ='Historical Data'!H145 -> 4052 | I80: ='Historical Data'!I145 -> 3508 | J80: ='Historical Data'!J145 -> 5671 | K80: ='Historical Data'!K145 -> 4239 | L80: ='Historical Data'!L145 -> 4088 | M80: =M28 -> 49506.211 | N80: =N28 -> 59451.962 | O80: =O28 -> 70209.508 | P80: =P28 -> 81651.773 | Q80: =Q28 -> 93637.123
C81: Cash Flow from Investing Activities | H81: =SUM(H76:H80) -> -418696 | I81: =SUM(I76:I80) -> -390802 | J81: =SUM(J76:J80) -> -502039 | K81: =SUM(K76:K80) -> -602698 | L81: =SUM(L76:L80) -> -585345 | M81: =SUM(M76:M80) -> -694123.48 | N81: =SUM(N76:N80) -> -759712.7 | O81: =SUM(O76:O80) -> -815817.15 | ... Q81: =SUM(Q76:Q80) -> -893515.6
B83: Cash Flow from Financing Activities
C84: Issuance/repayment of debt | H84: =SUM('Historical Data'!H150:H154,'Historical Data'!H156,'Historical Data'!H158:H165) -> -58232 | I84: =SUM('Historical Data'!I150:I154,'Historical Data'!I156,'Historical Data'!I158:I165) -> -194146 | J84: =SUM('Historical Data'!J150:J154,'Historical Data'!J156,'Historical Data'!J158:J165) -> -95677 | K84: =SUM('Historical Data'!K150:K154,'Historical Data'!K156,'Historical Data'!K158:K165) -> -120507 | L84: =SUM('Historical Data'!L150:L154,'Historical Data'!L156,'Historical Data'!L158:L165) -> -417722 | M84: =M111 -> -202950.67 | N84: =N111 -> -202950.67 | O84: =O111 -> -202950.67 | P84: =P111 -> -202950.67 | Q84: =Q111 -> -202950.67
C85: Proceeds from issue of preferance shares | H85: ='Historical Data'!H149 -> 52226 | I85: ='Historical Data'!I149 -> 52242 | J85: ='Historical Data'!J149 -> 0 | K85: ='Historical Data'!K149 -> 0 | L85: ='Historical Data'!L149 -> 156949
C86: Dividend paid | H86: ='Historical Data'!H157 -> -14438 | I86: ='Historical Data'!I157 -> -35898 | J86: ='Historical Data'!J157 -> -41845 | K86: ='Historical Data'!K157 -> -69349 | L86: ='Historical Data'!L157 -> -113277 | M86: =M31*-M12 -> -54803.584 | N86: =N31*-N12 -> -139543.53 | O86: =O31*-O12 -> -218450.51 | P86: =P31*-P12 -> -294968.73 | Q86: =Q31*-Q12 -> -371184.67
C87: Interest paid | H87: ='Historical Data'!H155 -> -131588 | I87: ='Historical Data'!I155 -> -66893 | J87: ='Historical Data'!J155 -> -140263 | K87: ='Historical Data'!K155 -> -175476 | L87: ='Historical Data'!L155 -> -148876 | M87: =M113 -> -195606.29 | N87: =N113 -> -175291.01 | O87: =O113 -> -154975.74 | P87: =P113 -> -134660.46 | Q87: =Q113 -> -114345.19
C88: Cash Flow from Financing Activities | H88: =SUM(H84:H87) -> -152032 | I88: =SUM(I84:I87) -> -244695 | J88: =SUM(J84:J87) -> -277785 | K88: =SUM(K84:K87) -> -365332 | L88: =SUM(L84:L87) -> -522926 | M88: =SUM(M84:M87) -> -453360.54 | N88: =SUM(N84:N87) -> -517785.21 | O88: =SUM(O84:O87) -> -576376.91 | ... Q88: =SUM(Q84:Q87) -> -688480.52
B90: Net decrease in Cash and Cash Equivalents | H90: =SUM(H88,H81,H73) -> -20562 | I90: =SUM(I88,I81,I73) -> 17749 | J90: =SUM(J88,J81,J73) -> 9158 | K90: =SUM(K88,K81,K73) -> 15292 | L90: =SUM(L88,L81,L73) -> 114025 | M90: =SUM(M88,M81,M73) -> 289366.56 | N90: =SUM(N88,N81,N73) -> 306973.73 | O90: =SUM(O88,O81,O73) -> 412001.34 | ... Q90: =SUM(Q88,Q81,Q73) -> 715549.34
C91: Opening Cash Balance | H91: ='Historical Data'!H170+'Historical Data'!H169 -> 94549 | I91: ='Historical Data'!I170+'Historical Data'!I169 -> 72465 | J91: ='Historical Data'!J170+'Historical Data'!J169 -> 81363 | K91: ='Historical Data'!K170+'Historical Data'!K169 -> 91239 | L91: ='Historical Data'!L170+'Historical Data'!L169 -> 129822 | M91: =L36 -> 303768 | N91: =M36 -> 593134.56 | O91: =N36 -> 900108.29 | P91: =O36 -> 1312109.6 | Q91: =P36 -> 1862729.8
C92: Closing Cash Balance | H92: =SUM(H90:H91)+'Historical Data'!H57 -> 134946 | I92: =SUM(I90:I91)+'Historical Data'!I57 -> 162008 | J92: =SUM(J90:J91)+'Historical Data'!J57 -> 159676 | K92: =SUM(K90:K91)+'Historical Data'!K57 -> 167587 | L92: =SUM(L90:L91)+'Historical Data'!L57 -> 381069 | M92: =SUM(M90:M91) -> 593134.56 | N92: =SUM(N90:N91) -> 900108.29 | O92: =SUM(O90:O91) -> 1312109.6 | P92: =SUM(P90:P91) -> 1862729.8 | Q92: =SUM(Q90:Q91) -> 2578279.1
A94: Supporting Schedule
B96: Working capital
C97: Trade Payable | H97: ='Historical Data'!H118 -> -4877 | I97: ='Historical Data'!I118 -> 12671 | J97: ='Historical Data'!J118 -> 6398 | K97: ='Historical Data'!K118 -> 8586 | L97: ='Historical Data'!L118 -> 24977 | M97: =M50-L50 -> 147624.54 | N97: =N50-M50 -> 120092.75 | O97: =O50-N50 -> 129894.98 | P97: =P50-O50 -> 138162.81 | Q97: =Q50-P50 -> 144720.46
C98: Trade Receivable | H98: ='Historical Data'!H117 -> -7131 | I98: ='Historical Data'!I117 -> -5583 | J98: ='Historical Data'!J117 -> -14941 | K98: ='Historical Data'!K117 -> 29658 | L98: ='Historical Data'!L117 -> -5654 | M98: =L38-M38 -> -10974.822 | N98: =M38-N38 -> -18231.756 | O98: =N38-O38 -> -19719.871 | P98: =O38-P38 -> -20975.044 | Q98: =P38-Q38 -> -21970.586
C99: Invenrories | H99: ='Historical Data'!H119 -> -1181 | I99: ='Historical Data'!I119 -> -1157 | J99: ='Historical Data'!J119 -> -771 | K99: ='Historical Data'!K119 -> -1416 | L99: ='Historical Data'!L119 -> -1982 | M99: =L37-M37 -> -725.52611 | N99: =M37-N37 -> -1352.96 | O99: =N37-O37 -> -1463.3916 | P99: =O37-P37 -> -1556.5366 | Q99: =P37-Q37 -> -1630.4148
C100: Other adjustment | H100: =SUM('Historical Data'!H120:H122) -> -1283 | I100: =SUM('Historical Data'!I120:I122) -> -37051 | J100: =SUM('Historical Data'!J120:J122) -> 33450 | K100: =SUM('Historical Data'!K120:K122) -> 46985 | L100: =SUM('Historical Data'!L120:L122) -> 54701 | M100: 0 | N100: =M100 -> 0 | O100: =N100 -> 0 | P100: =O100 -> 0 | Q100: =P100 -> 0
C101: TOTAL | H101: =SUM(H97:H100) -> -14472 | I101: =SUM(I97:I100) -> -31120 | J101: =SUM(J97:J100) -> 24136 | K101: =SUM(K97:K100) -> 83813 | L101: =SUM(L97:L100) -> 72042 | M101: =SUM(M97:M100) -> 135924.19 | N101: =SUM(N97:N100) -> 100508.03 | O101: =SUM(O97:O100) -> 108711.72 | ... Q101: =SUM(Q97:Q100) -> 121119.46
B103: Depreciation & Amortization
C104: Opening Balance | I104: =H107 -> 1839781 | J104: =I107 -> 2383985 | K104: =J107 -> 2377688 | L104: =K107 -> 2875282 | M104: =L107 -> 2952644 | N104: =M107 -> 2727236.1 | O104: =N107 -> 2651340.6 | P104: =O107 -> 2667215.4 | Q104: =P107 -> 2734275.9
C105: Add/Less: Purchase's & Sale | I105: =I107-I104-I106 -> 908522 | J105: =J107-J104-J106 -> 389079 | K105: =K107-K104-K106 -> 953297 | L105: =L107-L104-L106 -> 604470 | M105: =(M20-L20)/M16 -> 743629.69 | N105: =(N20-M20)/N16 -> 819164.66 | O105: =(O20-N20)/O16 -> 886026.65 | P105: =(P20-O20)/P16 -> 942422.38 | Q105: =(Q20-P20)/Q16 -> 987152.72
C106: Less: Depreciation & Amortization | H106: =H25 -> -330907 | I106: =I25 -> -364318 | J106: =J25 -> -395376 | K106: =K25 -> -455703 | L106: =L25 -> -527108 | M106: =M104*-M8 -> -969037.55 | N106: =N104*-N8 -> -895060.23 | O106: =O104*-O8 -> -870151.82 | P106: =P104*-P8 -> -875361.84 | Q106: =Q104*-Q8 -> -897370.65
C107: Closing Balance | H107: =H42+H43 -> 1839781 | I107: =I42+I43 -> 2383985 | J107: =J42+J43 -> 2377688 | K107: =K42+K43 -> 2875282 | L107: =L42+L43 -> 2952644 | M107: =SUM(M104:M106) -> 2727236.1 | N107: =SUM(N104:N106) -> 2651340.6 | O107: =SUM(O104:O106) -> 2667215.4 | P107: =SUM(P104:P106) -> 2734275.9 | Q107: =SUM(Q104:Q106) -> 2824058
B109: Debt Schedule
C110: Opeing Balance | I110: =H112 -> 1696779 | J110: =I112 -> 2260203 | K110: =J112 -> 2155923 | L110: =K112 -> 2136421 | M110: =L112 -> 1954117 | N110: =M112 -> 1751166.3 | O110: =N112 -> 1548215.7 | P110: =O112 -> 1345265 | Q110: =P112 -> 1142314.3
C111: Less: Issuance/repayment | I111: =I112-I110 -> 563424 | J111: =J112-J110 -> -104280 | K111: =K112-K110 -> -19502 | L111: =L112-L110 -> -182304 | M111: =-AVERAGE('Re-Payment'!H14:M14) -> -202950.67 | N111: =M111 -> -202950.67 | O111: =N111 -> -202950.67 | P111: =O111 -> -202950.67 | Q111: =P111 -> -202950.67
C112: Closing Balance | H112: =H54 -> 1696779 | I112: =I54 -> 2260203 | J112: =J54 -> 2155923 | K112: =K54 -> 2136421 | L112: =L54 -> 1954117 | M112: =SUM(M110:M111) -> 1751166.3 | N112: =SUM(N110:N111) -> 1548215.7 | O112: =SUM(O110:O111) -> 1345265 | P112: =SUM(P110:P111) -> 1142314.3 | Q112: =SUM(Q110:Q111) -> 939363.67
C113: Interest | H113: =H27 -> -166162 | I113: =I27 -> -192999 | J113: =J27 -> -226477 | K113: =K27 -> -217539 | L113: =L27 -> -215553 | M113: =M110*-M9 -> -195606.29 | N113: =N110*-N9 -> -175291.01 | O113: =O110*-O9 -> -154975.74 | P113: =P110*-P9 -> -134660.46 | Q113: =Q110*-Q9 -> -114345.19
A115: DCF Valuation
B117: Assumption's
B118: Transaction Date | F118: =DATE(2026,9,26) -> 46291
B119: Fiscal Year End Date | F119: =DATE(2027,3,31) -> 46477
B120: Tax Rate | F120: =M10 -> 0.23857816
...

Sheet Re-Payment
A1: Bharti Airtel Limited
A2: Loan Repayment & Lease Liabilities
D4: Instrument | H4: 2026 | I4: 2027 | J4: 2028* | K4: 2029 | L4: 2030 | M4: 2031+ | N4: Total
D5: Term loans — One time | H5: 55231 | I5: 25347 | J5: 1344.6667 | K5: 1344.6667 | L5: 1344.6667 | M5: 0 | N5: =SUM(H5:M5) -> 84612
D6: Term loans — Monthly | H6: 6714 | I6: 7075 | J6: 2204.3333 | K6: 2204.3333 | L6: 2204.3333 | M6: 658 | N6: =SUM(H6:M6) -> 21060
D7: Term loans — Quarterly | H7: 18592 | I7: 8536 | J7: 3673 | K7: 3673 | L7: 3673 | M7: 1078 | N7: =SUM(H7:M7) -> 39225
D8: Term loans — Half yearly | H8: 27665 | I8: 13328 | J8: 11480.667 | K8: 11480.667 | L8: 11480.667 | M8: 7293 | N8: =SUM(H8:M8) -> 82728
D9: Term loans — Annually | H9: 3278 | I9: 3278 | J9: 0 | K9: 0 | L9: 0 | M9: 0 | N9: =SUM(H9:M9) -> 6556
D10: Non-convertible bonds | H10: 0 | I10: 0 | J10: 0 | K10: 0 | L10: 0 | M10: 70955 | N10: =SUM(H10:M10) -> 70955
D11: Deferred payment liability — Spectrum | H11: 20727 | I11: 22237 | J11: 25636.667 | K11: 25636.667 | L11: 25636.667 | M11: 423395 | N11: =SUM(H11:M11) -> 543269
D12: Deferred payment liability — Adjusted Gross Revenue (AGR) | H12: 58614 | I12: 63303 | J12: 73982 | K12: 73982 | L12: 73982 | M12: 0 | N12: =SUM(H12:M12) -> 343863
D13: Bank overdraft | H13: 25436 | I13: 0 | J13: 0 | K13: 0 | L13: 0 | M13: 0 | N13: =SUM(H13:M13) -> 25436
D14: Total borrowings repayment | H14: =SUM(H5:H13) -> 216257 | I14: =SUM(I5:I13) -> 143104 | J14: =SUM(J5:J13) -> 118321.33 | K14: =SUM(K5:K13) -> 118321.33 | L14: =SUM(L5:L13) -> 118321.33 | M14: =SUM(M5:M13) -> 503379 | N14: =SUM(H14:M14) -> 1217704

Sheet Scenario
A1: Bharti Airtel Limited
A2: LIVE SCEANRIO
D5: Scenarios | E5: Growth % | H5: =Model!M2 -> 2027 | I5: =Model!N2 -> 2028 | J5: =Model!O2 -> 2029 | K5: =Model!P2 -> 2030 | L5: =Model!Q2 -> 2031
D6: Base Case | E6: =AVERAGE(Model!I5:L5) -> 0.16118821 | H6: =E6 -> 0.16118821 | I6: =H6*(1-$E$8) -> 0.14517851 | J6: =I6*(1-$E$8) -> 0.13075894 | K6: =J6*(1-$E$8) -> 0.11777157 | L6: =K6*(1-$E$8) -> 0.10607414
D7: Bull Case | E7: =+ABS(E6+STDEV(Model!I5:L5)) -> 0.2230534 | H7: =E7 -> 0.2230534 | I7: =H7*(1-$E$8) -> 0.20089907 | J7: =I7*(1-$E$8) -> 0.18094517 | K7: =J7*(1-$E$8) -> 0.16297315 | L7: =K7*(1-$E$8) -> 0.14678617
D8: Bear Case | E8: =+ABS(E6-STDEV(Model!I5:L5)) -> 0.099323008 | H8: =E8 -> 0.099323008 | I8: =H8*(1-$E$8) -> 0.089457948 | J8: =I8*(1-$E$8) -> 0.080572716 | K8: =J8*(1-$E$8) -> 0.072569991 | L8: =K8*(1-$E$8) -> 0.065362121
D9: Annual growth tapering | E9: =10% -> 0.1

Sheet Market Data
A1: Bharti Airtel Limited
A2: Market Data
E4: Index
D5: Date | E5: Close Price
D6: 46230 | E6: 23995.95 | H6: Period (yrs) | J6: 9
D7: 46227 | E7: 23767.45
D8: 46226 | E8: 23869.6 | H8: Returns | J8: =_xlfn.RRI(J6,E2622,E6) -> 0.13038872
D9: 46225 | E9: 23996.25
D10: 46224 | E10: 24187.7
D11: 46223 | E11: 24238.5
D12: 46220 | E12: 24334.3
D13: 46219 | E13: 24072.75
D14: 46218 | E14: 24078.5
D15: 46217 | E15: 24052.05
D16: 46216 | E16: 24211
D17: 46213 | E17: 24206.9
D18: 46212 | E18: 23962.8
D19: 46211 | E19: 23882.05
D20: 46210 | E20: 24398.7
... D2622: 42370 | E2622: 7963.2

Sheet WACC
A1: Bharti Airtel Limited
A2: Weighted-Average Cost of Capital (WACC)
A3: (All Amounts Denominated in INR Crore Unless Otherwise Stated)
A5: Comparable Companies Beta
H7: Equity | I7: Total | J7: Debt/ | K7: Debt/ | L7: Tax | M7: Levered | N7: Unlevered
D8: Company Name | H8: Value | I8: Debt | J8: Equity | K8: Capital | L8: Rate % | M8: Beta | N8: Beta
D9: Vodafone Idea Limited | H9: =Comp!K8 -> 1615403.3 | I9: =Comp!L8 -> 1925280 | J9: =I9/H9 -> 1.1918262 | K9: =I9/(H9+I9) -> 0.54375945 | L9: =Model!M10 -> 0.23857816 | M9: 1.75 | N9: =M9/(1+J9*(1-K9)) -> 1.1335963
D10: Bharti Hexacom Limited | H10: =Comp!K9 -> 825000 | I10: =Comp!L9 -> 26943 | J10: =I10/H10 -> 0.032658182 | K10: =I10/(H10+I10) -> 0.031625355 | L10: =L9 -> 0.23857816 | M10: 0.55 | N10: =M10/(1+J10*(1-K10)) -> 0.53313928
D11: Tata Communications Limited | H11: =Comp!K10 -> 513000 | I11: =Comp!L10 -> 122624 | J11: =I11/H11 -> 0.23903314 | K11: =I11/(H11+I11) -> 0.19291908 | L11: =L10 -> 0.23857816 | M11: 0.85 | N11: =M11/(1+J11*(1-K11)) -> 0.71253785
D12: Railtel Corporation of India Limited | H12: =Comp!K11 -> 96282 | I12: =Comp!L11 -> 637.2 | J12: =I12/H12 -> 0.0066180595 | K12: =I12/(H12+I12) -> 0.0065745487 | L12: =L11 -> 0.23857816 | M12: 0.7 | N12: =M12/(1+J12*(1-K12)) -> 0.69542788
D13: Average | J13: =AVERAGE(J9:J12) -> 0.36753389 | K13: =AVERAGE(K9:K12) -> 0.19371961 | L13: =AVERAGE(L9:L12) -> 0.23857816 | M13: =AVERAGE(M9:M12) -> 0.9625 | N13: =AVERAGE(N9:N12) -> 0.76867533
D14: Median | J14: =MEDIAN(J9:J12) -> 0.13584566 | K14: =MEDIAN(K9:K12) -> 0.11227222 | L14: =MEDIAN(L9:L12) -> 0.23857816 | M14: =MEDIAN(M9:M12) -> 0.775 | N14: =MEDIAN(N9:N12) -> 0.70398286
D16: Bharti Airtel Limited | H16: =Comp!K16 -> 11273160 | I16: =Comp!L16 -> 1954117
D18: WACC Calculation
C20: Target Capital Structure
D21: Proportion of Debt | I21: =Comp!L16/(Comp!K16+Comp!L16) -> 0.14773388
D22: Proportion of Equity | I22: =1-I21 -> 0.85226612
C25: Current Capital Structure
D26: Market Cap | I26: =H16 -> 11273160
D27: Total Debt | I27: =I16 -> 1954117
D28: Debt / Equity | I28: =I27/I26 -> 0.17334243
C30: Cost of Debt
D31: Pre-Tax Cost of Debt | I31: =Model!M9 -> 0.10009958
D32: Tax Rate | I32: =Model!M10 -> 0.23857816
D33: After-Tax Cost of Debt | I33: =I31*(1-I32) -> 0.076218006
C35: Cost of Equity
D36: Risk Free Rate | I36: 0.065
D37: Equity Market Return | I37: ='Market Data'!J8 -> 0.13038872
D38: Equity Risk Premium | I38: =I37-I36 -> 0.065388717
D39: Levered Equity Beta | I39: =N14*(1+I28)*(1-I32) -> 0.62894431
D40: Cost of Equity | I40: =I36+I39*I38 -> 0.10612586
D42: WACC | I42: =(I21*I33)+(I40*I22) -> 0.10170746

Sheet Comp Data
A1: Bharti Airtel Limited | H1: \
A2: Comp Data
D4: Company | H4: Ticker | I4: Price | J4: Shares | K4: Debt | L4: Cash | M4: Sales | N4: EBITDA | O4: Net Income
D5: Bharti Airtel Limited | H5: BHARTIARTL | I5: 1850 | J5: 6093.6 | K5: 1954117 | L5: 303768 | M5: 2109728 | N5: 1196745 | O5: 338228
D7: Vodafone Idea Limited | H7: IDEA | I7: 14.92 | J7: 108271 | K7: 1925280 | L7: 57310 | M7: 455390 | N7: 194251 | O7: 374058
D8: Bharti Hexacom Limited | H8: BHARTIHEXA | I8: 1650 | J8: 500 | K8: 26943 | L8: 330 | M8: 96010 | N8: 50519 | O8: 18240
D9: Tata Communications Limited | H9: TATACOMM | I9: 1800 | J9: 285 | K9: 122624 | L9: 9905 | M9: 254260 | N9: 49158 | O9: 9058
D10: Railtel Corporation of India Limited | H10: RAILTEL | I10: 300 | J10: 320.94 | K10: 637.2 | L10: 6541.1 | M10: 44270 | N10: 6521.8 | O10: 3460
D12: Source: www.screener.in

Sheet Comp
A1: Bharti Airtel Limited
A2: Comp Valuation
I5: Market Data | P5: Financial Data | T5: Valuation
I6: Price | J6: Shares | K6: Market Cap | L6: Debt | M6: Cash | N6: EV | P6: Sales | Q6: EBITDA | R6: Earnings | T6: EV/Sales | U6: EV/EBITDA | V6: P/E
D7: Company Name | F7: Ticker | I7: (₹/share) | J7: ₹ In CR | K7: ₹ In CR | M7: & Equivalents | N7: ₹ In CR | P7: ₹ In CR | Q7: ₹ In CR | R7: ₹ In CR | T7: x | U7: x | V7: x
D8: Vodafone Idea Limited | F8: IDEA | I8: ='Comp Data'!I7 -> 14.92 | J8: ='Comp Data'!J7 -> 108271 | K8: =I8*J8 -> 1615403.3 | L8: ='Comp Data'!K7 -> 1925280 | M8: ='Comp Data'!L7 -> 57310 | N8: =K8+L8-M8 -> 3483373.3 | P8: ='Comp Data'!M7 -> 455390 | Q8: ='Comp Data'!N7 -> 194251 | R8: ='Comp Data'!O7 -> 374058 | T8: =N8/P8 -> 7.6492091 | U8: =N8/Q8 -> 17.932331 | V8: =K8/R8 -> 4.3185905
D9: Bharti Hexacom Limited | F9: BHARTIHEXA | I9: ='Comp Data'!I8 -> 1650 | J9: ='Comp Data'!J8 -> 500 | K9: =I9*J9 -> 825000 | L9: ='Comp Data'!K8 -> 26943 | M9: ='Comp Data'!L8 -> 330 | N9: =K9+L9-M9 -> 851613 | P9: ='Comp Data'!M8 -> 96010 | Q9: ='Comp Data'!N8 -> 50519 | R9: ='Comp Data'!O8 -> 18240 | T9: =N9/P9 -> 8.8700448 | U9: =N9/Q9 -> 16.857281 | V9: =K9/R9 -> 45.230263
D10: Tata Communications Limited | F10: TATACOMM | I10: ='Comp Data'!I9 -> 1800 | J10: ='Comp Data'!J9 -> 285 | K10: =I10*J10 -> 513000 | L10: ='Comp Data'!K9 -> 122624 | M10: ='Comp Data'!L9 -> 9905 | N10: =K10+L10-M10 -> 625719 | P10: ='Comp Data'!M9 -> 254260 | Q10: ='Comp Data'!N9 -> 49158 | R10: ='Comp Data'!O9 -> 9058 | T10: =N10/P10 -> 2.4609416 | U10: =N10/Q10 -> 12.728732 | V10: =K10/R10 -> 56.635019
D11: Railtel Corporation of India Limited | F11: RAILTEL | I11: ='Comp Data'!I10 -> 300 | J11: ='Comp Data'!J10 -> 320.94 | K11: =I11*J11 -> 96282 | L11: ='Comp Data'!K10 -> 637.2 | M11: ='Comp Data'!L10 -> 6541.1 | N11: =K11+L11-M11 -> 90378.1 | P11: ='Comp Data'!M10 -> 44270 | Q11: ='Comp Data'!N10 -> 6521.8 | R11: ='Comp Data'!O10 -> 3460 | T11: =N11/P11 -> 2.0415202 | U11: =N11/Q11 -> 13.857846 | V11: =K11/R11 -> 27.827168
D13: Average | T13: =AVERAGE(T8:T11) -> 5.2554289 | U13: =AVERAGE(U8:U11) -> 15.344048 | V13: =AVERAGE(V8:V11) -> 33.50276
D14: Median | T14: =MEDIAN(T8:T11) -> 5.0550753 | U14: =MEDIAN(U8:U11) -> 15.357564 | V14: =MEDIAN(V8:V11) -> 36.528715
D16: Bharti Airtel Limited | I16: ='Comp Data'!I5 -> 1850 | J16: ='Comp Data'!J5 -> 6093.6 | K16: =I16*J16 -> 11273160 | L16: ='Comp Data'!K5 -> 1954117 | M16: ='Comp Data'!L5 -> 303768 | N16: =K16+L16-M16 -> 12923509 | P16: ='Comp Data'!M5 -> 2109728 | Q16: ='Comp Data'!N5 -> 1196745 | R16: ='Comp Data'!O5 -> 338228
D18: Metric | F18: Comps | I18: EV | J18: Net Debt | K18: Equity Value | L18: Shares | M18: Share Price
D19: =T6 -> EV/Sales | F19: =T14 -> 5.0550753 | I19: =F19*P16 -> 10664834 | J19: =L16-M16 -> 1650349 | K19: =I19-J19 -> 9014484.9 | L19: =J16 -> 6093.6 | M19: =K19/L19 -> 1479.3365
D20: =U6 -> EV/EBITDA | F20: =U14 -> 15.357564 | I20: =F20*Q16 -> 18379088 | J20: =J19 -> 1650349 | K20: =I20-J20 -> 16728739 | L20: =L19 -> 6093.6 | M20: =K20/L20 -> 2745.2965
D21: =V6 -> P/E | F21: =V14 -> 36.528715 | I21: =F21*R16 -> 12355034 | J21: =J20 -> 1650349 | K21: =I21-J21 -> 10704685 | L21: =L20 -> 6093.6 | M21: =K21/L21 -> 1756.7096

Sheet Football Field
A1: Bharti Airtel Limited
A2: FootBall Field Chart
E4: Comps | F4: DCF | G4: 52-week high/low | H4: Market Consensus
D5: High | E5: =E6 -> 2745.2965 | F5: =F6 -> 3225.7273 | G5: =G6 -> 2175 | H5: =H6 -> 2410
D6: High | E6: =Comp!M20 -> 2745.2965 | F6: 3225.7273 | G6: 2175 | H6: 2410 | I6: (ICICI Securities)
D7: Low | E7: =Comp!M19 -> 1479.3365 | F7: 2817.9719 | G7: 1740 | H7: 2180 | I7: (Prabhudas Lilladher)
D8: Low | E8: =E7 -> 1479.3365 | F8: =F7 -> 2817.9719 | G8: =G7 -> 1740 | H8: =H7 -> 2180
A10: FootBall Field Chart
