Workbook

Sheet Historical Data
A1: Alkem Laboratories Limited
A2: Historical Financial Data | L2: (Rs. In Million)
B4: Income | H4: 2021 | I4: =H4+1 -> 2022 | J4: =I4+1 -> 2023 | K4: =J4+1 -> 2024 | L4: =K4+1 -> 2025
C5: Revenue from operations | H5: 88650.1 | I5: 106341.9 | J5: 115992.6 | K5: 126675.8 | L5: 129645.2
C6: Other income | H6: 2332.1 | I6: 1626.5 | J6: 2160.8 | K6: 3108.4 | L6: 4937.4
C7: Total income | H7: 90982.2 | I7: 107968.4 | J7: 118153.4 | K7: 129784.2 | L7: 134582.6
B8: Expenses
C9: Cost of materials consumed | H9: 23945.4 | I9: 32260.6 | J9: 30569.2 | K9: 32945.9 | L9: 34403.7
C10: Purchases of stock-in-trade | H10: 14377.6 | I10: 14897.1 | J10: 13875.5 | K10: 16288.7 | L10: 15140.2
C11: Changes in inventories of finished goods, work-in-progress and stock-in-trade | H11: -3338.4 | I11: -5354.8 | J11: 4623.7 | K11: 141.2 | L11: -1901.3
C12: Employee benefits expense | H12: 16210.3 | I12: 19627.1 | J12: 21313.5 | K12: 22010.1 | L12: 24539.2
C13: Finance costs | H13: 589.2 | I13: 523.7 | J13: 1073.6 | K13: 1124.1 | L13: 1217
C14: Depreciation and amortisation expenses | H14: 2745.8 | I14: 3039.6 | J14: 3104.2 | K14: 2993 | L14: 3571.6
C15: Other expenses | H15: 18031.3 | I15: 24382.7 | J15: 29516.2 | K15: 32835 | L15: 32341.9
C16: Total expenses | H16: 72561.2 | I16: 89376 | J16: 104075.9 | K16: 108338 | L16: 109312.3
C17: Profit before exceptional items and tax (1) - (2) | H17: 18421 | I17: 18592.4 | J17: 14077.5 | K17: 21446.2 | L17: 25270.3
C18: Exceptional items | H18: 0 | I18: -149.6 | J18: -1029.8 | K18: -1214.9
C19: Profit before tax (3) + (4) | H19: 18421 | I19: 18442.8 | J19: 13047.7 | K19: 20231.3 | L19: 25270.3
C20: Current tax | H20: 3965.3 | I20: 3619.8 | J20: 2739 | K20: 4222.8 | L20: 5236
C21: Deferred tax credit (net) | H21: -1722 | I21: -1980.2 | J21: 240.6 | K21: -2106.1 | L21: -2125.7
C22: Total tax expenses (a + b) | H22: 2243.3 | I22: 1639.6 | J22: 2979.6 | K22: 2116.7 | L22: 3110.3
C23: Share in loss after tax of associate | L23: -6.2
C24: Profit for the year (5) - (6) + (7) | H24: 16177.7 | I24: 16803.2 | J24: 10068.1 | K24: 18114.6 | L24: 22153.8
C26: Balance Sheet
C28: ASSETS
C29: Non-current assets
C30: Property, plant and equipment | H30: 22339.3 | I30: 22871 | J30: 20654 | K30: 21614.6 | L30: 20639.3
C31: Right of use assets | J31: 1378.5 | K31: 2471.7 | L31: 3222.2
C32: Capital work in progress | H32: 3932.8 | I32: 3394.8 | J32: 3102.7 | K32: 1484 | L32: 4765.5
C33: Goodwill | H33: 3953.9 | I33: 4030.9 | J33: 4131.7 | K33: 4167.4 | L33: 4231.1
C34: Other intangible assets | H34: 1636.6 | I34: 2115.4 | J34: 664.1 | K34: 474.1 | L34: 430.5
C35: Intangible assets under development | J35: 129.7 | K35: 101.7 | L35: 715.2
C36: Financial assets
C37: Investment in associate | H37: 1539.5 | I37: 2316.7 | J37: 3046.1 | K37: - | L37: 323.8
C38: Other investments | H38: 80.2 | I38: 80.2 | J38: 80.2 | K38: 3348 | L38: 9108.6
C39: Other financial assets | H39: 607.9 | I39: 7106.7 | J39: 2952.5 | K39: 1202.2 | L39: 4753.6
C40: Other non-current assets | H40: 11079.1 | I40: 13092.6 | J40: 13025 | K40: 15148.3 | L40: 17382.5
C41: Deferred tax assets (net) | H41: 171.1 | I41: 533.1 | J41: 575.4 | K41: 781.7 | L41: 647.1
C42: Current tax assets (net) | H42: 564 | I42: 796.2 | J42: 529.6 | K42: 839.5 | L42: 1233.4
C43: Total non-current assets | H43: 45904.4 | I43: 56337.6 | J43: 50269.5 | K43: 51633.2 | L43: 67452.8
C45: Current assets
C46: Inventories | H46: 23124.4 | I46: 30055.3 | J46: 26075.3 | K46: 26611.8 | L46: 29224.1
C47: Financial assets
C48: Investments | H48: 1788.3 | I48: 1393.1 | J48: 3172.1 | K48: 1489.9 | L48: 9022.6
C49: Trade receivables | H49: 16072.1 | I49: 18846 | J49: 21321.8 | K49: 22528.1 | L49: 24662.5
C50: Cash and cash equivalents | H50: 1742.2 | I50: 2321.8 | J50: 2738 | K50: 4550.7 | L50: 3041.4
C51: Bank balances other than (iii) above | H51: 18162.3 | I51: 23464 | J51: 23430.9 | K51: 11242.8 | L51: 12589.4
C52: Loans | H52: 187.3 | I52: 202.5 | J52: 67.7 | K52: 90.7 | L52: 90.4
C53: Other financial assets | H53: 2606 | I53: 1731.5 | J53: 1897.5 | K53: 29302 | L53: 21154.8
C54: Other current assets | H54: 5550.1 | I54: 6322.8 | J54: 7360.9 | K54: 8299.8 | L54: 8326.7
C55: Total current assets | H55: 69232.7 | I55: 84337 | J55: 86064.2 | K55: 104115.8 | L55: 108111.9
C56: Assets held for sale | H56: 55.5 | I56: 17.3 | J56: 1232.6 | L56: 1346.3
C57: TOTAL ASSETS | H57: 115192.6 | I57: 140691.9 | J57: 137566.3 | K57: 155749 | L57: 176911
C59: EQUITY AND LIABILITIES
C60: Equity
C61: Equity share capital | H61: 239.1 | I61: 239.1 | J61: 239.1 | K61: 239.1 | L61: 239.1
C62: Other equity | H62: 73528.2 | I62: 86139.9 | J62: 90213.8 | K62: 102881.5 | L62: 119609.6
C63: Equity attributable to owners of the Company | H63: 73767.3 | I63: 86379 | J63: 90452.9 | K63: 103120.6 | L63: 119848.7
C64: Non-controlling interests | H64: 1812.8 | I64: 2094.3 | J64: 3897.1 | K64: 4023.4 | L64: 4487.6
C65: Total Equity | H65: 75580.1 | I65: 88473.3 | J65: 94350 | K65: 107144 | L65: 124336.3
C67: Liabilities
C68: Non-current liabilities
C69: Financial liabilities
C70: Borrowings | H70: 279.3 | I70: 93.8 | J70: 0 | K70: 400 | L70: 3109.1
C71: Lease liabilities | H71: 697.1 | I71: 664.7 | J71: 703.3 | K71: 1892.6 | L71: 2674.2
C72: Other financial liabilities | J72: 1660.1 | K72: 3109.9 | L72: 3539.9
C73: Provisions | H73: 2507.3 | I73: 3327.5 | J73: 3693.6 | K73: 2998.6 | L73: 3382.2
C74: Other non-current liabilities | H74: 88.3 | I74: 79.2 | J74: 88 | K74: 258.4 | L74: 219.5
C75: Total non-current liabilities | H75: 3572 | I75: 4165.2 | J75: 6145 | K75: 8659.5 | L75: 12924.9
C77: Current liabilities
C78: Financial liabilities
C79: Borrowings | H79: 16727.9 | I79: 25707.4 | J79: 13071.5 | K79: 11739.7 | L79: 7518.8
C80: Lease liabilities | H80: 215.5 | I80: 216 | J80: 192 | K80: 151.8 | L80: 506.9
C81: Trade payables
C82: Total outstanding dues of micro enterprises and small enterprises | H82: 1189.6 | I82: 924.2 | J82: 1104.6 | K82: 670 | L82: 879.8
C83: Total outstanding dues of creditors other than micro and small enterprises | H83: 9504.5 | I83: 10809.6 | J83: 10545.5 | K83: 16811.2 | L83: 17513.7
C84: Other financial liabilities | H84: 4653.9 | I84: 5993.8 | J84: 6326.9 | K84: 6457.7 | L84: 7908.6
C85: Other current liabilities | H85: 1193.4 | I85: 1503.2 | J85: 1868.9 | K85: 2296.5 | L85: 3057
C86: Provisions | H86: 2366.4 | I86: 2736 | J86: 3727.5 | K86: 1268.7 | L86: 1591.1
C87: Current tax liabilities | H87: 189.3 | I87: 163.2 | J87: 234.4 | K87: 549.9 | L87: 611
C88: Total current liabilities | H88: 36040.5 | I88: 48053.4 | J88: 37071.5 | K88: 39945.5 | L88: 39586.9
C89: Liabilities classified as held for sale | K89: - | L89: 62.9
C90: Total Liabilities | H90: 39612.5 | I90: 52218.6 | J90: 43216.5 | K90: 48605 | L90: 52574.7
C91: TOTAL EQUITY AND LIABILITIES | H91: 115192.6 | I91: 140691.9 | J91: 137566.5 | K91: 155749 | L91: 176911
C94: CASH FLOW STATEMENT
C95: Cash Flow from Operating Activities:
C96: Profit before Tax | H96: 18421 | I96: 18442.8 | J96: 13047.7 | K96: 20231.3 | L96: 25270.3
C97: Adjustments for:
C98: Depreciation and amortisation expense | H98: 2745.8 | I98: 3039.6 | J98: 3104.2 | K98: 2993 | L98: 3571.6
C99: Liabilities no longer required written back | H99: - | I99: -160.1 | J99: -17.5 | K99: -19.8 | L99: -155.1
C100: Profit on sale of investments (net) | H100: =-102.6+-351 -> -453.6 | I100: -33.8 | J100: -21.6 | K100: -146.3 | L100: -110.2
C101: Unrealised gain on fair valuation of investments (net) | H101: -266.9 | I101: 69 | J101: -287 | K101: -5.4 | L101: -418.7
C102: (Profit) / Loss on sale / write off of property plant and equipment (net) | H102: -37 | I102: 14.3 | J102: 123.6 | K102: 31.8 | L102: -46
C103: Employee stock compensation expenses | H103: 1.1 | K103: 189.4 | L103: 166.1
C104: Unrealised foreign currency loss on revaluation (net) | H104: 9.7 | I104: -177 | J104: -118.8 | K104: 594.3 | L104: 111.6
C105: Dividend Income | H105: -0.2 | I105: -1.9 | J105: -1.9 | K105: -1.9 | L105: -1.7
C106: Interest Income | H106: - | I106: 11.2 | J106: 1051.5 | K106: -2757.7 | L106: -3587.8
C107: Impairment loss on property, plant and equipment, capital work-in-progress and intangible assets under development | H107: -901.2 | I107: -1226.8 | J107: -1711.4 | K107: 992.2 | L107: 137.3
C108: Interest expenses | H108: 589.2 | I108: 523.7 | J108: 1073.6 | K108: 1124.1 | L108: 1217
C109: Provision for doubtful advances | H109: =82.8+-114.9 -> -32.1 | I109: 27.8 | J109: 48.8 | K109: 318 | L109: 20.2
...

Sheet Model
A1: Alkem Laboratories Limited | H1: Historical Period | M1: Forecasting Period
A2: Financial Statement Analysis & Valuation | H2: ='Historical Data'!H4 -> 2021 | I2: ='Historical Data'!I4 -> 2022 | J2: ='Historical Data'!J4 -> 2023 | K2: ='Historical Data'!K4 -> 2024 | L2: ='Historical Data'!L4 -> 2025 | M2: 2026 | N2: 2027 | O2: 2028 | P2: 2029 | Q2: 2030
A4: Ratio's & Assumptions
D6: LIVE SCENARIO | E6: Base Case | H6: =IF(E6=Scenarios!D5,1,IF(E6=Scenarios!D6,2,3)) -> 1
D7: Revenue Growth % | I7: =I22/H22-1 -> 0.19956887 | J7: =J22/I22-1 -> 0.090751623 | K7: =K22/J22-1 -> 0.092102427 | L7: =L22/K22-1 -> 0.023440941 | M7: {=CHOOSE(H6,Scenarios!H5:L5,Scenarios!H6:L6,Scenarios!H7:L7)} -> 0.10146596 | N7: 0.091319368 | O7: 0.082187431 | P7: 0.073968688 | Q7: 0.066571819
D8: COGS as % of revenue | H8: =-H23/H22 -> 0.39463689 | I8: =-I23/I22 -> 0.39309905 | J8: =-J23/J22 -> 0.42303043 | K8: =-K23/K22 -> 0.38978084 | L8: =-L23/L22 -> 0.36748449 | M8: =AVERAGE(H8:L8) -> 0.39360634 | N8: =M8 -> 0.39360634 | O8: =N8 -> 0.39360634 | P8: =O8 -> 0.39360634 | Q8: =P8 -> 0.39360634
D9: Operating Exp as % of revenue | H9: =-H25/H22 -> 0.38625563 | I9: =-I25/I22 -> 0.41385192 | J9: =-J25/J22 -> 0.43821502 | K9: =-K25/K22 -> 0.43295641 | L9: =-L25/L22 -> 0.43874436 | M9: =AVERAGE(H9:L9) -> 0.42200467 | N9: =M9 -> 0.42200467 | O9: =N9 -> 0.42200467 | P9: =O9 -> 0.42200467 | Q9: =P9 -> 0.42200467
D10: Depreciation as % of PPE | H10: =-H27/(H44+H45) -> 0.098385091 | I10: =-I27/(I44+I45) -> 0.10709907 | J10: =-J27/(J44+J45) -> 0.11971923 | K10: =-K27/(K44+K45) -> 0.11447214 | L10: =-L27/(L44+L45) -> 0.11996225 | M10: =AVERAGE(H10:L10) -> 0.11192756 | N10: =M10 -> 0.11192756 | O10: =N10 -> 0.11192756 | P10: =O10 -> 0.11192756 | Q10: =P10 -> 0.11192756
D11: Interest as % of Debt | H11: =-H29/H56 -> 0.032879831 | I11: =-I29/I56 -> 0.019627538 | J11: =-J29/J56 -> 0.076868001 | K11: =-K29/K56 -> 0.07925071 | L11: =-L29/L56 -> 0.088130929 | M11: =AVERAGE(H11:L11) -> 0.059351402 | N11: =M11 -> 0.059351402 | O11: =N11 -> 0.059351402 | P11: =O11 -> 0.059351402 | Q11: =P11 -> 0.059351402
D12: Other Income as % of revenue | H12: =H30/H22 -> 0.026306795 | I12: =I30/I22 -> 0.013888223 | J12: =J30/J22 -> 0.009750622 | K12: =K30/K22 -> 0.014947606 | L12: =L30/L22 -> 0.03808394 | M12: =AVERAGE(H12:L12) -> 0.020595437 | N12: =M12 -> 0.020595437 | O12: =N12 -> 0.020595437 | P12: =O12 -> 0.020595437 | Q12: =P12 -> 0.020595437
D13: Taxes as % of Pre-Tax Income | H13: =-H32/H31 -> 0.12177949 | I13: =-I32/I31 -> 0.088901902 | J13: =-J32/J31 -> 0.22836209 | K13: =-K32/K31 -> 0.10462501 | L13: =-L32/L31 -> 0.12308125 | M13: =AVERAGE(H13:L13) -> 0.13334995 | N13: =M13 -> 0.13334995 | O13: =N13 -> 0.13334995 | P13: =O13 -> 0.13334995 | Q13: =P13 -> 0.13334995
D14: Dividend Payout Ratio | H14: =-H89/H33 -> 0.20693918 | I14: =-I89/I33 -> 0.25108908 | J14: =-J89/J33 -> 0.52593836 | K14: =-K89/K33 -> 0.29837258 | L14: =-L89/L33 -> 0.22771661 | M14: =AVERAGE(H14:L14) -> 0.30201116 | N14: =M14 -> 0.30201116 | O14: =N14 -> 0.30201116 | P14: =O14 -> 0.30201116 | Q14: =P14 -> 0.30201116
D15: Days Sales Outstanding | H15: =H40/H22*365 -> 66.173828 | I15: =I40/I22*365 -> 64.685604 | J15: =J40/J22*365 -> 67.094427 | K15: =K40/K22*365 -> 64.911818 | L15: =L40/L22*365 -> 69.434214 | M15: =AVERAGE(H15:L15) -> 66.459978 | N15: =M15 -> 66.459978 | O15: =N15 -> 66.459978 | P15: =O15 -> 66.459978 | Q15: =P15 -> 66.459978
D16: Days Inventory Outstanding | H16: =H41/-H23*365 -> 241.26061 | I16: =I41/-I23*365 -> 262.4264 | J16: =J41/-J23*365 -> 193.96362 | K16: =K41/-K23*365 -> 196.72202 | L16: =L41/-L23*365 -> 223.89199 | M16: =AVERAGE(H16:L16) -> 223.65293 | N16: =M16 -> 223.65293 | O16: =N16 -> 223.65293 | P16: =O16 -> 223.65293 | Q16: =P16 -> 223.65293
D17: Days Payables Outstanding | H17: =H53/-H23*365 -> 111.57328 | I17: =I53/-I23*365 -> 102.45311 | J17: =J53/-J23*365 -> 86.660386 | K17: =K53/-K23*365 -> 129.22602 | L17: =L53/-L23*365 -> 140.91648 | M17: =AVERAGE(H17:L17) -> 114.16585 | N17: =M17 -> 114.16585 | O17: =N17 -> 114.16585 | P17: =O17 -> 114.16585 | Q17: =P17 -> 114.16585
D18: Capital Asset Turnover Ratio | H18: =H22/SUM(H44:H45) -> 3.1764324 | I18: =I22/SUM(I44:I45) -> 3.7469134 | J18: =J22/SUM(J44:J45) -> 4.4734699 | K18: =K22/SUM(K44:K45) -> 4.8449214 | L18: =L22/SUM(L44:L45) -> 4.3544993 | M18: =AVERAGE(H18:L18) -> 4.1192473 | N18: =M18 -> 4.1192473 | O18: =N18 -> 4.1192473 | P18: =O18 -> 4.1192473 | Q18: =P18 -> 4.1192473
A20: INCOME STATEMENT
D22: Revenue | H22: ='Historical Data'!H5 -> 88650.1 | I22: ='Historical Data'!I5 -> 106341.9 | J22: ='Historical Data'!J5 -> 115992.6 | K22: ='Historical Data'!K5 -> 126675.8 | L22: ='Historical Data'!L5 -> 129645.2 | M22: =L22*(1+M7) -> 142799.78 | N22: =M22*(1+N7) -> 155840.16 | O22: =N22*(1+O7) -> 168648.26 | P22: =O22*(1+P7) -> 181122.95 | Q22: =P22*(1+Q7) -> 193180.64
D23: Less: Cost of Good Sold | H23: =-SUM('Historical Data'!H9:H11) -> -34984.6 | I23: =-SUM('Historical Data'!I9:I11) -> -41802.9 | J23: =-SUM('Historical Data'!J9:J11) -> -49068.4 | K23: =-SUM('Historical Data'!K9:K11) -> -49375.8 | L23: =-SUM('Historical Data'!L9:L11) -> -47642.6 | M23: =-M22*M8 -> -56206.897 | N23: =-N22*N8 -> -61339.675 | O23: =-O22*O8 -> -66381.026 | P23: =-P22*P8 -> -71291.143 | Q23: =-Q22*Q8 -> -76037.124
D24: Gross Profit | H24: =SUM(H22:H23) -> 53665.5 | I24: =SUM(I22:I23) -> 64539 | J24: =SUM(J22:J23) -> 66924.2 | K24: =SUM(K22:K23) -> 77300 | L24: =SUM(L22:L23) -> 82002.6 | M24: =SUM(M22:M23) -> 86592.878 | N24: =SUM(N22:N23) -> 94500.485 | O24: =SUM(O22:O23) -> 102267.24 | ... Q24: =SUM(Q22:Q23) -> 117143.51
D25: Less: Operating Expenses | H25: =-SUM('Historical Data'!H12,'Historical Data'!H15) -> -34241.6 | I25: =-SUM('Historical Data'!I12,'Historical Data'!I15) -> -44009.8 | J25: =-SUM('Historical Data'!J12,'Historical Data'!J15) -> -50829.7 | K25: =-SUM('Historical Data'!K12,'Historical Data'!K15) -> -54845.1 | L25: =-SUM('Historical Data'!L12,'Historical Data'!L15) -> -56881.1 | M25: =M22*-M9 -> -60262.172 | N25: =N22*-N9 -> -65765.275 | O25: =O22*-O9 -> -71170.354 | P25: =P22*-P9 -> -76434.732 | Q25: =Q22*-Q9 -> -81523.131
D26: EBITDA | H26: =SUM(H24:H25) -> 19423.9 | I26: =SUM(I24:I25) -> 20529.2 | J26: =SUM(J24:J25) -> 16094.5 | K26: =SUM(K24:K25) -> 22454.9 | L26: =SUM(L24:L25) -> 25121.5 | M26: =SUM(M24:M25) -> 26330.706 | N26: =SUM(N24:N25) -> 28735.21 | O26: =SUM(O24:O25) -> 31096.883 | ... Q26: =SUM(Q24:Q25) -> 35620.383
D27: Less: Depreciation & Amortization | H27: =-'Historical Data'!H14 -> -2745.8 | I27: =-'Historical Data'!I14 -> -3039.6 | J27: =-'Historical Data'!J14 -> -3104.2 | K27: =-'Historical Data'!K14 -> -2993 | L27: =-'Historical Data'!L14 -> -3571.6 | M27: =M109 -> -3332.3855 | N27: =N109 -> -3316.8339 | O27: =O109 -> -3299.9201 | P27: =P109 -> -3278.5879 | Q27: =Q109 -> -3250.584
D28: EBIT | H28: =SUM(H26:H27) -> 16678.1 | I28: =SUM(I26:I27) -> 17489.6 | J28: =SUM(J26:J27) -> 12990.3 | K28: =SUM(K26:K27) -> 19461.9 | L28: =SUM(L26:L27) -> 21549.9 | M28: =SUM(M26:M27) -> 22998.321 | N28: =SUM(N26:N27) -> 25418.376 | O28: =SUM(O26:O27) -> 27796.963 | ... Q28: =SUM(Q26:Q27) -> 32369.799
D29: Less: Interest | H29: =-'Historical Data'!H13 -> -589.2 | I29: =-'Historical Data'!I13 -> -523.7 | J29: =-'Historical Data'!J13 -> -1073.6 | K29: =-'Historical Data'!K13 -> -1124.1 | L29: =-'Historical Data'!L13 -> -1217 | M29: =M116 -> -819.58351 | N29: =N116 -> -765.40043 | O29: =O116 -> -711.21735 | P29: =P116 -> -657.03426 | Q29: =Q116 -> -602.85118
D30: Other Income | H30: ='Historical Data'!H6+'Historical Data'!H18 -> 2332.1 | I30: ='Historical Data'!I6+'Historical Data'!I18 -> 1476.9 | J30: ='Historical Data'!J6+'Historical Data'!J18 -> 1131 | K30: ='Historical Data'!K6+'Historical Data'!K18 -> 1893.5 | L30: ='Historical Data'!L6+'Historical Data'!L18 -> 4937.4 | M30: =M22*M12 -> 2941.0238 | N30: =N22*N12 -> 3209.5962 | O30: =O22*O12 -> 3473.3847 | P30: =P22*P12 -> 3730.3064 | Q30: =Q22*Q12 -> 3978.6397
D31: Profit Before Tax | H31: =SUM(H28:H30) -> 18421 | I31: =SUM(I28:I30) -> 18442.8 | J31: =SUM(J28:J30) -> 13047.7 | K31: =SUM(K28:K30) -> 20231.3 | L31: =SUM(L28:L30) -> 25270.3 | M31: =SUM(M28:M30) -> 25119.761 | N31: =SUM(N28:N30) -> 27862.572 | O31: =SUM(O28:O30) -> 30559.13 | ... Q31: =SUM(Q28:Q30) -> 35745.587
D32: Less: Taxes | H32: =-'Historical Data'!H22 -> -2243.3 | I32: =-'Historical Data'!I22 -> -1639.6 | J32: =-'Historical Data'!J22 -> -2979.6 | K32: =-'Historical Data'!K22 -> -2116.7 | L32: =-'Historical Data'!L22 -> -3110.3 | M32: =M31*-M13 -> -3349.7188 | N32: =N31*-N13 -> -3715.4725 | O32: =O31*-O13 -> -4075.0584 | P32: =P31*-P13 -> -4426.1198 | Q32: =Q31*-Q13 -> -4766.6722
D33: Profit After Tax | H33: =SUM(H31:H32) -> 16177.7 | I33: =SUM(I31:I32) -> 16803.2 | J33: =SUM(J31:J32) -> 10068.1 | K33: =SUM(K31:K32) -> 18114.6 | L33: =SUM(L31:L32) -> 22160 | M33: =SUM(M31:M32) -> 21770.042 | N33: =SUM(N31:N32) -> 24147.099 | O33: =SUM(O31:O32) -> 26484.072 | ... Q33: =SUM(Q31:Q32) -> 30978.915
A35: BALANCE SHEET
B37: ASSET'S
C38: Current Assets
D39: Cash & Bank | H39: ='Historical Data'!H50+'Historical Data'!H51 -> 19904.5 | I39: ='Historical Data'!I50+'Historical Data'!I51 -> 25785.8 | J39: ='Historical Data'!J50+'Historical Data'!J51 -> 26168.9 | K39: ='Historical Data'!K50+'Historical Data'!K51 -> 15793.5 | L39: ='Historical Data'!L50+'Historical Data'!L51 -> 15630.8 | M39: =M95 -> 22683.804 | N39: =N95 -> 34862.331 | O39: =O95 -> 48781.233 | P39: =P95 -> 64452.328 | Q39: =Q95 -> 81866.656
D40: Accounts Receivable | H40: ='Historical Data'!H49 -> 16072.1 | I40: ='Historical Data'!I49 -> 18846 | J40: ='Historical Data'!J49 -> 21321.8 | K40: ='Historical Data'!K49 -> 22528.1 | L40: ='Historical Data'!L49 -> 24662.5 | M40: =M22/365*M15 -> 26001.287 | N40: =N22/365*N15 -> 28375.709 | O40: =O22/365*O15 -> 30707.835 | P40: =P22/365*P15 -> 32979.254 | Q40: =Q22/365*Q15 -> 35174.742
D41: Inventory | H41: ='Historical Data'!H46 -> 23124.4 | I41: ='Historical Data'!I46 -> 30055.3 | J41: ='Historical Data'!J46 -> 26075.3 | K41: ='Historical Data'!K46 -> 26611.8 | L41: ='Historical Data'!L46 -> 29224.1 | M41: =-M23/365*M16 -> 34440.65 | N41: =-N23/365*N16 -> 37585.748 | O41: =-O23/365*O16 -> 40674.824 | P41: =-P23/365*P16 -> 43683.487 | Q41: =-Q23/365*Q16 -> 46591.577
D42: Other Current Assets | H42: =SUM('Historical Data'!H48,'Historical Data'!H54,'Historical Data'!H53,'Historical Data'!H52,'Historical Data'!H56) -> 10187.2 | I42: =SUM('Historical Data'!I48,'Historical Data'!I54,'Historical Data'!I53,'Historical Data'!I52,'Historical Data'!I56) -> 9667.2 | J42: =SUM('Historical Data'!J48,'Historical Data'!J54,'Historical Data'!J53,'Historical Data'!J52,'Historical Data'!J56) -> 13730.8 | K42: =SUM('Historical Data'!K48,'Historical Data'!K54,'Historical Data'!K53,'Historical Data'!K52,'Historical Data'!K56) -> 39182.4 | L42: =SUM('Historical Data'!L48,'Historical Data'!L54,'Historical Data'!L53,'Historical Data'!L52,'Historical Data'!L56) -> 39940.8 | M42: =L42 -> 39940.8 | N42: =M42 -> 39940.8 | O42: =N42 -> 39940.8 | P42: =O42 -> 39940.8 | Q42: =P42 -> 39940.8
C43: Non-Current Assets
D44: Plant, Property & Equipment | H44: =SUM('Historical Data'!H30:'Historical Data'!H32) -> 26272.1 | I44: =SUM('Historical Data'!I30:'Historical Data'!I32) -> 26265.8 | J44: =SUM('Historical Data'!J30:'Historical Data'!J32) -> 25135.2 | K44: =SUM('Historical Data'!K30:'Historical Data'!K32) -> 25570.3 | L44: =SUM('Historical Data'!L30:'Historical Data'!L32) -> 28627 | M44: =M110-M45 -> 28488.056 | N44: =N110-N45 -> 28336.943 | O44: =O110-O45 -> 28146.353 | P44: =P110-P45 -> 27896.156 | Q44: =Q110-Q45 -> 27572.729
D45: Intangible Assets | H45: ='Historical Data'!H34+'Historical Data'!H35 -> 1636.6 | I45: ='Historical Data'!I34+'Historical Data'!I35 -> 2115.4 | J45: ='Historical Data'!J34+'Historical Data'!J35 -> 793.8 | K45: ='Historical Data'!K34+'Historical Data'!K35 -> 575.8 | L45: ='Historical Data'!L34+'Historical Data'!L35 -> 1145.7 | M45: =L45 -> 1145.7 | N45: =M45 -> 1145.7 | O45: =N45 -> 1145.7 | P45: =O45 -> 1145.7 | Q45: =P45 -> 1145.7
D46: Goodwill | H46: ='Historical Data'!H33 -> 3953.9 | I46: ='Historical Data'!I33 -> 4030.9 | J46: ='Historical Data'!J33 -> 4131.7 | K46: ='Historical Data'!K33 -> 4167.4 | L46: ='Historical Data'!L33 -> 4231.1 | M46: =L46 -> 4231.1 | N46: =M46 -> 4231.1 | O46: =N46 -> 4231.1 | P46: =O46 -> 4231.1 | Q46: =P46 -> 4231.1
D47: Financial Assets | H47: =SUM('Historical Data'!H37:H39) -> 2227.6 | I47: =SUM('Historical Data'!I37:I39) -> 9503.6 | J47: =SUM('Historical Data'!J37:J39) -> 6078.8 | K47: =SUM('Historical Data'!K37:K39) -> 4550.2 | L47: =SUM('Historical Data'!L37:L39) -> 14186 | M47: =L47 -> 14186 | N47: =M47 -> 14186 | O47: =N47 -> 14186 | P47: =O47 -> 14186 | Q47: =P47 -> 14186
D48: Other Non-Current Assets | H48: =SUM('Historical Data'!H40:H42) -> 11814.2 | I48: =SUM('Historical Data'!I40:I42) -> 14421.9 | J48: =SUM('Historical Data'!J40:J42) -> 14130 | K48: =SUM('Historical Data'!K40:K42) -> 16769.5 | L48: =SUM('Historical Data'!L40:L42) -> 19263 | M48: =L48 -> 19263 | N48: =M48 -> 19263 | O48: =N48 -> 19263 | P48: =O48 -> 19263 | Q48: =P48 -> 19263
D49: TOTAL ASSETS | H49: =SUM(H39:H48) -> 115192.6 | I49: =SUM(I39:I48) -> 140691.9 | J49: =SUM(J39:J48) -> 137566.3 | K49: =SUM(K39:K48) -> 155749 | L49: =SUM(L39:L48) -> 176911 | M49: =SUM(M39:M48) -> 190380.4 | N49: =SUM(N39:N48) -> 207927.33 | O49: =SUM(O39:O48) -> 227076.85 | ... Q49: =SUM(Q39:Q48) -> 269972.3
B51: LIABILITIE'S
C52: Current Liabilities
D53: Accounts Payable | H53: =SUM('Historical Data'!H82:H83) -> 10694.1 | I53: =SUM('Historical Data'!I82:I83) -> 11733.8 | J53: =SUM('Historical Data'!J82:J83) -> 11650.1 | K53: =SUM('Historical Data'!K82:K83) -> 17481.2 | L53: =SUM('Historical Data'!L82:L83) -> 18393.5 | M53: =-M23/365*M17 -> 17580.571 | N53: =-N23/365*N17 -> 19186.018 | O53: =-O23/365*O17 -> 20762.867 | P53: =-P23/365*P17 -> 22298.669 | Q53: =-Q23/365*Q17 -> 23783.132
D54: Other Current Liability | H54: =SUM('Historical Data'!H84:H87,'Historical Data'!H89) -> 8403 | I54: =SUM('Historical Data'!I84:I87,'Historical Data'!I89) -> 10396.2 | J54: =SUM('Historical Data'!J84:J87,'Historical Data'!J89) -> 12157.7 | K54: =SUM('Historical Data'!K84:K87,'Historical Data'!K89) -> 10572.8 | L54: =SUM('Historical Data'!L84:L87,'Historical Data'!L89) -> 13230.6 | M54: =L54 -> 13230.6 | N54: =M54 -> 13230.6 | O54: =N54 -> 13230.6 | P54: =O54 -> 13230.6 | Q54: =P54 -> 13230.6
C55: Non Current Liabilities
D56: Debt | H56: =SUM('Historical Data'!H70:H71,'Historical Data'!H79:H80) -> 17919.8 | I56: =SUM('Historical Data'!I70:I71,'Historical Data'!I79:I80) -> 26681.9 | J56: =SUM('Historical Data'!J70:J71,'Historical Data'!J79:J80) -> 13966.8 | K56: =SUM('Historical Data'!K70:K71,'Historical Data'!K79:K80) -> 14184.1 | L56: =SUM('Historical Data'!L70:L71,'Historical Data'!L79:L80) -> 13809 | M56: =M115 -> 12896.08 | N56: =N115 -> 11983.16 | O56: =O115 -> 11070.24 | P56: =P115 -> 10157.32 | Q56: =Q115 -> 9244.4
D57: Other Non Current Liability | H57: =SUM('Historical Data'!H72:H74) -> 2595.6 | I57: =SUM('Historical Data'!I72:I74) -> 3406.7 | J57: =SUM('Historical Data'!J72:J74) -> 5441.7 | K57: =SUM('Historical Data'!K72:K74) -> 6366.9 | L57: =SUM('Historical Data'!L72:L74) -> 7141.6 | M57: =L57 -> 7141.6 | N57: =M57 -> 7141.6 | O57: =N57 -> 7141.6 | P57: =O57 -> 7141.6 | Q57: =P57 -> 7141.6
D58: Total Liabilities | H58: =SUM(H53:H57) -> 39612.5 | I58: =SUM(I53:I57) -> 52218.6 | J58: =SUM(J53:J57) -> 43216.3 | K58: =SUM(K53:K57) -> 48605 | L58: =SUM(L53:L57) -> 52574.7 | M58: =SUM(M53:M57) -> 50848.851 | N58: =SUM(N53:N57) -> 51541.378 | O58: =SUM(O53:O57) -> 52205.307 | ... Q58: =SUM(Q53:Q57) -> 53399.732
D60: Equity | H60: ='Historical Data'!H61 -> 239.1 | I60: ='Historical Data'!I61 -> 239.1 | J60: ='Historical Data'!J61 -> 239.1 | K60: ='Historical Data'!K61 -> 239.1 | L60: ='Historical Data'!L61 -> 239.1 | M60: =L60 -> 239.1 | N60: =M60 -> 239.1 | O60: =N60 -> 239.1 | P60: =O60 -> 239.1 | Q60: =P60 -> 239.1
D61: Other Equity | H61: ='Historical Data'!H62 -> 73528.2 | I61: ='Historical Data'!I62 -> 86139.9 | J61: ='Historical Data'!J62 -> 90213.8 | K61: ='Historical Data'!K62 -> 102881.5 | L61: ='Historical Data'!L62 -> 119609.6 | M61: =L61+M33+M89 -> 134804.85 | N61: =M61+N33+N89 -> 151659.25 | O61: =N61+O33+O89 -> 170144.84 | P61: =O61+P33+P89 -> 190222.94 | Q61: =P61+Q33+Q89 -> 211845.87
D62: Shareholders' Funds | H62: =H60+H61 -> 73767.3 | I62: =I60+I61 -> 86379 | J62: =J60+J61 -> 90452.9 | K62: =K60+K61 -> 103120.6 | L62: =L60+L61 -> 119848.7 | M62: =M60+M61 -> 135043.95 | N62: =N60+N61 -> 151898.35 | O62: =O60+O61 -> 170383.94 | ... Q62: =Q60+Q61 -> 212084.97
D63: Non Controlling Interest | H63: ='Historical Data'!H64 -> 1812.8 | I63: ='Historical Data'!I64 -> 2094.3 | J63: ='Historical Data'!J64 -> 3897.1 | K63: ='Historical Data'!K64 -> 4023.4 | L63: ='Historical Data'!L64 -> 4487.6 | M63: =L63 -> 4487.6 | N63: =M63 -> 4487.6 | O63: =N63 -> 4487.6 | P63: =O63 -> 4487.6 | Q63: =P63 -> 4487.6
D64: Total Equity & Liabilities | H64: =SUM(H58,H62:H63) -> 115192.6 | I64: =SUM(I58,I62:I63) -> 140691.9 | J64: =SUM(J58,J62:J63) -> 137566.3 | K64: =SUM(K58,K62:K63) -> 155749 | L64: =SUM(L58,L62:L63) -> 176911 | M64: =SUM(M58,M62:M63) -> 190380.4 | N64: =SUM(N58,N62:N63) -> 207927.33 | O64: =SUM(O58,O62:O63) -> 227076.85 | ... Q64: =SUM(Q58,Q62:Q63) -> 269972.3
D66: CHECK | H66: =IF(H49=H64,"TALLIED","ERROR") -> TALLIED | I66: =IF(I49=I64,"TALLIED","ERROR") -> TALLIED | J66: =IF(J49=J64,"TALLIED","ERROR") -> TALLIED | K66: =IF(K49=K64,"TALLIED","ERROR") -> TALLIED | L66: =IF(L49=L64,"TALLIED","ERROR") -> TALLIED | M66: =IF(M49=M64,"TALLIED","ERROR") -> TALLIED | N66: =IF(N49=N64,"TALLIED","ERROR") -> TALLIED | O66: =IF(O49=O64,"TALLIED","ERROR") -> TALLIED | ... Q66: =IF(Q49=Q64,"TALLIED","ERROR") -> TALLIED
A68: CASH FLOW STATEMENT
C71: Cash Flow from Operations
D72: Profit after Tax | H72: ='Historical Data'!H96+'Historical Data'!H121 -> 14414.2 | I72: ='Historical Data'!I96+'Historical Data'!I121 -> 14473.8 | J72: ='Historical Data'!J96+'Historical Data'!J121 -> 10313.8 | K72: ='Historical Data'!K96+'Historical Data'!K121 -> 16161.9 | L72: ='Historical Data'!L96+'Historical Data'!L121 -> 20230.1 | M72: =M33 -> 21770.042 | N72: =N33 -> 24147.099 | O72: =O33 -> 26484.072 | P72: =P33 -> 28765.643 | Q72: =Q33 -> 30978.915
D73: Add: Depreciation & Amortization | H73: ='Historical Data'!H98 -> 2745.8 | I73: ='Historical Data'!I98 -> 3039.6 | J73: ='Historical Data'!J98 -> 3104.2 | K73: ='Historical Data'!K98 -> 2993 | L73: ='Historical Data'!L98 -> 3571.6 | M73: =-M109 -> 3332.3855 | N73: =-N109 -> 3316.8339 | O73: =-O109 -> 3299.9201 | P73: =-P109 -> 3278.5879 | Q73: =-Q109 -> 3250.584
D74: Add/Less: Other Adjustments | H74: ='Historical Data'!H111-'Historical Data'!H98 -> -1099.4 | I74: ='Historical Data'!I111-'Historical Data'!I98 -> -953.6 | J74: ='Historical Data'!J111-'Historical Data'!J98 -> 139.3 | K74: ='Historical Data'!K111-'Historical Data'!K98 -> 842.7 | L74: ='Historical Data'!L111-'Historical Data'!L98 -> -2533.6 | M74: =-SUM(M29:M30) -> -2121.4403 | N74: =-SUM(N29:N30) -> -2444.1958 | O74: =-SUM(O29:O30) -> -2762.1674 | P74: =-SUM(P29:P30) -> -3073.2722 | Q74: =-SUM(Q29:Q30) -> -3375.7885
D75: Add/Less: Working Capital Adjustments | H75: ='Historical Data'!H119 -> -3411.6 | I75: ='Historical Data'!I119 -> -5449.6 | J75: ='Historical Data'!J119 -> 3267.7 | K75: ='Historical Data'!K119 -> -516.9 | L75: ='Historical Data'!L119 -> -2139.7 | M75: =M104 -> -7368.2661 | N75: =N104 -> -3914.0729 | O75: =O104 -> -3844.3532 | P75: =P104 -> -3744.2796 | Q75: =Q104 -> -3619.1152
D76: Operating Cash Flow | H76: =SUM(H72:H75) -> 12649 | I76: =SUM(I72:I75) -> 11110.2 | J76: =SUM(J72:J75) -> 16825 | K76: =SUM(K72:K75) -> 19480.7 | L76: =SUM(L72:L75) -> 19128.4 | M76: =SUM(M72:M75) -> 15612.721 | N76: =SUM(N72:N75) -> 21105.664 | O76: =SUM(O72:O75) -> 23177.471 | ... Q76: =SUM(Q72:Q75) -> 27234.595
C78: Cash Flow from Investing Activities
D79: Investment in PP&E | H79: ='Historical Data'!H124 -> -1949.1 | I79: ='Historical Data'!I124 -> -3388.8 | J79: ='Historical Data'!J124 -> -2329.1 | K79: ='Historical Data'!K124 -> -2592.9 | L79: ='Historical Data'!L124 -> -6756.2 | M79: =-M108 -> -3193.4415 | N79: =-N108 -> -3165.7204 | O79: =-O108 -> -3109.3308 | P79: =-P108 -> -3028.3908 | Q79: =-Q108 -> -2927.1573
D80: Sale proceeds from sale of PP&E | H80: ='Historical Data'!H125 -> 104.6 | I80: ='Historical Data'!I125 -> 109 | J80: ='Historical Data'!J125 -> 32 | K80: ='Historical Data'!K125 -> 724.8 | L80: ='Historical Data'!L125 -> 408.4
D81: Purchase/sale of investments | H81: =SUM('Historical Data'!H126:H130) -> -8935 | I81: =SUM('Historical Data'!I126:I130) -> -12049.2 | J81: =SUM('Historical Data'!J126:J130) -> 1956.4 | K81: =SUM('Historical Data'!K126:K130) -> -10611.6 | L81: =SUM('Historical Data'!L126:L130) -> -10118.6 | M81: =L47-M47 -> 0 | N81: =M47-N47 -> 0 | O81: =N47-O47 -> 0 | P81: =O47-P47 -> 0 | Q81: =P47-Q47 -> 0
D82: Dividend Income | H82: ='Historical Data'!H131 -> 785.7 | I82: ='Historical Data'!I131 -> 977.7 | J82: ='Historical Data'!J131 -> 1469.1 | K82: ='Historical Data'!K131 -> 1.9 | L82: ='Historical Data'!L131 -> 1.7
D83: Interest income | H83: ='Historical Data'!H132 -> 8.4 | I83: ='Historical Data'!I132 -> 0 | J83: ='Historical Data'!J132 -> 0 | K83: ='Historical Data'!K132 -> 2392.8 | L83: ='Historical Data'!L132 -> 3477.1 | M83: =M30 -> 2941.0238 | N83: =N30 -> 3209.5962 | O83: =O30 -> 3473.3847 | P83: =P30 -> 3730.3064 | Q83: =Q30 -> 3978.6397
D84: Cash Flow from Investing Activities | H84: =SUM(H79:H83) -> -9985.4 | I84: =SUM(I79:I83) -> -14351.3 | J84: =SUM(J79:J83) -> 1128.4 | K84: =SUM(K79:K83) -> -10085 | L84: =SUM(L79:L83) -> -12987.6 | M84: =SUM(M79:M83) -> -252.41771 | N84: =SUM(N79:N83) -> 43.87582 | O84: =SUM(O79:O83) -> 364.0539 | ... Q84: =SUM(Q79:Q83) -> 1051.4825
C86: Cash Flow from Financing Activities
D87: Issuance/repayment of debt | H87: =SUM('Historical Data'!H135:H136,'Historical Data'!H139,'Historical Data'!H146) -> 1166.5 | I87: =SUM('Historical Data'!I135:I136,'Historical Data'!I139,'Historical Data'!I146) -> 8416.1 | J87: =SUM('Historical Data'!J135:J136,'Historical Data'!J139,'Historical Data'!J146) -> -13023.2 | K87: =SUM('Historical Data'!K135:K136,'Historical Data'!K139,'Historical Data'!K146) -> -1244.5 | L87: =SUM('Historical Data'!L135:L136,'Historical Data'!L139,'Historical Data'!L146) -> 1984.7 | M87: =M114 -> -912.92 | N87: =N114 -> -912.92 | O87: =O114 -> -912.92 | P87: =P114 -> -912.92 | Q87: =Q114 -> -912.92
D88: Proceeds from issue of preferance shares | H88: ='Historical Data'!H137 -> 0 | I88: ='Historical Data'!I137 -> 0 | J88: ='Historical Data'!J137 -> 1614.8 | K88: ='Historical Data'!K137 -> 0 | L88: ='Historical Data'!L137 -> 0 | M88: ='Historical Data'!M137 -> 0 | N88: ='Historical Data'!N137 -> 0 | O88: ='Historical Data'!O137 -> 0 | ... Q88: ='Historical Data'!Q137 -> 0
D89: Dividend paid | H89: ='Historical Data'!H138 -> -3347.8 | I89: ='Historical Data'!I138 -> -4219.1 | J89: ='Historical Data'!J138 -> -5295.2 | K89: ='Historical Data'!K138 -> -5404.9 | L89: ='Historical Data'!L138 -> -5046.2 | M89: =M33*-M14 -> -6574.7957 | N89: =N33*-N14 -> -7292.6935 | O89: =O33*-O14 -> -7998.4852 | P89: =P33*-P14 -> -8687.5452 | Q89: =Q33*-Q14 -> -9355.9781
D90: Interest paid | H90: ='Historical Data'!H140 -> -536.2 | I90: ='Historical Data'!I140 -> -401.3 | J90: ='Historical Data'!J140 -> -904.6 | K90: ='Historical Data'!K140 -> -913.1 | L90: ='Historical Data'!L140 -> -806.1 | M90: =M116 -> -819.58351 | N90: =N116 -> -765.40043 | O90: =O116 -> -711.21735 | P90: =P116 -> -657.03426 | Q90: =Q116 -> -602.85118
D91: Cash Flow from Financing Activities | H91: =SUM(H87:H90) -> -2717.5 | I91: =SUM(I87:I90) -> 3795.7 | J91: =SUM(J87:J90) -> -17608.2 | K91: =SUM(K87:K90) -> -7562.5 | L91: =SUM(L87:L90) -> -3867.6 | M91: =SUM(M87:M90) -> -8307.2992 | N91: =SUM(N87:N90) -> -8971.0139 | O91: =SUM(O87:O90) -> -9622.6226 | ... Q91: =SUM(Q87:Q90) -> -10871.749
C93: Net decrease in Cash and Cash Equivalents | H93: =H76+H84+H91 -> -53.9 | I93: =I76+I84+I91 -> 554.6 | J93: =J76+J84+J91 -> 345.2 | K93: =K76+K84+K91 -> 1833.2 | L93: =L76+L84+L91 -> 2273.2 | M93: =M76+M84+M91 -> 7053.0043 | N93: =N76+N84+N91 -> 12178.526 | O93: =O76+O84+O91 -> 13918.902 | ... Q93: =Q76+Q84+Q91 -> 17414.328
D94: Opening Cash Balance | H94: ='Historical Data'!H143+'Historical Data'!H144+'Historical Data'!H51 -> 19958.4 | I94: ='Historical Data'!I143+'Historical Data'!I144+'Historical Data'!I51 -> 25231.2 | J94: ='Historical Data'!J143+'Historical Data'!J144+'Historical Data'!J51 -> 25823.7 | K94: ='Historical Data'!K143+'Historical Data'!K144+'Historical Data'!K51 -> 13960.3 | L94: ='Historical Data'!L143+'Historical Data'!L144+'Historical Data'!L51 -> 13357.6 | M94: =L95 -> 15630.8 | N94: =M95 -> 22683.804 | O94: =N95 -> 34862.331 | P94: =O95 -> 48781.233 | Q94: =P95 -> 64452.328
D95: Closing Cash Balance | H95: =SUM(H93:H94) -> 19904.5 | I95: =SUM(I93:I94) -> 25785.8 | J95: =SUM(J93:J94) -> 26168.9 | K95: =SUM(K93:K94) -> 15793.5 | L95: =SUM(L93:L94) -> 15630.8 | M95: =SUM(M93:M94) -> 22683.804 | N95: =SUM(N93:N94) -> 34862.331 | O95: =SUM(O93:O94) -> 48781.233 | ... Q95: =SUM(Q93:Q94) -> 81866.656
A97: SUPPORTING SCHEDULES
C99: Working Capital
D100: Accounts Receivable | H100: ='Historical Data'!H114 -> -257.6 | I100: ='Historical Data'!I114 -> -2217.5 | J100: ='Historical Data'!J114 -> -1347.1 | K100: ='Historical Data'!K114 -> -2219.9 | L100: ='Historical Data'!L114 -> -2185.5 | M100: =L40-M40 -> -1338.7875 | N100: =M40-N40 -> -2374.4211 | O100: =N40-O40 -> -2332.1266 | P100: =O40-P40 -> -2271.4183 | Q100: =P40-Q40 -> -2195.4889
D101: Inventory | H101: ='Historical Data'!H116 -> -4977 | I101: ='Historical Data'!I116 -> -6731.4 | J101: ='Historical Data'!J116 -> 4734.1 | K101: ='Historical Data'!K116 -> -734 | L101: ='Historical Data'!L116 -> -2612.3 | M101: =L41-M41 -> -5216.5496 | N101: =M41-N41 -> -3145.0984 | O101: =N41-O41 -> -3089.0761 | P101: =O41-P41 -> -3008.6634 | Q101: =P41-Q41 -> -2908.0892
D102: Accounts Payable | H102: ='Historical Data'!H117 -> 2124.2 | I102: ='Historical Data'!I117 -> 3344.9 | J102: ='Historical Data'!J117 -> 145.1 | K102: ='Historical Data'!K117 -> 5252.8 | L102: ='Historical Data'!L117 -> 2166.5 | M102: =M53-L53 -> -812.92902 | N102: =N53-M53 -> 1605.4466 | O102: =O53-N53 -> 1576.8495 | P102: =P53-O53 -> 1535.802 | Q102: =Q53-P53 -> 1484.463
D103: Others | H103: ='Historical Data'!H118+'Historical Data'!H115 -> -301.2 | I103: ='Historical Data'!I118+'Historical Data'!I115 -> 154.4 | J103: ='Historical Data'!J118+'Historical Data'!J115 -> -264.4 | K103: ='Historical Data'!K118+'Historical Data'!K115 -> -2815.8 | L103: ='Historical Data'!L118+'Historical Data'!L115 -> 491.6
D104: Total | H104: =SUM(H100:H103) -> -3411.6 | I104: =SUM(I100:I103) -> -5449.6 | J104: =SUM(J100:J103) -> 3267.7 | K104: =SUM(K100:K103) -> -516.9 | L104: =SUM(L100:L103) -> -2139.7 | M104: =SUM(M100:M103) -> -7368.2661 | N104: =SUM(N100:N103) -> -3914.0729 | O104: =SUM(O100:O103) -> -3844.3532 | ... Q104: =SUM(Q100:Q103) -> -3619.1152
C106: Depreciation & Amortization
D107: Opening Balance | I107: =H110 -> 27908.7 | J107: =I110 -> 28381.2 | K107: =J110 -> 25929 | L107: =K110 -> 26146.1 | M107: =L110 -> 29772.7 | N107: =M110 -> 29633.756 | O107: =N110 -> 29482.643 | P107: =O110 -> 29292.053 | Q107: =P110 -> 29041.856
D108: Add/Less: Purchase/sale | I108: =I110-I107-I109 -> 3512.1 | J108: =J110-J107-J109 -> 652 | K108: =K110-K107-K109 -> 3210.1 | L108: =L110-L107-L109 -> 7198.2 | M108: =(M22-L22)/M18 -> 3193.4415 | N108: =(N22-M22)/N18 -> 3165.7204 | O108: =(O22-N22)/O18 -> 3109.3308 | P108: =(P22-O22)/P18 -> 3028.3908 | Q108: =(Q22-P22)/Q18 -> 2927.1573
D109: Less: Depreciation & Amortization | H109: =H27 -> -2745.8 | I109: =I27 -> -3039.6 | J109: =J27 -> -3104.2 | K109: =K27 -> -2993 | L109: =L27 -> -3571.6 | M109: =M107*-M10 -> -3332.3855 | N109: =N107*-N10 -> -3316.8339 | O109: =O107*-O10 -> -3299.9201 | P109: =P107*-P10 -> -3278.5879 | Q109: =Q107*-Q10 -> -3250.584
D110: Closing Balance | H110: =H44+H45 -> 27908.7 | I110: =I44+I45 -> 28381.2 | J110: =J44+J45 -> 25929 | K110: =K44+K45 -> 26146.1 | L110: =L44+L45 -> 29772.7 | M110: =SUM(M107:M109) -> 29633.756 | N110: =SUM(N107:N109) -> 29482.643 | O110: =SUM(O107:O109) -> 29292.053 | P110: =SUM(P107:P109) -> 29041.856 | Q110: =SUM(Q107:Q109) -> 28718.429
C112: Debt Schedule
D113: Opening Balance | I113: =H115 -> 17919.8 | J113: =I115 -> 26681.9 | K113: =J115 -> 13966.8 | L113: =K115 -> 14184.1 | M113: =L115 -> 13809 | N113: =M115 -> 12896.08 | O113: =N115 -> 11983.16 | P113: =O115 -> 11070.24 | Q113: =P115 -> 10157.32
D114: Issuance/repayment | I114: =I115-I113 -> 8762.1 | J114: =J115-J113 -> -12715.1 | K114: =K115-K113 -> 217.3 | L114: =L115-L113 -> -375.1 | M114: =-'Lease Liab'!H12 -> -912.92 | N114: =M114 -> -912.92 | O114: =N114 -> -912.92 | P114: =O114 -> -912.92 | Q114: =P114 -> -912.92
D115: Closing Balance | H115: =H56 -> 17919.8 | I115: =I56 -> 26681.9 | J115: =J56 -> 13966.8 | K115: =K56 -> 14184.1 | L115: =L56 -> 13809 | M115: =SUM(M113:M114) -> 12896.08 | N115: =SUM(N113:N114) -> 11983.16 | O115: =SUM(O113:O114) -> 11070.24 | P115: =SUM(P113:P114) -> 10157.32 | Q115: =SUM(Q113:Q114) -> 9244.4
D116: Interest Expense | H116: =H29 -> -589.2 | I116: =I29 -> -523.7 | J116: =J29 -> -1073.6 | K116: =K29 -> -1124.1 | L116: =L29 -> -1217 | M116: =-M113*M11 -> -819.58351 | N116: =-N113*N11 -> -765.40043 | O116: =-O113*O11 -> -711.21735 | P116: =-P113*P11 -> -657.03426 | Q116: =-Q113*Q11 -> -602.85118
A118: DCF VALUTION
D121: Assumption's
D122: Transaction Date | F122: 46230
...

Sheet Lease Liab
A1: Alkem Laboratories Limited
A2: Lease Liability
E5: Amount | F5: Duration | G5: Rate | H5: Repay
D6: Exim | E6: 800 | F6: 5 | G6: 0.085 | H6: =E6/F6 -> 160
D7: HSBC | E7: 1259.4 | F7: 5 | G7: 0.0549 | H7: =E7/F7 -> 251.88
D8: Citi | E8: 1205.2 | F8: 5 | G8: 0.0489 | H8: =E8/F8 -> 241.04
D9: OD | E9: 4242.3
D10: CC | E10: 3106.6
D11: Lease Liab | E11: 3195.5 | H11: 260
E12: =SUM(E6:E11) -> 13809 | H12: =SUM(H6:H11) -> 912.92

Sheet Scenarios
A1: Alkem Laboratories Limited
A2: Revenue Scenarios
D4: Scenarios | E4: Growth % | H4: =[1]Model!L2+1 -> 2026 | I4: =[1]Model!M2+1 -> 2027 | J4: =[1]Model!N2+1 -> 2028 | K4: =[1]Model!O2+1 -> 2029 | L4: =[1]Model!P2+1 -> 2030
D5: Base Case | E5: =AVERAGE(Model!I7:L7) -> 0.10146596 | H5: =E5 -> 0.10146596 | I5: =H5*(1-$E$8) -> 0.091319368 | J5: =I5*(1-$E$8) -> 0.082187431 | K5: =J5*(1-$E$8) -> 0.073968688 | L5: =K5*(1-$E$8) -> 0.066571819
D6: Bull Case | E6: =MAX(Model!I7:L7) -> 0.19956887 | H6: =E6 -> 0.19956887 | I6: =H6*(1-$E$8) -> 0.17961198 | J6: =I6*(1-$E$8) -> 0.16165078 | K6: =J6*(1-$E$8) -> 0.1454857 | L6: =K6*(1-$E$8) -> 0.13093713
D7: Bear Case | E7: =MIN(Model!I7:L7) -> 0.023440941 | H7: =E7 -> 0.023440941 | I7: =H7*(1-$E$8) -> 0.021096847 | J7: =I7*(1-$E$8) -> 0.018987163 | K7: =J7*(1-$E$8) -> 0.017088446 | L7: =K7*(1-$E$8) -> 0.015379602
D8: Annual growth tapering | E8: =10% -> 0.1

Sheet WACC
A1: Alkem Laboratories Limited
A2: Weighted-Average Cost of Capital (WACC)
A3: All Amounts Denominated in INR MM Unless Otherwise Stated
A5: Comparable Companies Beta
H8: Equity | I8: Total | J8: Debt/ | K8: Debt/ | L8: Tax | M8: Levered | N8: Unlevered
D9: Company Name | H9: Value | I9: Debt | J9: Equity | K9: Capital | L9: Rate % | M9: Beta | N9: Beta
D10: Dr. Reddy's Laboratories Limited | H10: =Comps!N8 -> 1134356 | I10: =Comps!L8 -> 46770 | J10: =I10/H10 -> 0.041230443 | K10: =I10/(H10+I10) -> 0.039597808 | L10: 0.3 | M10: 0.26 | N10: =M10/(1+J10*(1+K10)) -> 0.24931365
D11: Zydus Lifesciences Limited | H11: =Comps!N9 -> 1066200 | I11: =Comps!L9 -> 32130 | J11: =I11/H11 -> 0.030135059 | K11: =I11/(H11+I11) -> 0.029253503 | L11: =L10 -> 0.3 | M11: 0.4 | N11: =M11/(1+J11*(1+K11)) -> 0.38796659
D12: Torrent Pharmaceuticals Limited | H12: =Comps!N10 -> 1578482 | I12: =Comps!L10 -> 32020 | J12: =I12/H12 -> 0.020285312 | K12: =I12/(H12+I12) -> 0.019882 | L12: =L11 -> 0.3 | M12: 0.14 | N12: =M12/(1+J12*(1+K12)) -> 0.1371623
D13: Mankind Pharma Limited | H13: =Comps!N11 -> 1043740 | I13: =Comps!L11 -> 85110 | J13: =I13/H13 -> 0.081543296 | K13: =I13/(H13+I13) -> 0.075395314 | L13: =L12 -> 0.3 | M13: 0.45 | N13: =M13/(1+J13*(1+K13)) -> 0.41372033
D14: Lupin Limited | H14: =Comps!N12 -> 1033390 | I14: =Comps!L12 -> 54480 | J14: =I14/H14 -> 0.05271969 | K14: =I14/(H14+I14) -> 0.050079513 | L14: =L13 -> 0.3 | M14: 0.18 | N14: =M14/(1+J14*(1+K14)) -> 0.17055794
D15: Aurobindo Pharma Limited | H15: =Comps!N13 -> 843550 | I15: =Comps!L13 -> 82630 | J15: =I15/H15 -> 0.097955071 | K15: =I15/(H15+I15) -> 0.089215919 | L15: =L14 -> 0.3 | M15: 0.02 | N15: =M15/(1+J15*(1+K15)) -> 0.018071839
D16: Abbott India Limited | H16: =Comps!N14 -> 538403 | I16: =Comps!L14 -> 1970 | J16: =I16/H16 -> 0.0036589692 | K16: =I16/(H16+I16) -> 0.00364563 | L16: =L15 -> 0.3 | M16: 0.02 | N16: =M16/(1+J16*(1+K16)) -> 0.019926823
D17: GlaxoSmithKline Pharmaceuticals Limited | H17: =Comps!N15 -> 339336 | I17: =Comps!L15 -> 100 | J17: =I17/H17 -> 0.00029469317 | K17: =I17/(H17+I17) -> 0.00029460635 | L17: =L16 -> 0.3 | M17: 0.05 | N17: =M17/(1+J17*(1+K17)) -> 0.049985265
D18: Ipca Laboratories Limited | H18: =Comps!N16 -> 416530 | I18: =Comps!L16 -> 13630 | J18: =I18/H18 -> 0.032722733 | K18: =I18/(H18+I18) -> 0.031685884 | L18: =L17 -> 0.3 | M18: 0.05 | N18: =M18/(1+J18*(1+K18)) -> 0.048367145
D19: Gland Pharma Limited | H19: =Comps!N17 -> 376160 | I19: =Comps!L17 -> 3140 | J19: =I19/H19 -> 0.0083475117 | K19: =I19/(H19+I19) -> 0.0082784076 | L19: =L18 -> 0.3 | M19: 0.49 | N19: =M19/(1+J19*(1+K19)) -> 0.48591028
D20: Average | J20: =AVERAGE(J10:J19) -> 0.036889278 | K20: =AVERAGE(K10:K19) -> 0.034732858 | L20: =AVERAGE(L10:L19) -> 0.3 | M20: =AVERAGE(M10:M19) -> 0.206 | N20: =AVERAGE(N10:N19) -> 0.19809822
D21: Median | J21: =MEDIAN(J10:J19) -> 0.031428896 | K21: =MEDIAN(K10:K19) -> 0.030469694 | L21: =MEDIAN(L10:L19) -> 0.3 | M21: =MEDIAN(M10:M19) -> 0.16 | N21: =MEDIAN(N10:N19) -> 0.15386012
D23: Alkem Pharma | H23: =Comps!K23 -> 654960 | I23: =Comps!L23 -> 13810
D25: WACC Calculation
C27: Target Capital Structure
D29: Proportion of Debt | I29: =K20 -> 0.034732858
D30: Proportion of Equity | I30: =1-I29 -> 0.96526714
C32: Current Capital Structure
D33: Market Cap | I33: =H23 -> 654960
D34: Total Debt | I34: =I23 -> 13810
D35: Debt / Equity | I35: =I34/I33 -> 0.021085257
C37: Current Capital Structure
D38: Pre-Tax Cost of Debt | I38: =Model!M11 -> 0.059351402
D39: Tax Rate | I39: =Model!M13 -> 0.13334995
D40: After-Tax Cost of Debt | I40: =I38*(1-I39) -> 0.051436896
C42: Cost of Equity
D43: Risk Free Rate | I43: 0.065
D44: Equity Market Return | I44: =Market_Data!I8 -> 0.13038872
D45: Equity Risk Premium | I45: =I44-I43 -> 0.065388717
D46: Levered Equity Beta | I46: =N21*(1+I35)*(1-I39) -> 0.13615445
D47: Cost of Equity | I47: =I43+I46*I45 -> 0.073902965
D49: WACC | I49: =(I29*I40)+(I47*I30) -> 0.073122654

Sheet Market_Data
A1: Alkem Laboratories Limited
A2: Market Data
E4: Index
D5: Date | E5: Close Price
D6: 46230 | E6: 23995.95 | G6: Periods (yrs) | I6: 9
D7: 46227 | E7: 23767.45
D8: 46226 | E8: 23869.6 | G8: Return's | I8: =_xlfn.RRI(I6,E2622,E6) -> 0.13038872
D9: 46225 | E9: 23996.25
D10: 46224 | E10: 24187.7
D11: 46223 | E11: 24238.5
D12: 46220 | E12: 24334.3
D13: 46219 | E13: 24072.75
D14: 46218 | E14: 24078.5
D15: 46217 | E15: 24052.05
D16: 46216 | E16: 24211
D17: 46213 | E17: 24206.9
D18: 46212 | E18: 23962.8
D19: 46211 | E19: 23882.05
D20: 46210 | E20: 24398.7
... D2622: 42370 | E2622: 7963.2

Sheet Comps
A1: Alkem Laboratories Limited
A2: Comps Valuation
I5: Market Data | P5: Financial Data | T5: Valuation
I6: Price | J6: Shares | K6: Market Cap | L6: Debt | M6: Cash | N6: EV | P6: Sales | Q6: EBITDA | R6: Earnings | T6: EV/Sales | U6: EV/EBITDA | V6: P/E
D7: Company Name | G7: Ticker | I7: (₹/share) | J7: M | K7: ₹ MM | M7: & Equivalents | N7: ₹ MM | P7: ₹ MM | Q7: ₹ MM | R7: ₹ MM | T7: x | U7: x | V7: x
D8: Dr. Reddy's Laboratories Limited | G8: DRREDDY | I8: =Comps_Data!I7 -> 1328 | J8: =Comps_Data!J7 -> 830 | K8: =I8*J8 -> 1102240 | L8: =Comps_Data!K7 -> 46770 | M8: =Comps_Data!L7 -> 14654 | N8: =K8+L8-M8 -> 1134356 | P8: =Comps_Data!M7 -> 325535 | Q8: =Comps_Data!N7 -> 92133 | R8: =Comps_Data!O7 -> 56544 | T8: =N8/P8 -> 3.48459 | U8: =N8/Q8 -> 12.312157 | V8: =K8/R8 -> 19.493492
D9: Zydus Lifesciences Limited | G9: ZYDUSLIFE | I9: =Comps_Data!I8 -> 1104 | J9: =Comps_Data!J8 -> 1010 | K9: =I9*J9 -> 1115040 | L9: =Comps_Data!K8 -> 32130 | M9: =Comps_Data!L8 -> 80970 | N9: =K9+L9-M9 -> 1066200 | P9: =Comps_Data!M8 -> 232420 | Q9: =Comps_Data!N8 -> 70580 | R9: =Comps_Data!O8 -> 46730 | T9: =N9/P9 -> 4.5873849 | U9: =N9/Q9 -> 15.106262 | V9: =K9/R9 -> 23.861331
D10: Torrent Pharmaceuticals Limited | G10: TORNTPHARM | I10: =Comps_Data!I9 -> 4604 | J10: =Comps_Data!J9 -> 338 | K10: =I10*J10 -> 1556152 | L10: =Comps_Data!K9 -> 32020 | M10: =Comps_Data!L9 -> 9690 | N10: =K10+L10-M10 -> 1578482 | P10: =Comps_Data!M9 -> 115160 | Q10: =Comps_Data!N9 -> 37210 | R10: =Comps_Data!O9 -> 19110 | T10: =N10/P10 -> 13.70686 | U10: =N10/Q10 -> 42.420908 | V10: =K10/R10 -> 81.431293
D11: Mankind Pharma Limited | G11: MANKIND | I11: =Comps_Data!I10 -> 2393 | J11: =Comps_Data!J10 -> 410 | K11: =I11*J11 -> 981130 | L11: =Comps_Data!K10 -> 85110 | M11: =Comps_Data!L10 -> 22500 | N11: =K11+L11-M11 -> 1043740 | P11: =Comps_Data!M10 -> 122070 | Q11: =Comps_Data!N10 -> 30260 | R11: =Comps_Data!O10 -> 20110 | T11: =N11/P11 -> 8.55034 | U11: =N11/Q11 -> 34.492399 | V11: =K11/R11 -> 48.788165
D12: Lupin Limited | G12: LUPIN | I12: =Comps_Data!I11 -> 2278 | J12: =Comps_Data!J11 -> 455 | K12: =I12*J12 -> 1036490 | L12: =Comps_Data!K11 -> 54480 | M12: =Comps_Data!L11 -> 57580 | N12: =K12+L12-M12 -> 1033390 | P12: =Comps_Data!M11 -> 227080 | Q12: =Comps_Data!N11 -> 54792 | R12: =Comps_Data!O11 -> 33060 | T12: =N12/P12 -> 4.5507751 | U12: =N12/Q12 -> 18.860235 | V12: =K12/R12 -> 31.351785
D13: Aurobindo Pharma Limited | G13: AUROPHARMA | I13: =Comps_Data!I12 -> 1454 | J13: =Comps_Data!J12 -> 580 | K13: =I13*J13 -> 843320 | L13: =Comps_Data!K12 -> 82630 | M13: =Comps_Data!L12 -> 82400 | N13: =K13+L13-M13 -> 843550 | P13: =Comps_Data!M12 -> 317240 | Q13: =Comps_Data!N12 -> 65510 | R13: =Comps_Data!O12 -> 34840 | T13: =N13/P13 -> 2.6590279 | U13: =N13/Q13 -> 12.87666 | V13: =K13/R13 -> 24.205511
D14: Abbott India Limited | G14: ABBOTINDIA | I14: =Comps_Data!I13 -> 26073 | J14: =Comps_Data!J13 -> 21 | K14: =I14*J14 -> 547533 | L14: =Comps_Data!K13 -> 1970 | M14: =Comps_Data!L13 -> 11100 | N14: =K14+L14-M14 -> 538403 | P14: =Comps_Data!M13 -> 64090 | Q14: =Comps_Data!N13 -> 16950 | R14: =Comps_Data!O13 -> 14140 | T14: =N14/P14 -> 8.4007333 | U14: =N14/Q14 -> 31.764189 | V14: =K14/R14 -> 38.722277
D15: GlaxoSmithKline Pharmaceuticals Limited | G15: GLAXO | I15: =Comps_Data!I14 -> 2174 | J15: =Comps_Data!J14 -> 169 | K15: =I15*J15 -> 367406 | L15: =Comps_Data!K14 -> 100 | M15: =Comps_Data!L14 -> 28170 | N15: =K15+L15-M15 -> 339336 | P15: =Comps_Data!M14 -> 37490 | Q15: =Comps_Data!N14 -> 11790 | R15: =Comps_Data!O14 -> 9280 | T15: =N15/P15 -> 9.0513737 | U15: =N15/Q15 -> 28.781679 | V15: =K15/R15 -> 39.591164
D16: Ipca Laboratories Limited | G16: IPCALAB | I16: =Comps_Data!I15 -> 1656 | J16: =Comps_Data!J15 -> 250 | K16: =I16*J16 -> 414000 | L16: =Comps_Data!K15 -> 13630 | M16: =Comps_Data!L15 -> 11100 | N16: =K16+L16-M16 -> 416530 | P16: =Comps_Data!M15 -> 88970 | Q16: =Comps_Data!N15 -> 17310 | R16: =Comps_Data!O15 -> 7850 | T16: =N16/P16 -> 4.6816905 | U16: =N16/Q16 -> 24.062969 | V16: =K16/R16 -> 52.738854
D17: Gland Pharma Limited | G17: GLAND | I17: =Comps_Data!I16 -> 2522 | J17: =Comps_Data!J16 -> 160 | K17: =I17*J17 -> 403520 | L17: =Comps_Data!K16 -> 3140 | M17: =Comps_Data!L16 -> 30500 | N17: =K17+L17-M17 -> 376160 | P17: =Comps_Data!M16 -> 56160 | Q17: =Comps_Data!N16 -> 12690 | R17: =Comps_Data!O16 -> 6990 | T17: =N17/P17 -> 6.6980057 | U17: =N17/Q17 -> 29.642238 | V17: =K17/R17 -> 57.728183
D20: Average | T20: =AVERAGE(T8:T17) -> 6.6370781 | U20: =AVERAGE(U8:U17) -> 25.03197 | V20: =AVERAGE(V8:V17) -> 41.791205
D21: Median | T21: =MEDIAN(T8:T17) -> 5.6898481 | U21: =MEDIAN(U8:U17) -> 26.422324 | V21: =MEDIAN(V8:V17) -> 39.156721
D23: Alkem Laboratories Limited | H23: ALKEM | I23: =Comps_Data!I5 -> 5458 | J23: =Comps_Data!J5 -> 120 | K23: =I23*J23 -> 654960 | L23: =Comps_Data!K5 -> 13810 | M23: =Comps_Data!L5 -> 18810 | N23: =K23+L23-M23 -> 649960 | P23: =Comps_Data!M5 -> 129650 | Q23: =Comps_Data!N5 -> 25120 | R23: =Comps_Data!O5 -> 22150
D25: Metric | E25: Comps | H25: EV | I25: Net Debt | J25: Equity Value | K25: Shares | L25: Share Price
D26: EV/Revenue | E26: =T21 -> 5.6898481 | H26: =E26*P23 -> 737688.8 | I26: =$L$23-$M$23 -> -5000 | J26: =H26-I26 -> 742688.8 | K26: =J23 -> 120 | L26: =J26/K26 -> 6189.0734
D27: Ev/EBITDA | E27: =U21 -> 26.422324 | H27: =E27*Q23 -> 663728.79 | I27: =$L$23-$M$23 -> -5000 | J27: =H27-I27 -> 668728.79 | K27: =K26 -> 120 | L27: =J27/K27 -> 5572.7399
D28: PE | E28: =V21 -> 39.156721 | H28: =E28*R23 -> 867321.36 | I28: =$L$23-$M$23 -> -5000 | J28: =H28-I28 -> 872321.36 | K28: =K27 -> 120 | L28: =J28/K28 -> 7269.3447

Sheet Comps_Data
A1: Alkem Laboratories Limited
A2: Comps Data
D4: Company | H4: Ticker | I4: Price | J4: Shares | K4: Debt | L4: Cash | M4: Sales | N4: EBITDA | O4: Net Income
D5: Alkem Laboratories Limited | H5: ALKEM | I5: 5458 | J5: 120 | K5: 13810 | L5: 18810 | M5: 129650 | N5: 25120 | O5: 22150
D7: Dr. Reddy's Laboratories Limited | H7: DRREDDY | I7: 1328 | J7: 830 | K7: 46770 | L7: 14654 | M7: 325535 | N7: 92133 | O7: 56544
D8: Zydus Lifesciences Limited | H8: ZYDUSLIFE | I8: 1104 | J8: 1010 | K8: 32130 | L8: 80970 | M8: 232420 | N8: 70580 | O8: 46730
D9: Torrent Pharmaceuticals Limited | H9: TORNTPHARM | I9: 4604 | J9: 338 | K9: 32020 | L9: 9690 | M9: 115160 | N9: 37210 | O9: 19110
D10: Mankind Pharma Limited | H10: MANKIND | I10: 2393 | J10: 410 | K10: 85110 | L10: 22500 | M10: 122070 | N10: 30260 | O10: 20110
D11: Lupin Limited | H11: LUPIN | I11: 2278 | J11: 455 | K11: 54480 | L11: 57580 | M11: 227080 | N11: 54792 | O11: 33060
D12: Aurobindo Pharma Limited | H12: AUROPHARMA | I12: 1454 | J12: 580 | K12: 82630 | L12: 82400 | M12: 317240 | N12: 65510 | O12: 34840
D13: Abbott India Limited | H13: ABBOTINDIA | I13: 26073 | J13: 21 | K13: 1970 | L13: 11100 | M13: 64090 | N13: 16950 | O13: 14140
D14: GlaxoSmithKline Pharmaceuticals Limited | H14: GLAXO | I14: 2174 | J14: 169 | K14: 100 | L14: 28170 | M14: 37490 | N14: 11790 | O14: 9280
D15: Ipca Laboratories Limited | H15: IPCALAB | I15: 1656 | J15: 250 | K15: 13630 | L15: 11100 | M15: 88970 | N15: 17310 | O15: 7850
D16: Gland Pharma Limited | H16: GLAND | I16: 2522 | J16: 160 | K16: 3140 | L16: 30500 | M16: 56160 | N16: 12690 | O16: 6990
C18: Source: www.screener.in

Sheet Foot_Ball Field
A1: Alkem Laboratories Limited
A2: Football Field Chart
A4: Football Field Chart
E6: Comps | F6: DCF | G6: 52-week high/low | H6: Market Consensus
D7: High | E7: =MAX(Comps!L26:L28) -> 7269.3447 | F7: 8152.17 | G7: 4738.5 | H7: =H8 -> 5840
D8: High | E8: =E7 -> 7269.3447 | F8: =F7 -> 8152.17 | G8: =G7 -> 4738.5 | H8: 5840 | I8: ( Motilal Oswal )
D9: Low | E9: =MIN(Comps!L26:L28) -> 5572.7399 | F9: 5606.58 | G9: 5933.5 | H9: 6500 | I9: ( ICICI Securities)
D10: Low | E10: =E9 -> 5572.7399 | F10: =F9 -> 5606.58 | G10: =G9 -> 5933.5 | H10: 6500
A12: Valuation Summary
