Workbook

Sheet Historical_Data
A1: AMBUJA CEMENT
A2: Historical Financial Data | L2: (Rs. In Crore)
C4: Income | H4: 2022 | I4: 2023 | J4: =I4+1 -> 2024 | K4: =J4+1 -> 2025 | L4: =K4+1 -> 2026
D5: Revenue from operations | H5: 28965.46 | I5: 38937.03 | J5: 33159.64 | K5: 33697.7 | L5: 40446.04
D6: Government grants / duty credits | H6: 0 | I6: 0 | J6: 0 | K6: 1347.06 | L6: 209.64
D7: Other income | H7: 352.44 | I7: 737.71 | J7: 1166.4 | K7: 2654.25 | L7: 834.34
D8: Total Income | H8: =H5+H6+H7 -> 29317.9 | I8: =I5+I6+I7 -> 39674.74 | J8: =J5+J6+J7 -> 34326.04 | K8: =K5+K6+K7 -> 37699.01 | L8: =L5+L6+L7 -> 41490.02
C10: Expenses
D11: Cost of materials consumed | H11: 3183.41 | I11: 4749.65 | J11: 4321.96 | K11: 5708.07 | L11: 6511.54
D12: Purchase of stock-in-trade | H12: 309.21 | I12: 481.12 | J12: 576.83 | K12: 763.66 | L12: 609.25
D13: Changes in inventories | H13: -530.34 | I13: -119.86 | J13: 23.99 | K13: 55.69 | L13: -378.29
D14: Employee benefits expense | H14: 1529.15 | I14: 1856.53 | J14: 1352.79 | K14: 1403.41 | L14: 1602.65
D15: Finance costs | H15: 145.66 | I15: 194.9 | J15: 276.38 | K15: 215.94 | L15: 223.61
D16: Depreciation and amortisation | H16: 1152.49 | I16: 1644.67 | J16: 1623.38 | K16: 2478.34 | L16: 3570.41
D17: Power and fuel | H17: 6787.52 | I17: 11761.9 | J17: 8109.31 | K17: 8347.84 | L17: 10023.78
D18: Freight and forwarding expense | H18: 7132.9 | I18: 9523.72 | J18: 8000.64 | K18: 8301.19 | L18: 9497.28
D19: Other expenses | H19: 4387.84 | I19: 5608.5 | J19: 4388.97 | K19: 4515.13 | L19: 6263.32
D20: Captive consumption of cement (credit) | H20: -44.63 | I20: -46.9 | J20: -14.36 | K20: -20.88 | L20: -12.79
D21: Total Expenses | H21: =SUM(H11:H20) -> 24053.21 | I21: =SUM(I11:I20) -> 35654.23 | J21: =SUM(J11:J20) -> 28659.89 | K21: =SUM(K11:K20) -> 31768.39 | L21: =SUM(L11:L20) -> 37910.76
D23: Profit before share of JV/associates, exceptional items & tax | H23: =H8-H21 -> 5264.69 | I23: =I8-I21 -> 4020.51 | J23: =J8-J21 -> 5666.15 | K23: =K8-K21 -> 5930.62 | L23: =L8-L21 -> 3579.26
D24: Share of profit of JV and associates | H24: 20.23 | I24: 28.02 | J24: 22.9 | K24: 13.22 | L24: 20.05
D25: Profit before exceptional items and tax | H25: =H23+H24 -> 5284.92 | I25: =I23+I24 -> 4048.53 | J25: =J23+J24 -> 5689.05 | K25: =K23+K24 -> 5943.84 | L25: =L23+L24 -> 3599.31
D26: Exceptional items (expense / (income)) | H26: 120.45 | I26: 319.04 | J26: -211.57 | K26: 21.47 | L26: 300.54
D27: Profit before tax | H27: =H25-H26 -> 5164.47 | I27: =I25-I26 -> 3729.49 | J27: =J25-J26 -> 5900.62 | K27: =K25-K26 -> 5922.37 | L27: =L25-L26 -> 3298.77
D28: Total tax expense / (credit) | H28: 1453.43 | I28: 705.11 | J28: 1162.61 | K28: 763.96 | L28: -2338.31
D29: Profit after tax (PAT) | H29: =H27-H28 -> 3711.04 | I29: =I27-I28 -> 3024.38 | J29: =J27-J28 -> 4738.01 | K29: =K27-K28 -> 5158.41 | L29: =L27-L28 -> 5637.08
B31: Balance Sheet
C33: ASSETS
D34: Non-current assets
D35: Property, plant and equipment | H35: 13661.89 | I35: 14729.35 | J35: 19956.67 | K35: 24656.29 | L35: 33801.18
D36: Right-of-use assets | H36: 497.87 | I36: 588.15 | J36: 758.34 | K36: 1464.76 | L36: 1483
D37: Capital work-in-progress | H37: 2196.38 | I37: 2525.87 | J37: 2658.45 | K37: 9820.4 | L37: 9084.7
D38: Goodwill | H38: 7869.69 | I38: 7869.69 | J38: 8219.27 | K38: 10856.07 | L38: 13545.52
D39: Other intangible assets | H39: 224.11 | I39: 364.3 | J39: 3454.19 | K39: 5600.63 | L39: 9433.12
D40: Other intangible assets under development | H40: 0 | I40: 0 | J40: 0 | K40: 65.31 | L40: 36.24
D41: Investments in associates and joint ventures | H41: 170.51 | I41: 186.05 | J41: 62.26 | K41: 60.39 | L41: 73.56
C42: Financial assets
D43: Investments | H43: 27.6 | I43: 27.6 | J43: 27.6 | K43: 28.96 | L43: 39.61
D44: Loans | H44: 11.56 | I44: 9.89 | J44: 11.58 | K44: 4.95 | L44: 5.04
D45: Other financial assets | H45: 1255.12 | I45: 3133.72 | J45: 1167.39 | K45: 3721.7 | L45: 3769.07
D46: Non-current tax assets (net) | H46: 1125.86 | I46: 1128.08 | J46: 1250.36 | K46: 1748.48 | L46: 1534.83
D47: Deferred tax assets (net) | H47: 2.91 | I47: 0 | J47: 36.94 | K47: 4.37 | L47: 32.66
D48: Other non-current assets | H48: 1141.36 | I48: 1909.39 | J48: 2842.6 | K48: 3195.95 | L48: 3052.14
C50: Current assets
D51: Inventories | H51: 2738.04 | I51: 3272.79 | J51: 3608.55 | K51: 4248.01 | L51: 4552.33
C52: Financial assets
D53: Cash and cash equivalents | H53: 11358.49 | I53: 543.87 | J53: 3007.1 | K53: 5043.32 | L53: 891.59
D54: Bank balances other than cash & cash equivalents | H54: 335.8 | I54: 2417.17 | J54: 8061.77 | K54: 1128.84 | L54: 67.01
D55: Trade receivables | H55: 645.83 | I55: 1154.36 | J55: 1213.14 | K55: 1590.3 | L55: 1868.47
D56: Loans | H56: 9.91 | I56: 8.61 | J56: 6.24 | K56: 7.7 | L56: 10.02
D57: Investments | H57: 0 | I57: 0 | J57: 758.69 | K57: 1822.16 | L57: 0
D58: Other financial assets | H58: 474.25 | I58: 7901.58 | J58: 5715 | K58: 1888.24 | L58: 1794.45
D59: Current tax assets (net) | H59: 0 | I59: 0 | J59: 0 | K59: 16.18 | L59: 0
D60: Other current assets | H60: 1434.66 | I60: 3948.86 | J60: 2459.74 | K60: 3965.63 | L60: 4532.06
D61: Non-current assets classified as held for sale | H61: 25.44 | I61: 2.13 | J61: 21.93 | K61: 6.77 | L61: 0
D62: Total Current assets | H62: =SUM(H51:H61) -> 17022.42 | I62: =SUM(I51:I61) -> 19249.37 | J62: =SUM(J51:J61) -> 24852.16 | K62: =SUM(K51:K61) -> 19717.15 | L62: =SUM(L51:L61) -> 13715.93
D63: TOTAL ASSETS | H63: =SUM(H35:H61) -> 45207.28 | I63: =SUM(I35:I61) -> 51721.46 | J63: =SUM(J35:J61) -> 65297.81 | K63: =SUM(K35:K61) -> 80945.41 | L63: =SUM(L35:L61) -> 89606.6
C65: EQUITY AND LIABILITIES
D67: Equity
D68: Equity share capital | H68: 397.13 | I68: 397.13 | J68: 439.54 | K68: 492.62 | L68: 494.36
D69: Other equity | H69: 24956.61 | I69: 26301.04 | J69: 38235.87 | K69: 52950.63 | L69: 58852.96
D70: Money received against share warrants | H70: 0 | I70: 5000.03 | J70: 2779.65 | K70: 0 | L70: 0
D71: Equity attributable to owners of the Company | H71: =SUM(H68:H70) -> 25353.74 | I71: =SUM(I68:I70) -> 31698.2 | J71: =SUM(J68:J70) -> 41455.06 | K71: =SUM(K68:K70) -> 53443.25 | L71: =SUM(L68:L70) -> 59347.32
D72: Non-controlling interest | H72: 7145.03 | I72: 7058.35 | J72: 9390.84 | K72: 10368.17 | L72: 12498.92
D73: Total Equity | H73: 32498.77 | I73: 38756.55 | J73: 50845.9 | K73: 63811.42 | L73: 71846.24
C75: Non-current liabilities
C76: Financial liabilities
D77: Borrowings | H77: 43.5 | I77: 34.22 | J77: 18.91 | K77: 14.39 | L77: 44.79
D78: Lease liabilities | H78: 362.52 | I78: 414.5 | J78: 499.05 | K78: 457.54 | L78: 621.63
D79: Other financial liabilities | H79: 0.13 | I79: 0 | J79: 0 | K79: 0 | L79: 142.38
D80: Provisions | H80: 281.54 | I80: 264.88 | J80: 255.97 | K80: 254.08 | L80: 236.45
D81: Deferred tax liabilities (net) | H81: 756.19 | I81: 700.37 | J81: 1549.1 | K81: 2407.57 | L81: 3466.33
D82: Other non-current liabilities | H82: 36.74 | I82: 37.27 | J82: 0 | K82: 155.15 | L82: 152.54
D83: Total Non-current liabilities | H83: 1480.62 | I83: 1451.24 | J83: 2323.03 | K83: 3288.73 | L83: 4664.12
C85: Current liabilities
D86: Borrowings | I86: 13.49 | J86: 17.87 | K86: 12.43 | L86: 7.99
C87: Financial liabilities
D88: Trade payables — dues to micro & small enterprises | H88: 34.95 | I88: 51.22 | J88: 717.42 | K88: 472.59 | L88: 771.19
D89: Trade payables — dues to others | H89: 2877.87 | I89: 2722.69 | J89: 2391.33 | K89: 2286.87 | L89: 3413.84
D90: Lease liabilities (current) | H90: 67.11 | I90: 60.52 | J90: 163.18 | K90: 304.14 | L90: 191.52
D91: Other financial liabilities | H91: 2008.86 | I91: 2121.13 | J91: 2389.52 | K91: 4935.99 | L91: 5394.5
D92: Other current liabilities | H92: 4305.87 | I92: 4732.7 | J92: 3751.65 | K92: 3057.19 | L92: 2495.17
D93: Provisions | H93: 24.64 | I93: 14.64 | J93: 42.97 | K93: 55.09 | L93: 259.04
D94: Current tax liabilities (net) | H94: 1908.59 | I94: 1797.28 | J94: 2654.94 | K94: 2720.96 | L94: 562.99
D95: Total Current liabilities | H95: 11227.89 | I95: 11513.67 | J95: 12128.88 | K95: 13845.26 | L95: 13096.24
D96: Total Liabilities | H96: =H83+H95 -> 12708.51 | I96: =I83+I95 -> 12964.91 | J96: =J83+J95 -> 14451.91 | K96: =K83+K95 -> 17133.99 | L96: =L83+L95 -> 17760.36
D97: TOTAL EQUITY AND LIABILITIES | H97: =SUM(H77:H82,H86:H94)+H73 -> 45207.28 | I97: =I73+I96 -> 51721.46 | J97: =J73+J96 -> 65297.81 | K97: =K73+K96 -> 80945.41 | L97: =L73+L96 -> 89606.6
B99: Cash Flow Statement
C101: A) Cash flows from Operating activities
D102: Profit before tax | H102: 5164.47 | I102: 3729.49 | J102: 5900.62 | K102: 5922.37 | L102: 3298.77
D103: Adjustments to reconcile profit before tax to net cash flows
D104: Depreciation and amortisation expense (net) | H104: 1152.49 | I104: 1644.67 | J104: 1623.38 | K104: 2478.34 | L104: 3570.41
D105: (Profit)/Loss on sale or write-off of PP&E and other intangible assets (net) | H105: 25.27 | I105: -96.09 | J105: -115.81 | K105: -35.79 | L105: 37.94
D106: Exceptional items (net) | H106: 113.11 | I106: 0 | J106: -211.57 | K106: 21.47 | L106: 300.54
D107: Provision for restructuring cost | H107: 0 | I107: 147.13 | J107: 0 | K107: 0 | L107: 0
D108: Impairment of goodwill in subsidiary company | H108: 6.42 | I108: 0 | J108: 0 | K108: 0 | L108: 0
D109: Expected credit loss on non-current financial assets | H109: 0 | I109: 0 | J109: 0 | K109: 0 | L109: 0
D110: Loss on buy-back of shares in joint venture | H110: 0 | I110: 0 | J110: 0 | K110: 0 | L110: 0
D111: Gain on finance lease of asset (net) | H111: 0 | I111: 0 | J111: 0 | K111: 0 | L111: -122.94
D112: Gain on sale of current financial assets measured at FVTPL | H112: -17.8 | I112: -52.25 | J112: -46.31 | K112: -116.72 | L112: -67.2
...

Sheet Model
A1: AMBUJA CEMENT | H1: Historical Period | M1: Forecasted Period
A2: Financial Statement Analysis & Valuation | H2: 2022 | I2: =H2+1 -> 2023 | J2: =I2+1 -> 2024 | K2: =J2+1 -> 2025 | L2: =K2+1 -> 2026 | M2: =L2+1 -> 2027 | N2: =M2+1 -> 2028 | O2: =N2+1 -> 2029 | P2: =O2+1 -> 2030 | Q2: =P2+1 -> 2031
A4: Ratios & Assumptions
C6: LIVE SCENARIO | E6: Bull Case | G6: =IF(E6=Scenario!D5,1,IF(E6=Scenario!D6,2,3)) -> 1
D7: Revenue Growth % | I7: =I22/H22-1 -> 0.34425726 | J7: =J22/I22-1 -> -0.14837778 | K7: =K22/J22-1 -> 0.016226352 | L7: =L22/K22-1 -> 0.20026115 | M7: {=CHOOSE(G6,Scenario!H5:L5,Scenario!H6:L6,Scenario!H7:L7)} -> 0.34425726 | N7: 0.30983154 | O7: 0.27884838 | P7: 0.25096355 | Q7: 0.22586719
D8: COGS as % of Revenue | H8: =H23/-H22 -> 0.10226939 | I8: =I23/-I22 -> 0.13126091 | J8: =J23/-J22 -> 0.14845698 | K8: =K23/-K22 -> 0.19370521 | L8: =L23/-L22 -> 0.16670359 | M8: =AVERAGE(H8:L8) -> 0.14847922 | N8: =M8 -> 0.14847922 | O8: =N8 -> 0.14847922 | P8: =O8 -> 0.14847922 | Q8: =P8 -> 0.14847922
D9: Operating Expense | H9: =H25/-H22 -> 0.68332352 | I9: =I25/-I22 -> 0.73718386 | J9: =J25/-J22 -> 0.65855208 | K9: =K25/-K22 -> 0.66908691 | L9: =L25/-L22 -> 0.6768089 | M9: =AVERAGE(H9:L9) -> 0.68499105 | N9: =M9 -> 0.68499105 | O9: =N9 -> 0.68499105 | P9: =O9 -> 0.68499105 | Q9: =P9 -> 0.68499105
D10: Interest as % of Debt | H10: =H29/-H57 -> 0.30786465 | I10: =I29/-I57 -> 0.37285023 | J10: =J29/-J57 -> 0.39538776 | K10: =K29/-K57 -> 0.27386176 | L10: =L29/-L57 -> 0.25823103 | M10: =AVERAGE(H10:L10) -> 0.32163909 | N10: =M10 -> 0.32163909 | O10: =N10 -> 0.32163909 | P10: =O10 -> 0.32163909 | Q10: =P10 -> 0.32163909
D11: Taxes as % PBT | H11: =H32/-H31 -> 0.27607134 | I11: =I32/-I31 -> 0.17537825 | J11: =J32/-J31 -> 0.20518518 | K11: =K32/-K31 -> 0.12881621 | L11: =L32/-L31 -> -0.65329426 | M11: =AVERAGE(H11:L11) -> 0.026431343 | N11: =M11 -> 0.026431343 | O11: =N11 -> 0.026431343 | P11: =O11 -> 0.026431343 | Q11: =P11 -> 0.026431343
D12: Other Income as % of Revenue | H12: =H30/H22 -> 0.012167595 | I12: =I30/I22 -> 0.018946232 | J12: =J30/J22 -> 0.035175291 | K12: =K30/K22 -> 0.11874134 | L12: =L30/L22 -> 0.025811674 | M12: =AVERAGE(H12:L12) -> 0.042168426 | N12: =M12 -> 0.042168426 | O12: =N12 -> 0.042168426 | P12: =O12 -> 0.042168426 | Q12: =P12 -> 0.042168426
D13: Depreciation & Amortization as % of PPE | H13: =H27/-H38 -> 0.072674384 | I13: =I27/-I38 -> 0.095314345 | J13: =J27/-J38 -> 0.071782949 | K13: =K27/-K38 -> 0.071884511 | L13: =L27/-L38 -> 0.083253742 | M13: =AVERAGE(H13:L13) -> 0.078981986 | N13: =M13 -> 0.078981986 | O13: =N13 -> 0.078981986 | P13: =O13 -> 0.078981986 | Q13: =P13 -> 0.078981986
D14: Dividend Payout Ratio | H14: =H90/-H33 -> 0.08748288 | I14: =I90/-I33 -> 0.54155758 | J14: =J90/-J33 -> 0.12985562 | K14: =K90/-K33 -> 0.10896401 | L14: =L90/-L33 -> 0.095471621 | M14: =AVERAGE(H14:L14) -> 0.19266634 | N14: =M14 -> 0.19266634 | O14: =N14 -> 0.19266634 | P14: =O14 -> 0.19266634 | Q14: =P14 -> 0.19266634
D15: Day Payable Outstanding | H15: =H53/H22*365 -> 36.705072 | I15: =I53/I22*365 -> 26.002937 | J15: =J53/J22*365 -> 34.219121 | K15: =K53/K22*365 -> 29.889366 | L15: =L53/L22*365 -> 37.767256 | M15: =AVERAGE(H15:L15) -> 32.916751 | N15: =M15 -> 32.916751 | O15: =N15 -> 32.916751 | P15: =O15 -> 32.916751 | Q15: =P15 -> 32.916751
D16: Day Inventory Outstanding | H16: =H47/-H23*365 -> 337.37007 | I16: =I47/-I23*365 -> 233.72909 | J16: =J47/-J23*365 -> 267.55629 | K16: =K47/-K23*365 -> 237.54005 | L16: =L47/-L23*365 -> 246.43685 | M16: =AVERAGE(H16:L16) -> 264.52647 | N16: =M16 -> 264.52647 | O16: =N16 -> 264.52647 | P16: =O16 -> 264.52647 | Q16: =P16 -> 264.52647
D17: Day Receivable Outstanding | H17: =H46/H22*365 -> 8.1382429 | I17: =I46/I22*365 -> 10.821098 | J17: =J46/J22*365 -> 13.353465 | K17: =K46/K22*365 -> 17.225493 | L17: =L46/L22*365 -> 16.861763 | M17: =AVERAGE(H17:L17) -> 13.280012 | N17: =M17 -> 13.280012 | O17: =N17 -> 13.280012 | P17: =O17 -> 13.280012 | Q17: =P17 -> 13.280012
D18: Capital Assest Turnover Ratio | H18: =H22/(H38+H39) -> 1.801068 | I18: =I22/(I38+I39) -> 2.2098803 | J18: =J22/(J38+J39) -> 1.27198 | K18: =K22/(K38+K39) -> 0.83944923 | L18: =L22/(L38+L39) -> 0.77253089 | M18: =AVERAGE(H18:L18) -> 1.3789817 | N18: =M18 -> 1.3789817 | O18: =N18 -> 1.3789817 | P18: =O18 -> 1.3789817 | Q18: =P18 -> 1.3789817
A20: INCOME STATEMNET
D22: Revenue | H22: =Historical_Data!H5 -> 28965.46 | I22: =Historical_Data!I5 -> 38937.03 | J22: =Historical_Data!J5 -> 33159.64 | K22: =Historical_Data!K5 -> 33697.7 | L22: =Historical_Data!L5 -> 40446.04 | M22: =L22*(1+M7) -> 54369.883 | N22: =M22*(1+N7) -> 71215.388 | O22: =N22*(1+O7) -> 91073.683 | P22: =O22*(1+P7) -> 113929.86 | Q22: =P22*(1+Q7) -> 139662.87
D23: Less: Cost of Good Sold | H23: =-SUM(Historical_Data!H11:H13) -> -2962.28 | I23: =-SUM(Historical_Data!I11:I13) -> -5110.91 | J23: =-SUM(Historical_Data!J11:J13) -> -4922.78 | K23: =-SUM(Historical_Data!K11:K13) -> -6527.42 | L23: =-SUM(Historical_Data!L11:L13) -> -6742.5 | M23: =-M22*M8 -> -8072.7976 | N23: =-N22*N8 -> -10574.005 | O23: =-O22*O8 -> -13522.549 | P23: =-P22*P8 -> -16916.216 | Q23: =-Q22*Q8 -> -20737.034
D24: Gross Profit | H24: =SUM(H22:H23) -> 26003.18 | I24: =SUM(I22:I23) -> 33826.12 | J24: =SUM(J22:J23) -> 28236.86 | K24: =SUM(K22:K23) -> 27170.28 | L24: =SUM(L22:L23) -> 33703.54 | M24: =SUM(M22:M23) -> 46297.085 | N24: =SUM(N22:N23) -> 60641.383 | O24: =SUM(O22:O23) -> 77551.134 | ... Q24: =SUM(Q22:Q23) -> 118925.84
D25: Less: Operating Expense | H25: =-SUM(Historical_Data!H17:H20,Historical_Data!H14) -> -19792.78 | I25: =-SUM(Historical_Data!I17:I20,Historical_Data!I14) -> -28703.75 | J25: =-SUM(Historical_Data!J17:J20,Historical_Data!J14) -> -21837.35 | K25: =-SUM(Historical_Data!K17:K20,Historical_Data!K14) -> -22546.69 | L25: =-SUM(Historical_Data!L17:L20,Historical_Data!L14) -> -27374.24 | M25: =-M22*M9 -> -37242.884 | N25: =-N22*N9 -> -48781.903 | O25: =-O22*O9 -> -62384.658 | P25: =-P22*P9 -> -78040.933 | Q25: =-Q22*Q9 -> -95667.82
D26: EBITDA | H26: =SUM(H24:H25) -> 6210.4 | I26: =SUM(I24:I25) -> 5122.37 | J26: =SUM(J24:J25) -> 6399.51 | K26: =SUM(K24:K25) -> 4623.59 | L26: =SUM(L24:L25) -> 6329.3 | M26: =SUM(M24:M25) -> 9054.2019 | N26: =SUM(N24:N25) -> 11859.479 | O26: =SUM(O24:O25) -> 15166.476 | ... Q26: =SUM(Q24:Q25) -> 23258.021
D27: Less: Depreciation & Amortization | H27: =-Historical_Data!H16 -> -1152.49 | I27: =-Historical_Data!I16 -> -1644.67 | J27: =-Historical_Data!J16 -> -1623.38 | K27: =-Historical_Data!K16 -> -2478.34 | L27: =-Historical_Data!L16 -> -3570.41 | M27: =M110 -> -4135.1208 | N27: =N110 -> -4606.0171 | O27: =O110 -> -5207.0609 | P27: =P110 -> -5933.1924 | Q27: =Q110 -> -6773.6779
D28: EBIT | H28: =SUM(H26:H27) -> 5057.91 | I28: =SUM(I26:I27) -> 3477.7 | J28: =SUM(J26:J27) -> 4776.13 | K28: =SUM(K26:K27) -> 2145.25 | L28: =SUM(L26:L27) -> 2758.89 | M28: =SUM(M26:M27) -> 4919.0811 | N28: =SUM(N26:N27) -> 7253.4621 | O28: =SUM(O26:O27) -> 9959.415 | ... Q28: =SUM(Q26:Q27) -> 16484.343
D29: Less: Interest | H29: =-Historical_Data!H15 -> -145.66 | I29: =-Historical_Data!I15 -> -194.9 | J29: =-Historical_Data!J15 -> -276.38 | K29: =-Historical_Data!K15 -> -215.94 | L29: =-Historical_Data!L15 -> -223.61 | M29: =M117 -> -278.51693 | N29: =N117 -> -173.54439 | O29: =O117 -> -68.571845 | P29: =P117 -> 0 | Q29: =Q117 -> 0
D30: Other Income | H30: =SUM(Historical_Data!H6:H7) -> 352.44 | I30: =SUM(Historical_Data!I6:I7) -> 737.71 | J30: =SUM(Historical_Data!J6:J7) -> 1166.4 | K30: =SUM(Historical_Data!K6:K7) -> 4001.31 | L30: =SUM(Historical_Data!L6:L7) -> 1043.98 | M30: =M22*M12 -> 2292.6924 | N30: =N22*N12 -> 3003.0408 | O30: =O22*O12 -> 3840.4339 | P30: =P22*P12 -> 4804.2428 | Q30: =Q22*Q12 -> 5889.3636
D31: Profit Before Tax | H31: =SUM(H28:H30) -> 5264.69 | I31: =SUM(I28:I30) -> 4020.51 | J31: =SUM(J28:J30) -> 5666.15 | K31: =SUM(K28:K30) -> 5930.62 | L31: =SUM(L28:L30) -> 3579.26 | M31: =SUM(M28:M30) -> 6933.2565 | N31: =SUM(N28:N30) -> 10082.959 | O31: =SUM(O28:O30) -> 13731.277 | ... Q31: =SUM(Q28:Q30) -> 22373.706
D32: Less: Taxes | H32: =-SUM(Historical_Data!H28) -> -1453.43 | I32: =-SUM(Historical_Data!I28) -> -705.11 | J32: =-SUM(Historical_Data!J28) -> -1162.61 | K32: =-SUM(Historical_Data!K28) -> -763.96 | L32: =-SUM(Historical_Data!L28) -> 2338.31 | M32: =-M31*M11 -> -183.25529 | N32: =-N31*N11 -> -266.50614 | O32: =-O31*O11 -> -362.9361 | P32: =-P31*P11 -> -471.63452 | Q32: =-Q31*Q11 -> -591.36712
D33: Profit After Tax | H33: =SUM(H31:H32) -> 3811.26 | I33: =SUM(I31:I32) -> 3315.4 | J33: =SUM(J31:J32) -> 4503.54 | K33: =SUM(K31:K32) -> 5166.66 | L33: =SUM(L31:L32) -> 5917.57 | M33: =SUM(M31:M32) -> 6750.0013 | N33: =SUM(N31:N32) -> 9816.4524 | O33: =SUM(O31:O32) -> 13368.341 | ... Q33: =SUM(Q31:Q32) -> 21782.339
A35: BALANCE SHEET
C37: Non-current assets
D38: Property, Plant and equipment | H38: =SUM(Historical_Data!H35,Historical_Data!H37) -> 15858.27 | I38: =SUM(Historical_Data!I35,Historical_Data!I37) -> 17255.22 | J38: =SUM(Historical_Data!J35,Historical_Data!J37) -> 22615.12 | K38: =SUM(Historical_Data!K35,Historical_Data!K37) -> 34476.69 | L38: =SUM(Historical_Data!L35,Historical_Data!L37) -> 42885.88 | M38: =M111-M39 -> 48847.951 | N38: =N111-N39 -> 56457.836 | O38: =O111-O39 -> 65651.471 | P38: =P111-P39 -> 76292.954 | Q38: =Q111-Q39 -> 88180.16
D39: Intangible Assets | H39: =SUM(Historical_Data!H39:H40) -> 224.11 | I39: =SUM(Historical_Data!I39:I40) -> 364.3 | J39: =SUM(Historical_Data!J39:J40) -> 3454.19 | K39: =SUM(Historical_Data!K39:K40) -> 5665.94 | L39: =SUM(Historical_Data!L39:L40) -> 9469.36 | M39: =L39 -> 9469.36 | N39: =M39 -> 9469.36 | O39: =N39 -> 9469.36 | P39: =O39 -> 9469.36 | Q39: =P39 -> 9469.36
D40: Goodwill | H40: =Historical_Data!H38 -> 7869.69 | I40: =Historical_Data!I38 -> 7869.69 | J40: =Historical_Data!J38 -> 8219.27 | K40: =Historical_Data!K38 -> 10856.07 | L40: =Historical_Data!L38 -> 13545.52 | M40: =L40 -> 13545.52 | N40: =M40 -> 13545.52 | O40: =N40 -> 13545.52 | P40: =O40 -> 13545.52 | Q40: =P40 -> 13545.52
D41: Financial Asset | H41: =SUM(Historical_Data!H43:H45) -> 1294.28 | I41: =SUM(Historical_Data!I43:I45) -> 3171.21 | J41: =SUM(Historical_Data!J43:J45) -> 1206.57 | K41: =SUM(Historical_Data!K43:K45) -> 3755.61 | L41: =SUM(Historical_Data!L43:L45) -> 3813.72 | M41: =L41 -> 3813.72 | N41: =M41 -> 3813.72 | O41: =N41 -> 3813.72 | P41: =O41 -> 3813.72 | Q41: =P41 -> 3813.72
D42: Other Intangible Assets | H42: =SUM(Historical_Data!H46:H48,Historical_Data!H41,Historical_Data!H36) -> 2938.51 | I42: =SUM(Historical_Data!I46:I48,Historical_Data!I41,Historical_Data!I36) -> 3811.67 | J42: =SUM(Historical_Data!J46:J48,Historical_Data!J41,Historical_Data!J36) -> 4950.5 | K42: =SUM(Historical_Data!K46:K48,Historical_Data!K41,Historical_Data!K36) -> 6473.95 | L42: =SUM(Historical_Data!L46:L48,Historical_Data!L41,Historical_Data!L36) -> 6176.19 | M42: =L42 -> 6176.19 | N42: =M42 -> 6176.19 | O42: =N42 -> 6176.19 | P42: =O42 -> 6176.19 | Q42: =P42 -> 6176.19
C44: Current Assets
D45: Cash and cash equivalents | H45: =Historical_Data!H53 -> 11358.49 | I45: =Historical_Data!I53 -> 543.87 | J45: =Historical_Data!J53 -> 3007.1 | K45: =Historical_Data!K53 -> 5043.32 | L45: =Historical_Data!L53 -> 891.59 | M45: =M96 -> -4812.3184 | N45: =N96 -> -7023.452 | O45: =O96 -> -8231.077 | P45: =P96 -> -7832.4915 | Q45: =Q96 -> -5494.8308
D46: Trade receivables | H46: =Historical_Data!H55 -> 645.83 | I46: =Historical_Data!I55 -> 1154.36 | J46: =Historical_Data!J55 -> 1213.14 | K46: =Historical_Data!K55 -> 1590.3 | L46: =Historical_Data!L55 -> 1868.47 | M46: =M22/365*M17 -> 1978.1718 | N46: =N22/365*N17 -> 2591.0719 | O46: =O22/365*O17 -> 3313.5881 | P46: =P22/365*P17 -> 4145.1779 | Q46: =Q22/365*Q17 -> 5081.4376
D47: Inventories | H47: =Historical_Data!H51 -> 2738.04 | I47: =Historical_Data!I51 -> 3272.79 | J47: =Historical_Data!J51 -> 3608.55 | K47: =Historical_Data!K51 -> 4248.01 | L47: =Historical_Data!L51 -> 4552.33 | M47: =-M23/365*M16 -> 5850.599 | N47: =-N23/365*N16 -> 7663.2991 | O47: =-O23/365*O16 -> 9800.1977 | P47: =-P23/365*P16 -> 12259.69 | Q47: =-Q23/365*Q16 -> 15028.752
D48: Other Current Assets | H48: =SUM(Historical_Data!H56:H61,Historical_Data!H54) -> 2280.06 | I48: =SUM(Historical_Data!I56:I61,Historical_Data!I54) -> 14278.35 | J48: =SUM(Historical_Data!J56:J61,Historical_Data!J54) -> 17023.37 | K48: =SUM(Historical_Data!K56:K61,Historical_Data!K54) -> 8835.52 | L48: =SUM(Historical_Data!L56:L61,Historical_Data!L54) -> 6403.54 | M48: =L48 -> 6403.54 | N48: =M48 -> 6403.54 | O48: =N48 -> 6403.54 | P48: =O48 -> 6403.54 | Q48: =P48 -> 6403.54
D49: TOTAL ASSETS | H49: =SUM(H38:H48) -> 45207.28 | I49: =SUM(I38:I48) -> 51721.46 | J49: =SUM(J38:J48) -> 65297.81 | K49: =SUM(K38:K48) -> 80945.41 | L49: =SUM(L38:L48) -> 89606.6 | M49: =SUM(M38:M48) -> 91272.734 | N49: =SUM(N38:N48) -> 99097.085 | O49: =SUM(O38:O48) -> 109942.51 | ... Q49: =SUM(Q38:Q48) -> 142203.85
C52: Current Liabilities
D53: Trade Payable | H53: =SUM(Historical_Data!H88:H89) -> 2912.82 | I53: =SUM(Historical_Data!I88:I89) -> 2773.91 | J53: =SUM(Historical_Data!J88:J89) -> 3108.75 | K53: =SUM(Historical_Data!K88:K89) -> 2759.46 | L53: =SUM(Historical_Data!L88:L89) -> 4185.03 | M53: =-M23/365*M15 -> 728.02813 | N53: =-N23/365*N15 -> 953.5942 | O53: =-O23/365*O15 -> 1219.5024 | P53: =-P23/365*P15 -> 1525.553 | Q53: =-Q23/365*Q15 -> 1870.1254
D54: Other Current Liability | H54: =SUM(Historical_Data!H91:H94) -> 8247.96 | I54: =SUM(Historical_Data!I91:I94) -> 8665.75 | J54: =SUM(Historical_Data!J91:J94) -> 8839.08 | K54: =SUM(Historical_Data!K91:K94) -> 10769.23 | L54: =SUM(Historical_Data!L91:L94) -> 8711.7 | M54: =L54 -> 8711.7 | N54: =M54 -> 8711.7 | O54: =N54 -> 8711.7 | P54: =O54 -> 8711.7 | Q54: =P54 -> 8711.7
C56: Non-current Liabilities
D57: Debt | H57: =SUM(Historical_Data!H77,Historical_Data!H78)+Historical_Data!H90+Historical_Data!H86 -> 473.13 | I57: =SUM(Historical_Data!I77,Historical_Data!I78)+Historical_Data!I90+Historical_Data!I86 -> 522.73 | J57: =SUM(Historical_Data!J77,Historical_Data!J78)+Historical_Data!J90+Historical_Data!J86 -> 699.01 | K57: =SUM(Historical_Data!K77,Historical_Data!K78)+Historical_Data!K90+Historical_Data!K86 -> 788.5 | L57: =SUM(Historical_Data!L77,Historical_Data!L78)+Historical_Data!L90+Historical_Data!L86 -> 865.93 | M57: =M116 -> 539.5625 | N57: =N116 -> 213.195 | O57: =O116 -> 0 | P57: =P116 -> 0 | Q57: =Q116 -> 0
D58: Other Non-Current Liability | H58: =SUM(Historical_Data!H79:H82) -> 1074.6 | I58: =SUM(Historical_Data!I79:I82) -> 1002.52 | J58: =SUM(Historical_Data!J79:J82) -> 1805.07 | K58: =SUM(Historical_Data!K79:K82) -> 2816.8 | L58: =SUM(Historical_Data!L79:L82) -> 3997.7 | M58: =L58 -> 3997.7 | N58: =M58 -> 3997.7 | O58: =N58 -> 3997.7 | P58: =O58 -> 3997.7 | Q58: =P58 -> 3997.7
D59: TOTAL LIBILITY | H59: =SUM(H53:H54,H57:H58) -> 12708.51 | I59: =SUM(I53:I54,I57:I58) -> 12964.91 | J59: =SUM(J53:J54,J57:J58) -> 14451.91 | K59: =SUM(K53:K54,K57:K58) -> 17133.99 | L59: =SUM(L53:L54,L57:L58) -> 17760.36 | M59: =SUM(M53:M54,M57:M58) -> 13976.991 | N59: =SUM(N53:N54,N57:N58) -> 13876.189 | O59: =SUM(O53:O54,O57:O58) -> 13928.902 | ... Q59: =SUM(Q53:Q54,Q57:Q58) -> 14579.525
D61: Equity | H61: =Historical_Data!H68 -> 397.13 | I61: =Historical_Data!I68 -> 397.13 | J61: =Historical_Data!J68 -> 439.54 | K61: =Historical_Data!K68 -> 492.62 | L61: =Historical_Data!L68 -> 494.36 | M61: =L61 -> 494.36 | N61: =M61 -> 494.36 | O61: =N61 -> 494.36 | P61: =O61 -> 494.36 | Q61: =P61 -> 494.36
D62: Other Equity | H62: =Historical_Data!H69+Historical_Data!H70 -> 24956.61 | I62: =Historical_Data!I69+Historical_Data!I70 -> 31301.07 | J62: =Historical_Data!J69+Historical_Data!J70 -> 41015.52 | K62: =Historical_Data!K69+Historical_Data!K70 -> 52950.63 | L62: =Historical_Data!L69+Historical_Data!L70 -> 58852.96 | M62: =L62+M33+M90 -> 64302.463 | N62: =M62+N33+N90 -> 72227.616 | O62: =N62+O33+O90 -> 83020.327 | P62: =O62+P33+P90 -> 97045.428 | Q62: =P62+Q33+Q90 -> 114631.04
D63: Shareholder's Funds | H63: =SUM(H61:H62) -> 25353.74 | I63: =SUM(I61:I62) -> 31698.2 | J63: =SUM(J61:J62) -> 41455.06 | K63: =SUM(K61:K62) -> 53443.25 | L63: =SUM(L61:L62) -> 59347.32 | M63: =SUM(M61:M62) -> 64796.823 | N63: =SUM(N61:N62) -> 72721.976 | O63: =SUM(O61:O62) -> 83514.687 | ... Q63: =SUM(Q61:Q62) -> 115125.4
D64: Non-Controlling Interest | H64: =Historical_Data!H72 -> 7145.03 | I64: =Historical_Data!I72 -> 7058.35 | J64: =Historical_Data!J72 -> 9390.84 | K64: =Historical_Data!K72 -> 10368.17 | L64: =Historical_Data!L72 -> 12498.92 | M64: =L64 -> 12498.92 | N64: =M64 -> 12498.92 | O64: =N64 -> 12498.92 | P64: =O64 -> 12498.92 | Q64: =P64 -> 12498.92
D65: TOTAL EQUITY & LIABILITIES | H65: =SUM(H63:H64)+H59 -> 45207.28 | I65: =SUM(I63:I64)+I59 -> 51721.46 | J65: =SUM(J63:J64)+J59 -> 65297.81 | K65: =SUM(K63:K64)+K59 -> 80945.41 | L65: =SUM(L63:L64)+L59 -> 89606.6 | M65: =SUM(M63:M64)+M59 -> 91272.734 | N65: =SUM(N63:N64)+N59 -> 99097.085 | O65: =SUM(O63:O64)+O59 -> 109942.51 | ... Q65: =SUM(Q63:Q64)+Q59 -> 142203.85
D67: CHECK | H67: =IF(H65=H49,"TALLIED","ERROR") -> TALLIED | I67: =IF(I65=I49,"TALLIED","ERROR") -> TALLIED | J67: =IF(J65=J49,"TALLIED","ERROR") -> TALLIED | K67: =IF(K65=K49,"TALLIED","ERROR") -> TALLIED | L67: =IF(L65=L49,"TALLIED","ERROR") -> TALLIED | M67: =IF(M65=M49,"TALLIED","ERROR") -> TALLIED | N67: =IF(N65=N49,"TALLIED","ERROR") -> TALLIED | O67: =IF(O65=O49,"TALLIED","ERROR") -> TALLIED | ... Q67: =IF(Q65=Q49,"TALLIED","ERROR") -> TALLIED
A69: CASHFLOW STATEMENT
C72: Cash Flow From Operations
D73: Profit after Tax | H73: =Historical_Data!H102+Historical_Data!H141 -> 4516.86 | I73: =Historical_Data!I102+Historical_Data!I141 -> 2991 | J73: =Historical_Data!J102+Historical_Data!J141 -> 4985.06 | K73: =Historical_Data!K102+Historical_Data!K141 -> 5542.19 | L73: =Historical_Data!L102+Historical_Data!L141 -> 3580.98 | M73: =M33 -> 6750.0013 | N73: =N33 -> 9816.4524 | O73: =O33 -> 13368.341 | P73: =P33 -> 17372.124 | Q73: =Q33 -> 21782.339
D74: Add: Depreciation & Amortization | H74: =Historical_Data!H104 -> 1152.49 | I74: =Historical_Data!I104 -> 1644.67 | J74: =Historical_Data!J104 -> 1623.38 | K74: =Historical_Data!K104 -> 2478.34 | L74: =Historical_Data!L104 -> 3570.41 | M74: =-M110 -> 4135.1208 | N74: =-N110 -> 4606.0171 | O74: =-O110 -> 5207.0609 | P74: =-P110 -> 5933.1924 | Q74: =-Q110 -> 6773.6779
D75: Add/Less: Other Adjustment | H75: =SUM(Historical_Data!H105:H128) -> -28.78 | I75: =SUM(Historical_Data!I105:I128) -> -427.84 | J75: =SUM(Historical_Data!J105:J128) -> -1156.71 | K75: =SUM(Historical_Data!K105:K128) -> -2381.96 | L75: =SUM(Historical_Data!L105:L128) -> 57.76 | M75: =-SUM(M29:M30) -> -2014.1755 | N75: =-SUM(N29:N30) -> -2829.4964 | O75: =-SUM(O29:O30) -> -3771.862 | P75: =-SUM(P29:P30) -> -4804.2428 | Q75: =-SUM(Q29:Q30) -> -5889.3636
D76: Add/Less: Working Capital Adjustment | H76: =SUM(Historical_Data!H131:H138) -> -331.41 | I76: =SUM(Historical_Data!I131:I138) -> -3472.91 | J76: =SUM(Historical_Data!J131:J138) -> 194.09 | K76: =SUM(Historical_Data!K131:K138) -> -3401.22 | L76: =SUM(Historical_Data!L131:L138) -> -1847.62 | M76: =M105 -> -4864.9727 | N76: =N105 -> -2200.034 | O76: =O105 -> -2593.5066 | P76: =P105 -> -2985.0315 | Q76: =Q105 -> -3360.749
D77: Operating Cash Flow | H77: =SUM(H73:H76) -> 5309.16 | I77: =SUM(I73:I76) -> 734.92 | J77: =SUM(J73:J76) -> 5645.82 | K77: =SUM(K73:K76) -> 2237.35 | L77: =SUM(L73:L76) -> 5361.53 | M77: =SUM(M73:M76) -> 4005.9739 | N77: =SUM(N73:N76) -> 9392.939 | O77: =SUM(O73:O76) -> 12210.033 | ... Q77: =SUM(Q73:Q76) -> 19305.905
C79: Cash Flow From Investing Activities
D80: Investment in PP&E | H80: =Historical_Data!H145 -> -2334.1 | I80: =Historical_Data!I145 -> -4231.78 | J80: =Historical_Data!J145 -> -4482.46 | K80: =Historical_Data!K145 -> -8687.05 | L80: =Historical_Data!L145 -> -6344.33 | M80: =-M109 -> -10097.192 | N80: =-N109 -> -12215.902 | O80: =-O109 -> -14400.696 | P80: =-P109 -> -16574.676 | Q80: =-Q109 -> -18660.884
D81: Purchase/Sale of Investment | H81: =SUM(Historical_Data!H147:H159) -> 6.67 | I81: =SUM(Historical_Data!I147:I159) -> -10862.08 | J81: =SUM(Historical_Data!J147:J159) -> -6018.93 | K81: =SUM(Historical_Data!K147:K159) -> 63.76 | L81: =SUM(Historical_Data!L147:L159) -> -2312.39 | M81: 0 | N81: =M81 -> 0 | O81: =N81 -> 0 | P81: =O81 -> 0 | Q81: =P81 -> 0
D82: Sale Procceds From Sale Of PPE's | H82: =Historical_Data!H146 -> 37.76 | I82: =Historical_Data!I146 -> 165.85 | J82: =Historical_Data!J146 -> 521.32 | K82: =Historical_Data!K146 -> 95.56 | L82: =Historical_Data!L146 -> 388.62 | M82: 0 | N82: =M82 -> 0 | O82: =N82 -> 0 | P82: =O82 -> 0 | Q82: =P82 -> 0
D83: Dividend Income | H83: =Historical_Data!H160 -> 4.31 | I83: =Historical_Data!I160 -> 12.39 | J83: =Historical_Data!J160 -> 26.04 | K83: =Historical_Data!K160 -> 15.07 | L83: =Historical_Data!L160 -> 6.89 | M83: 0 | N83: =M83 -> 0 | O83: =N83 -> 0 | P83: =O83 -> 0 | Q83: =P83 -> 0
D84: Interest Income | H84: =Historical_Data!H161 -> 278.31 | I84: =Historical_Data!I161 -> 434.87 | J84: =Historical_Data!J161 -> 1003.6 | K84: =Historical_Data!K161 -> 981.56 | L84: =Historical_Data!L161 -> 326.02 | M84: =M30 -> 2292.6924 | N84: =N30 -> 3003.0408 | O84: =O30 -> 3840.4339 | P84: =P30 -> 4804.2428 | Q84: =Q30 -> 5889.3636
D85: Cash Flow from Investing Activities | H85: =SUM(H80:H84) -> -2007.05 | I85: =SUM(I80:I84) -> -14480.75 | J85: =SUM(J80:J84) -> -8950.43 | K85: =SUM(K80:K84) -> -7531.1 | L85: =SUM(L80:L84) -> -7935.19 | M85: =SUM(M80:M84) -> -7804.4998 | N85: =SUM(N80:N84) -> -9212.8608 | O85: =SUM(O80:O84) -> -10560.262 | ... Q85: =SUM(Q80:Q84) -> -12771.52
C87: Cash Flow From Financing Activities
D88: Issuance/Repayment of Debt | H88: =SUM(Historical_Data!H165:H166,Historical_Data!H168:H171) -> -75.13 | I88: =SUM(Historical_Data!I165:I166,Historical_Data!I168:I171) -> 4853.99 | J88: =SUM(Historical_Data!J165:J166,Historical_Data!J168:J171) -> 6507.66 | K88: =SUM(Historical_Data!K165:K166,Historical_Data!K168:K171) -> 6330.81 | L88: =SUM(Historical_Data!L165:L166,Historical_Data!L168:L171) -> -912.13 | M88: =M115 -> -326.3675 | N88: =N115 -> -326.3675 | O88: =O115 -> -213.195 | P88: =P115 -> 0 | Q88: =Q115 -> 0
D89: Proceeds from issue of share capital
D90: Dividend Paid | H90: =SUM(Historical_Data!H172:H173) -> -333.42 | I90: =SUM(Historical_Data!I172:I173) -> -1795.48 | J90: =SUM(Historical_Data!J172:J173) -> -584.81 | K90: =SUM(Historical_Data!K172:K173) -> -562.98 | L90: =SUM(Historical_Data!L172:L173) -> -564.96 | M90: =M33*-M14 -> -1300.4981 | N90: =N33*-N14 -> -1891.3 | O90: =O33*-O14 -> -2575.6294 | P90: =P33*-P14 -> -3347.0237 | Q90: =Q33*-Q14 -> -4196.7237
D91: Interest Paid | H91: =Historical_Data!H167 -> -107.21 | I91: =Historical_Data!I167 -> -127.5 | J91: =Historical_Data!J167 -> -234.08 | K91: =Historical_Data!K167 -> -175.79 | L91: =Historical_Data!L167 -> -152.31 | M91: =M117 -> -278.51693 | N91: =N117 -> -173.54439 | O91: =O117 -> -68.571845 | P91: =P117 -> 0 | Q91: =Q117 -> 0
D92: Cash Flow From Financing Activities | H92: =SUM(H88:H91) -> -515.76 | I92: =SUM(I88:I91) -> 2931.01 | J92: =SUM(J88:J91) -> 5688.77 | K92: =SUM(K88:K91) -> 5592.04 | L92: =SUM(L88:L91) -> -1629.4 | M92: =SUM(M88:M91) -> -1905.3825 | N92: =SUM(N88:N91) -> -2391.2119 | O92: =SUM(O88:O91) -> -2857.3962 | ... Q92: =SUM(Q88:Q91) -> -4196.7237
D94: Net Decrease in Cash and Cash Equivalents | H94: =SUM(H77+H85+H92) -> 2786.35 | I94: =SUM(I77+I85+I92) -> -10814.82 | J94: =SUM(J77+J85+J92) -> 2384.16 | K94: =SUM(K77+K85+K92) -> 298.29 | L94: =SUM(L77+L85+L92) -> -4203.06 | M94: =SUM(M77+M85+M92) -> -5703.9084 | N94: =SUM(N77+N85+N92) -> -2211.1336 | O94: =SUM(O77+O85+O92) -> -1207.625 | ... Q94: =SUM(Q77+Q85+Q92) -> 2337.6607
D95: Opening Cash Balance | H95: =Historical_Data!H178 -> 8571.56 | I95: =H96 -> 11358.49 | J95: =I96 -> 543.87 | K95: =J96 -> 3007.1 | L95: =K96 -> 5043.32 | M95: =L45 -> 891.59 | N95: =M96 -> -4812.3184 | O95: =N96 -> -7023.452 | P95: =O96 -> -8231.077 | Q95: =P96 -> -7832.4915
D96: Closing Cash Balance | H96: =Historical_Data!H53 -> 11358.49 | I96: =Historical_Data!I53 -> 543.87 | J96: =Historical_Data!J53 -> 3007.1 | K96: =Historical_Data!K53 -> 5043.32 | L96: =Historical_Data!L53 -> 891.59 | M96: =SUM(M94:M95) -> -4812.3184 | N96: =SUM(N94:N95) -> -7023.452 | O96: =SUM(O94:O95) -> -8231.077 | P96: =SUM(P94:P95) -> -7832.4915 | Q96: =SUM(Q94:Q95) -> -5494.8308
A98: Supporting Schedules
C100: Working Capital
D101: Accounts Receivable | H101: =Historical_Data!H132 -> -268.03 | I101: =Historical_Data!I132 -> -547.07 | J101: =Historical_Data!J132 -> 24.35 | K101: =Historical_Data!K132 -> -382.32 | L101: =Historical_Data!L132 -> -21.37 | M101: =L46-M46 -> -109.70184 | N101: =M46-N46 -> -612.90002 | O101: =N46-O46 -> -722.5162 | P101: =O46-P46 -> -831.58981 | Q101: =P46-Q46 -> -936.25968
D102: Inventory | H102: =Historical_Data!H131 -> -1121.71 | I102: =Historical_Data!I131 -> -466.99 | J102: =Historical_Data!J131 -> -228.29 | K102: =Historical_Data!K131 -> -512.89 | L102: =Historical_Data!L131 -> -9.26 | M102: =L47-M47 -> -1298.269 | N102: =M47-N47 -> -1812.7001 | O102: =N47-O47 -> -2136.8986 | P102: =O47-P47 -> -2459.4923 | Q102: =P47-Q47 -> -2769.0617
D103: Accounts Payable | H103: =Historical_Data!H135 -> 1058.33 | I103: =Historical_Data!I135 -> -27.76 | J103: =Historical_Data!J135 -> 102.98 | K103: =Historical_Data!K135 -> -576.29 | L103: =Historical_Data!L135 -> 665 | M103: =M53-L53 -> -3457.0019 | N103: =N53-M53 -> 225.56607 | O103: =O53-N53 -> 265.9082 | P103: =P53-O53 -> 306.05065 | Q103: =Q53-P53 -> 344.57238
D104: Other's | H104: =SUM(Historical_Data!H136:H138,Historical_Data!H133:H134) -> 0 | I104: =SUM(Historical_Data!I136:I138,Historical_Data!I133:I134) -> -2431.09 | J104: =SUM(Historical_Data!J136:J138,Historical_Data!J133:J134) -> 295.05 | K104: =SUM(Historical_Data!K136:K138,Historical_Data!K133:K134) -> -1929.72 | L104: =SUM(Historical_Data!L136:L138,Historical_Data!L133:L134) -> -2481.99
D105: Total | H105: =SUM(H101:H104) -> -331.41 | I105: =SUM(I101:I104) -> -3472.91 | J105: =SUM(J101:J104) -> 194.09 | K105: =SUM(K101:K104) -> -3401.22 | L105: =SUM(L101:L104) -> -1847.62 | M105: =SUM(M101:M104) -> -4864.9727 | N105: =SUM(N101:N104) -> -2200.034 | O105: =SUM(O101:O104) -> -2593.5066 | ... Q105: =SUM(Q101:Q104) -> -3360.749
C107: Depreciation & Amortization
D108: Opening Balance | I108: =H111 -> 16082.38 | J108: =I111 -> 17619.52 | K108: =J111 -> 26069.31 | L108: =K111 -> 40142.63 | M108: =L111 -> 52355.24 | N108: =M111 -> 58317.311 | O108: =N111 -> 65927.196 | P108: =O111 -> 75120.831 | Q108: =P111 -> 85762.314
D109: Add/Less: Purchase/sale | I109: =I111-I110-I108 -> 3181.81 | J109: =J111-J110-J108 -> 10073.17 | K109: =K111-K110-K108 -> 16551.66 | L109: =L111-L110-L108 -> 15783.02 | M109: =(M22-L22)/M18 -> 10097.192 | N109: =(N22-M22)/N18 -> 12215.902 | O109: =(O22-N22)/O18 -> 14400.696 | P109: =(P22-O22)/P18 -> 16574.676 | Q109: =(Q22-P22)/Q18 -> 18660.884
D110: Less: Depreciation & Amortization | H110: =-Historical_Data!H104 -> -1152.49 | I110: =-Historical_Data!I104 -> -1644.67 | J110: =-Historical_Data!J104 -> -1623.38 | K110: =-Historical_Data!K104 -> -2478.34 | L110: =-Historical_Data!L104 -> -3570.41 | M110: =M108*-M13 -> -4135.1208 | N110: =N108*-N13 -> -4606.0171 | O110: =O108*-O13 -> -5207.0609 | P110: =P108*-P13 -> -5933.1924 | Q110: =Q108*-Q13 -> -6773.6779
D111: Closing Balance | H111: =H38+H39 -> 16082.38 | I111: =I38+I39 -> 17619.52 | J111: =J38+J39 -> 26069.31 | K111: =K38+K39 -> 40142.63 | L111: =L38+L39 -> 52355.24 | M111: =SUM(M108:M110) -> 58317.311 | N111: =SUM(N108:N110) -> 65927.196 | O111: =SUM(O108:O110) -> 75120.831 | P111: =SUM(P108:P110) -> 85762.314 | Q111: =SUM(Q108:Q110) -> 97649.52
C113: Debt Schedule
D114: Opening Balance | I114: =H116 -> 473.13 | J114: =I116 -> 522.73 | K114: =J116 -> 699.01 | L114: =K116 -> 788.5 | M114: =L116 -> 865.93 | N114: =M116 -> 539.5625 | O114: =N116 -> 213.195 | P114: =O116 -> 0 | Q114: =P116 -> 0
D115: Issuance/repayment | I115: =I114-I116 -> -49.6 | J115: =J114-J116 -> -176.28 | K115: =K114-K116 -> -89.49 | L115: =L114-L116 -> -77.43 | M115: =-AVERAGE(Repayment!H11:K11) -> -326.3675 | N115: =M115 -> -326.3675 | O115: =-O114 -> -213.195 | P115: 0 | Q115: 0
D116: Closing Balance | H116: =H57 -> 473.13 | I116: =I57 -> 522.73 | J116: =J57 -> 699.01 | K116: =K57 -> 788.5 | L116: =L57 -> 865.93 | M116: =SUM(M114:M115) -> 539.5625 | N116: =SUM(N114:N115) -> 213.195 | O116: =SUM(O114:O115) -> 0 | P116: =SUM(P114:P115) -> 0 | Q116: =SUM(Q114:Q115) -> 0
D117: Interest Expense | H117: =H29 -> -145.66 | I117: =I29 -> -194.9 | J117: =J29 -> -276.38 | K117: =K29 -> -215.94 | L117: =L29 -> -223.61 | M117: =-M114*M10 -> -278.51693 | N117: =-N114*N10 -> -173.54439 | O117: =-O114*O10 -> -68.571845 | P117: =-P114*P10 -> 0 | Q117: =-Q114*Q10 -> 0
A119: DCF Valuation
C122: Assumption's
D123: Transaction Date | F123: =DATE(2026,8,16) -> 46250
D124: Fiscal Year End Date | F124: =DATE(2027,3,31) -> 46477
D125: Tax Rate | F125: =M11 -> 0.026431343
...

Sheet Scenario
A1: AMBUJA CEMENT
A2: Revenue Scenarios
E4: Growth % | H4: =Model!M2 -> 2027 | I4: =Model!N2 -> 2028 | J4: =Model!O2 -> 2029 | K4: =Model!P2 -> 2030 | L4: =Model!Q2 -> 2031
D5: Bull Case | E5: =MAX(Model!I7:L7) -> 0.34425726 | H5: =E5 -> 0.34425726 | I5: =H5*(1-$E$8) -> 0.30983154 | J5: =I5*(1-$E$8) -> 0.27884838 | K5: =J5*(1-$E$8) -> 0.25096355 | L5: =K5*(1-$E$8) -> 0.22586719
D6: Base Case | E6: =AVERAGE(Model!I7:L7) -> 0.10309175 | H6: =E6 -> 0.10309175 | I6: =H6*(1-$E$8) -> 0.092782571 | J6: =I6*(1-$E$8) -> 0.083504314 | K6: =J6*(1-$E$8) -> 0.075153883 | L6: =K6*(1-$E$8) -> 0.067638494
D7: Bear Case | E7: =MIN(Model!I7:L7) -> -0.14837778 | H7: =E7 -> -0.14837778 | I7: =H7*(1-$E$8) -> -0.13354 | J7: =I7*(1-$E$8) -> -0.120186 | K7: =J7*(1-$E$8) -> -0.1081674 | L7: =K7*(1-$E$8) -> -0.09735066
D8: Annual growth tapering | E8: 0.1

Sheet Repayment
A1: AMBUJA CEMENT
A2: Issuance/Repayment of Debt
D5: TERM DEBT (Amortizing — has a defined repayment schedule) | H5: FY2027 | I5: FY2028 | J5: FY2029 | K5: FY2030
D6: Interest-free State Government Loans — Parent level (Ambuja Cements / ACC) (Single-installment loans; secured by bank guarantee backed by pledged fixed deposits) | H6: 8.47 | I6: 0 | J6: 0 | K6: 9.72
D8: LEASE LIABILITIES (Ind AS 116 — not financial debt, but contractual cash outflow)
D9: Lease Liabilities — Current portion (undiscounted, due FY2027) | H9: 275.52 | I9: 0 | J9: 0 | K9: 0
D10: Lease Liabilities — Non-current portion (undiscounted future total, 1-5yr + >5yr combined) | H10: 0 | I10: 1011.76 | J10: 0 | K10: 0
D11: Total | H11: =SUM(H6,H9:H10) -> 283.99 | I11: =SUM(I6,I9:I10) -> 1011.76 | J11: =SUM(J6,J9:J10) -> 0 | K11: =SUM(K6,K9:K10) -> 9.72

Sheet WACC
A1: AMBUJA CEMENT
A2: Weighted-Average Cost of Capital (WACC)
A3: All Amounts Denominated in Rs. Crore Unless Otherwise Stated
A5: Comparable Companies Beta
H7: Equity | I7: Total | J7: Debt/ | K7: Debt/ | L7: Tax | M7: Levered | N7: Unlevered
D8: Company Name | H8: Value | I8: Debt | J8: Equity | K8: Capital | L8: Rate % | M8: Beta | N8: Beta
D9: UltraTech Cement Limited | H9: =Comp!M7 -> 365131.5 | I9: =Comp!K7 -> 23755 | J9: =I9/H9 -> 0.065058753 | K9: =I9/(H9+I9) -> 0.061084661 | L9: =Model!M11 -> 0.026431343 | M9: 0.5 | N9: =M9/(1+J9*(1+K9)) -> 0.46771248
D10: Grasim Industries Limited | H10: =Comp!M8 -> 446877.2 | I10: =Comp!K8 -> 229393 | J10: =I10/H10 -> 0.51332447 | K10: =I10/(H10+I10) -> 0.33920318 | L10: =L9 -> 0.026431343 | M10: 0.9 | N10: =M10/(1+J10*(1+K10)) -> 0.53335048
D11: Shree Cement Limited | H11: =Comp!M9 -> 91015 | I11: =Comp!K9 -> 1868 | J11: =I11/H11 -> 0.020524089 | K11: =I11/(H11+I11) -> 0.020111323 | L11: =L10 -> 0.026431343 | M11: 0.7 | N11: =M11/(1+J11*(1+K11)) -> 0.68564475
D12: JK Cement Limited | H12: =Comp!M10 -> 46570.2 | I12: =Comp!K10 -> 6183 | J12: =I12/H12 -> 0.13276731 | K12: =I12/(H12+I12) -> 0.11720616 | L12: =L11 -> 0.026431343 | M12: 1.1 | N12: =M12/(1+J12*(1+K12)) -> 0.95791409
D13: Dalmia Bharat Limited | H13: =Comp!M11 -> 41845.6 | I13: =Comp!K11 -> 7428 | J13: =I13/H13 -> 0.1775097 | K13: =I13/(H13+I13) -> 0.1507501 | L13: =L12 -> 0.026431343 | M13: 1 | N13: =M13/(1+J13*(1+K13)) -> 0.83037905
D14: ACC Limited | H14: =Comp!M12 -> 24726.8 | I14: =Comp!K12 -> 429 | J14: =I14/H14 -> 0.017349596 | K14: =I14/(H14+I14) -> 0.017053721 | L14: =L13 -> 0.026431343 | M14: 0.55 | N14: =M14/(1+J14*(1+K14)) -> 0.54046327
D15: The Ramco Cements Limited | H15: =Comp!M13 -> 25151.2 | I15: =Comp!K13 -> 3871 | J15: =I15/H15 -> 0.15390916 | K15: =I15/(H15+I15) -> 0.13338065 | L15: =L14 -> 0.026431343 | M15: 1 | N15: =M15/(1+J15*(1+K15)) -> 0.85147133
D16: Birla Corporation Limited | H16: =Comp!M14 -> 9679.5 | I16: =Comp!K14 -> 3391 | J16: =I16/H16 -> 0.35032801 | K16: =I16/(H16+I16) -> 0.2594392 | L16: =L15 -> 0.026431343 | M16: 1.1 | N16: =M16/(1+J16*(1+K16)) -> 0.76324393
D17: JK Lakshmi Cement Limited | H17: =Comp!M15 -> 8393.6 | I17: =Comp!K15 -> 2586 | J17: =I17/H17 -> 0.30809188 | K17: =I17/(H17+I17) -> 0.23552771 | L17: =L16 -> 0.026431343 | M17: 1 | N17: =M17/(1+J17*(1+K17)) -> 0.72429335
D19: Average | J19: =AVERAGE(J9:J17) -> 0.193207 | K19: =AVERAGE(K9:K17) -> 0.14819519 | L19: =AVERAGE(L9:L17) -> 0.026431343 | M19: =AVERAGE(M9:M17) -> 0.87222222 | N19: =AVERAGE(N9:N17) -> 0.70605253
D20: Median | J20: =MEDIAN(J9:J17) -> 0.15390916 | K20: =MEDIAN(K9:K17) -> 0.13338065 | L20: =MEDIAN(L9:L17) -> 0.026431343 | M20: =MEDIAN(M9:M17) -> 1 | N20: =MEDIAN(N9:N17) -> 0.72429335
D22: Ambuja Cement | H22: =Comp!M20 -> 103303.6 | I22: =Comp!K20 -> 866
D24: WACC Calculation
C26: Target Capital Structure
D28: Proportion of Debt | I28: =K19 -> 0.14819519
D29: Proportion of Equity | I29: =1-I28 -> 0.85180481
C31: Current Capital Structure
D32: Market Cap (EV proxy) | I32: =H22 -> 103303.6
D33: Total Debt | I33: =I22 -> 866
D34: Debt / Equity | I34: =I33/I32 -> 0.0083830573
C36: Cost of Debt
D37: Pre-Tax Cost of Debt | I37: =Model!M10 -> 0.32163909
D38: Tax Rate | I38: =Model!M11 -> 0.026431343
D39: After-Tax Cost of Debt | I39: =I37*(1-I38) -> 0.31313773
C41: Cost of Equity
D42: Risk Free Rate | I42: 0.068
D43: Equity Market Return | I43: =Market_Data!J10 -> 0.13038872
D44: Equity Risk Premium | I44: =I43-I42 -> 0.062388717
D45: Levered Equity Beta | I45: =N20*(1+I34)*(1-I38) -> 0.71106061
D46: Cost of Equity | I46: =I42+I45*I44 -> 0.11236216
D48: WACC | I48: =(I28*I39)+(I46*I29) -> 0.14211613

Sheet Market_Data
A1: AMBUJA CEMENT
A2: Equity Market Return
F5: Index | G5: Index Closing Price
F7: 46230 | G7: 23995.95
F8: 46227 | G8: 23767.45 | I8: Period (yrs) | J8: 9
F9: 46226 | G9: 23869.6
F10: 46225 | G10: 23996.25 | I10: Returns | J10: =_xlfn.RRI(J8,G2623,G7) -> 0.13038872
F11: 46224 | G11: 24187.7
F12: 46223 | G12: 24238.5
F13: 46220 | G13: 24334.3
F14: 46219 | G14: 24072.75
F15: 46218 | G15: 24078.5
F16: 46217 | G16: 24052.05
F17: 46216 | G17: 24211
F18: 46213 | G18: 24206.9
F19: 46212 | G19: 23962.8
F20: 46211 | G20: 23882.05
F21: 46210 | G21: 24398.7
F22: 46209 | G22: 24430.35
... F2623: 42370 | G2623: 7963.2

Sheet Comp
A1: AMBUJA CEMENT
A2: Comp Valuation
H4: Market Data | O4: Financial Data | S4: Valuation
H5: Price | I5: Shares | J5: Market Cap | K5: Debt | L5: Cash | M5: EV | O5: Sales | P5: EBITDA | Q5: Earnings | S5: EV/Sales | T5: EV/EBITDA | U5: P/E
D6: Company Name | F6: Ticker | H6: (₹/share) | L6: & Equivalents | S6: x | T6: x | U6: x
D7: =Comp_Data!D7 -> UltraTech Cement | F7: =Comp_Data!H7 -> ULTRACEMCO | H7: =Comp_Data!I7 -> 11619 | I7: =Comp_Data!J7 -> 29.5 | J7: =H7*I7 -> 342760.5 | K7: =Comp_Data!K7 -> 23755 | L7: =Comp_Data!L7 -> 1384 | M7: =J7+K7-L7 -> 365131.5 | O7: =Comp_Data!M7 -> 88512 | P7: =Comp_Data!N7 -> 17004 | Q7: =Comp_Data!O7 -> 8188 | S7: =M7/O7 -> 4.1252203 | T7: =M7/P7 -> 21.473271 | U7: =J7/Q7 -> 41.861321
D8: =Comp_Data!D8 -> Grasim Industries | F8: =Comp_Data!H8 -> GRASIM | H8: =Comp_Data!I8 -> 3249 | I8: =Comp_Data!J8 -> 67.8 | J8: =H8*I8 -> 220282.2 | K8: =Comp_Data!K8 -> 229393 | L8: =Comp_Data!L8 -> 2798 | M8: =J8+K8-L8 -> 446877.2 | O8: =Comp_Data!M8 -> 175431 | P8: =Comp_Data!N8 -> 36296 | Q8: =Comp_Data!O8 -> 10300 | S8: =M8/O8 -> 2.5473103 | T8: =M8/P8 -> 12.312023 | U8: =J8/Q8 -> 21.386621
D9: =Comp_Data!D9 -> Shree Cement | F9: =Comp_Data!H9 -> SHREECEM | H9: =Comp_Data!I9 -> 24795 | I9: =Comp_Data!J9 -> 3.6 | J9: =H9*I9 -> 89262 | K9: =Comp_Data!K9 -> 1868 | L9: =Comp_Data!L9 -> 115 | M9: =J9+K9-L9 -> 91015 | O9: =Comp_Data!M9 -> 20943 | P9: =Comp_Data!N9 -> 4638 | Q9: =Comp_Data!O9 -> 1749 | S9: =M9/O9 -> 4.3458435 | T9: =M9/P9 -> 19.62376 | U9: =J9/Q9 -> 51.036021
D10: =Comp_Data!D10 -> JK Cement | F10: =Comp_Data!H10 -> JKCEMENT | H10: =Comp_Data!I10 -> 5306 | I10: =Comp_Data!J10 -> 7.7 | J10: =H10*I10 -> 40856.2 | K10: =Comp_Data!K10 -> 6183 | L10: =Comp_Data!L10 -> 469 | M10: =J10+K10-L10 -> 46570.2 | O10: =Comp_Data!M10 -> 13722 | P10: =Comp_Data!N10 -> 2379 | Q10: =Comp_Data!O10 -> 988 | S10: =M10/O10 -> 3.3938347 | T10: =M10/P10 -> 19.575536 | U10: =J10/Q10 -> 41.352429
D11: =Comp_Data!D11 -> Dalmia Bharat | F11: =Comp_Data!H11 -> DALBHARAT | H11: =Comp_Data!I11 -> 1842 | I11: =Comp_Data!J11 -> 18.8 | J11: =H11*I11 -> 34629.6 | K11: =Comp_Data!K11 -> 7428 | L11: =Comp_Data!L11 -> 212 | M11: =J11+K11-L11 -> 41845.6 | O11: =Comp_Data!M11 -> 14804 | P11: =Comp_Data!N11 -> 3083 | Q11: =Comp_Data!O11 -> 1157 | S11: =M11/O11 -> 2.8266414 | T11: =M11/P11 -> 13.573013 | U11: =J11/Q11 -> 29.93051
D12: =Comp_Data!D12 -> ACC Ltd | F12: =Comp_Data!H12 -> ACC | H12: =Comp_Data!I12 -> 1321 | I12: =Comp_Data!J12 -> 18.8 | J12: =H12*I12 -> 24834.8 | K12: =Comp_Data!K12 -> 429 | L12: =Comp_Data!L12 -> 537 | M12: =J12+K12-L12 -> 24726.8 | O12: =Comp_Data!M12 -> 25962 | P12: =Comp_Data!N12 -> 2958 | Q12: =Comp_Data!O12 -> 2137 | S12: =M12/O12 -> 0.95242277 | T12: =M12/P12 -> 8.3592968 | U12: =J12/Q12 -> 11.621338
D13: =Comp_Data!D13 -> The Ramco Cements | F13: =Comp_Data!H13 -> RAMCOCEM | H13: =Comp_Data!I13 -> 907 | I13: =Comp_Data!J13 -> 23.6 | J13: =H13*I13 -> 21405.2 | K13: =Comp_Data!K13 -> 3871 | L13: =Comp_Data!L13 -> 125 | M13: =J13+K13-L13 -> 25151.2 | O13: =Comp_Data!M13 -> 9029 | P13: =Comp_Data!N13 -> 1437 | Q13: =Comp_Data!O13 -> 699 | S13: =M13/O13 -> 2.7856019 | T13: =M13/P13 -> 17.502575 | U13: =J13/Q13 -> 30.622604
D14: =Comp_Data!D14 -> Birla Corporation | F14: =Comp_Data!H14 -> BIRLACORPN | H14: =Comp_Data!I14 -> 905 | I14: =Comp_Data!J14 -> 7.7 | J14: =H14*I14 -> 6968.5 | K14: =Comp_Data!K14 -> 3391 | L14: =Comp_Data!L14 -> 680 | M14: =J14+K14-L14 -> 9679.5 | O14: =Comp_Data!M14 -> 9656 | P14: =Comp_Data!N14 -> 1455 | Q14: =Comp_Data!O14 -> 558 | S14: =M14/O14 -> 1.0024337 | T14: =M14/P14 -> 6.6525773 | U14: =J14/Q14 -> 12.488351
D15: =Comp_Data!D15 -> JK Lakshmi Cement | F15: =Comp_Data!H15 -> JKLAKSHMI | H15: =Comp_Data!I15 -> 549 | I15: =Comp_Data!J15 -> 12.4 | J15: =H15*I15 -> 6807.6 | K15: =Comp_Data!K15 -> 2586 | L15: =Comp_Data!L15 -> 1000 | M15: =J15+K15-L15 -> 8393.6 | O15: =Comp_Data!M15 -> 6763 | P15: =Comp_Data!N15 -> 1000 | Q15: =Comp_Data!O15 -> 413 | S15: =M15/O15 -> 1.241106 | T15: =M15/P15 -> 8.3936 | U15: =J15/Q15 -> 16.483293
D17: Average | S17: =AVERAGE(S7:S15) -> 2.5800461 | T17: =AVERAGE(T7:T15) -> 14.16285 | U17: =AVERAGE(U7:U15) -> 28.531388
D18: Median | S18: =MEDIAN(S7:S15) -> 2.7856019 | T18: =MEDIAN(T7:T15) -> 13.573013 | U18: =MEDIAN(U7:U15) -> 29.93051
D20: =Comp_Data!D5 -> Ambuja Cement | F20: =Comp_Data!H5 -> AMBUJACEM | H20: =Comp_Data!I5 -> 418 | I20: =Comp_Data!J5 -> 247.2 | J20: =H20*I20 -> 103329.6 | K20: =Comp_Data!K5 -> 866 | L20: =Comp_Data!L5 -> 892 | M20: =J20+K20-L20 -> 103303.6 | O20: =Comp_Data!M5 -> 40656 | P20: =Comp_Data!N5 -> 6577 | Q20: =Comp_Data!O5 -> 5637
D22: Metric | E22: Comps | H22: EV | I22: Net Debt | J22: Equity Value | K22: Shares | L22: Share Price
D23: EV/Sales | E23: =S18 -> 2.7856019 | H23: =E23*O20 -> 113251.43 | I23: =K20 -> 866 | J23: =H23-I23 -> 112385.43 | K23: =I20 -> 247.2 | L23: =J23/K23 -> 454.63363
D24: EV/EBITDA | E24: =T18 -> 13.573013 | H24: =E24*P20 -> 89269.708 | I24: =I23 -> 866 | J24: =H24-I24 -> 88403.708 | K24: =K23 -> 247.2 | L24: =J24/K24 -> 357.62018
D25: P/E | E25: =U18 -> 29.93051 | H25: =E25*Q20 -> 168718.28 | I25: =I24 -> 866 | J25: =H25-I25 -> 167852.28 | K25: =K24 -> 247.2 | L25: =J25/K25 -> 679.0141

Sheet Comp_Data
A1: AMBUJA CEMENT
A2: Comp Data
D4: Company | H4: Ticker | I4: Price | J4: Shares | K4: Debt | L4: Cash | M4: Sales | N4: EBITDA | O4: Net Income
D5: Ambuja Cement | H5: AMBUJACEM | I5: 418 | J5: 247.2 | K5: 866 | L5: 892 | M5: 40656 | N5: 6577 | O5: 5637
D7: UltraTech Cement | H7: ULTRACEMCO | I7: 11619 | J7: 29.5 | K7: 23755 | L7: 1384 | M7: 88512 | N7: 17004 | O7: 8188
D8: Grasim Industries | H8: GRASIM | I8: 3249 | J8: 67.8 | K8: 229393 | L8: 2798 | M8: 175431 | N8: 36296 | O8: 10300
D9: Shree Cement | H9: SHREECEM | I9: 24795 | J9: 3.6 | K9: 1868 | L9: 115 | M9: 20943 | N9: 4638 | O9: 1749
D10: JK Cement | H10: JKCEMENT | I10: 5306 | J10: 7.7 | K10: 6183 | L10: 469 | M10: 13722 | N10: 2379 | O10: 988
D11: Dalmia Bharat | H11: DALBHARAT | I11: 1842 | J11: 18.8 | K11: 7428 | L11: 212 | M11: 14804 | N11: 3083 | O11: 1157
D12: ACC Ltd | H12: ACC | I12: 1321 | J12: 18.8 | K12: 429 | L12: 537 | M12: 25962 | N12: 2958 | O12: 2137
D13: The Ramco Cements | H13: RAMCOCEM | I13: 907 | J13: 23.6 | K13: 3871 | L13: 125 | M13: 9029 | N13: 1437 | O13: 699
D14: Birla Corporation | H14: BIRLACORPN | I14: 905 | J14: 7.7 | K14: 3391 | L14: 680 | M14: 9656 | N14: 1455 | O14: 558
D15: JK Lakshmi Cement | H15: JKLAKSHMI | I15: 549 | J15: 12.4 | K15: 2586 | L15: 1000 | M15: 6763 | N15: 1000 | O15: 413
C17: Source: www.screener.in (accessed Aug 2026)

Sheet Foot_Ball Field
A1: Ambuja Cements Limited
A2: Football Field Chart
A4: Football Field Chart
E6: Comps | F6: DCF | G6: 52-week high/low | H6: Market Consensus
D7: High | E7: 679.0141 | F7: 396.59339 | G7: 605.5 | H7: 718
D8: High | E8: 679.0141 | F8: 396.59339 | G8: 605.5 | H8: 718 | I8: (Prabhudas Lilladher)
D9: Low | E9: 357.62018 | F9: 216.33956 | G9: 394.6 | H9: 530 | I9: (Motilal Oswal)
D10: Low | E10: 357.62018 | F10: 216.33956 | G10: 394.6 | H10: 530
A12: Valuation Summary
