Workbook

Sheet Historical Data
A1: NETFLIX, INC.
A2: Historical Data
H4: 2021 | I4: =H4+1 -> 2022 | J4: =I4+1 -> 2023 | K4: =J4+1 -> 2024 | L4: =K4+1 -> 2025
C5: Revenues | H5: 29697844 | I5: 31615550 | J5: 33723297 | K5: 39000966 | L5: 45183036
D6: Cost of revenues | H6: 17332683 | I6: 19168285 | J6: 19715368 | K6: 21038464 | L6: 23275329
D7: Marketing / Sales and marketing | H7: 2545146 | I7: 2530502 | J7: 2657883 | K7: 2917554 | L7: 3301306
D8: Technology and development | H8: 2273885 | I8: 2711041 | J8: 2675758 | K8: 2925295 | L8: 3391390
D9: General and administrative | H9: 1351621 | I9: 1572891 | J9: 1720285 | K9: 1702039 | L9: 1888408
C10: Operating income | H10: =H5-H6-H7-H8-H9 -> 6194509 | I10: =I5-I6-I7-I8-I9 -> 5632831 | J10: =J5-J6-J7-J8-J9 -> 6954003 | K10: =K5-K6-K7-K8-K9 -> 10417614 | L10: =L5-L6-L7-L8-L9 -> 13326603
D12: Other income (expense):
D13: Interest expense | H13: -765620 | I13: -706212 | J13: -699826 | K13: -718733 | L13: -776510
D14: Interest and other income (expense) | H14: 411214 | I14: 337310 | J14: -48772 | K14: 266776 | L14: 172459
D15: Income before income taxes | H15: =H10+H13+H14 -> 5840103 | I15: =I10+I13+I14 -> 5263929 | J15: =J10+J13+J14 -> 6205405 | K15: =K10+K13+K14 -> 9965657 | L15: =L10+L13+L14 -> 12722552
D16: Provision for income taxes | H16: -723875 | I16: -772005 | J16: -797415 | K16: -1254026 | L16: -1741351
C17: Net income | H17: =H15+H16 -> 5116228 | I17: =I15+I16 -> 4491924 | J17: =J15+J16 -> 5407990 | K17: =K15+K16 -> 8711631 | L17: =L15+L16 -> 10981201
A19: BALANCE SHEET
B20: Assets
C21: Current assets:
D22: Cash and cash equivalents | H22: 6027804 | I22: 5147176 | J22: 7116913 | K22: 7804733 | L22: 9033681
D23: Short-term investments | H23: 0 | I23: 911276 | J23: 20973 | K23: 1779006 | L23: 28678
D24: Other current assets | H24: 2042021 | I24: 3208021 | J24: 2780247 | K24: 3516640 | L24: 3957832
C25: Total current assets | H25: =SUM(H22:H24) -> 8069825 | I25: =SUM(I22:I24) -> 9266473 | J25: =SUM(J22:J24) -> 9918133 | K25: =SUM(K22:K24) -> 13100379 | L25: =SUM(L22:L24) -> 13020191
D27: Content assets, net | H27: 30919539 | I27: 32736713 | J27: 31658056 | K27: 32452462 | L27: 32778392
D28: Property and equipment, net | H28: 1323453 | I28: 1398257 | J28: 1491444 | K28: 1593756 | L28: 2004350
D29: Other non-current assets | H29: 4271846 | I29: 5193325 | J29: 5664359 | K29: 6483777 | L29: 7794060
C30: Total assets | H30: =H25+H27+H28+H29 -> 44584663 | I30: =I25+I27+I28+I29 -> 48594768 | J30: =J25+J27+J28+J29 -> 48731992 | K30: =K25+K27+K28+K29 -> 53630374 | L30: =L25+L27+L28+L29 -> 55596993
A32: Liabilities and Stockholders' Equity
B33: Current liabilities:
D34: Current content liabilities | H34: 4292967 | I34: 4480150 | J34: 4466470 | K34: 4393681 | L34: 4084854
D35: Accounts payable | H35: 837483 | I35: 671513 | J35: 747412 | K35: 899909 | L35: 900612
D36: Accrued expenses and other liabilities | H36: 1449351 | I36: 1514650 | J36: 1803960 | K36: 2156544 | L36: 3220869
D37: Deferred revenue | H37: 1209342 | I37: 1264661 | J37: 1442969 | K37: 1520813 | L37: 1775730
D38: Short-term debt | H38: 699823 | I38: 0 | J38: 399844 | K38: 1784453 | L38: 998865
C39: Total current liabilities | H39: =SUM(H34:H38) -> 8488966 | I39: =SUM(I34:I38) -> 7930974 | J39: =SUM(J34:J38) -> 8860655 | K39: =SUM(K34:K38) -> 10755400 | L39: =SUM(L34:L38) -> 10980930
D41: Non-current content liabilities | H41: 3094213 | I41: 3081277 | J41: 2578173 | K41: 1780806 | L41: 1579476
D42: Long-term debt | H42: 14693072 | I42: 14353076 | J42: 14143417 | K42: 13798351 | L42: 13463971
D43: Other non-current liabilities | H43: 2459164 | I43: 2452040 | J43: 2561434 | K43: 2552250 | L43: 2957128
C44: Total liabilities | H44: =H39+H41+H42+H43 -> 28735415 | I44: =I39+I41+I42+I43 -> 27817367 | J44: =J39+J41+J42+J43 -> 28143679 | K44: =K39+K41+K42+K43 -> 28886807 | L44: =L39+L41+L42+L43 -> 28981505
A46: Stockholders' equity:
D47: Preferred stock ($0.001 par; none issued/outstanding) | H47: 0 | I47: 0 | J47: 0 | K47: 0 | L47: 0
D48: Common stock and additional paid-in capital | H48: 4024561 | I48: 4637601 | J48: 5145172 | K48: 6252126 | L48: 7286410
D49: Treasury stock, at cost | H49: -824190 | I49: -824190 | J49: -6922200 | K49: -13171638 | L49: -22372658
D50: Accumulated other comprehensive income (loss) | H50: -40495 | I50: -217306 | J50: -223945 | K50: 362162 | L50: -580382
D51: Retained earnings | H51: 12689372 | I51: 17181296 | J51: 22589286 | K51: 31300917 | L51: 42282118
C52: Total stockholders' equity | H52: =H48+H49+H50+H51 -> 15849248 | I52: =I48+I49+I50+I51 -> 20777401 | J52: =J48+J49+J50+J51 -> 20588313 | K52: =K48+K49+K50+K51 -> 24743567 | L52: =L48+L49+L50+L51 -> 26615488
C53: Total liabilities and stockholders' equity | H53: =H44+H52 -> 44584663 | I53: =I44+I52 -> 48594768 | J53: =J44+J52 -> 48731992 | K53: =K44+K52 -> 53630374 | L53: =L44+L52 -> 55596993
A55: CASH FLOW
B56: Cash flows from operating activities:
D57: Net income | H57: 5116228 | I57: 4491924 | J57: 5407990 | K57: 8711631 | L57: 10981201
C58: Adjustments to reconcile net income to net cash provided by operating activities:
D59: Additions to content assets | H59: -17702202 | I59: -16839038 | J59: -12554703 | K59: -16223617 | L59: -17096617
D60: Change in content liabilities | H60: 232898 | I60: 179310 | J60: -585602 | K60: -779135 | L60: -610838
D61: Amortization of content assets | H61: 12230367 | I61: 14026132 | J61: 14197437 | K61: 15301517 | L61: 16422166
D62: Depreciation and amortization of property, equipment and intangibles | H62: 208412 | I62: 336682 | J62: 356947 | K62: 328914 | L62: 333389
D63: Stock-based compensation expense | H63: 403220 | I63: 575452 | J63: 339368 | K63: 272588 | L63: 368449
D64: Foreign currency remeasurement (gain) loss on debt | H64: -430661 | I64: -353111 | J64: 176296 | K64: -121539 | L64: 72348
D65: Other non-cash items | H65: 376777 | I65: 533543 | J65: 512075 | K65: 494778 | L65: 577451
D66: Deferred income taxes | H66: 199548 | I66: -166550 | J66: -459359 | K66: -590698 | L66: -442056
C67: Changes in operating assets and liabilities:
D68: Other current assets | H68: -369681 | I68: -353834 | J68: -181003 | K68: 22180 | L68: -790661
D69: Accounts payable | H69: 145115 | I69: -158543 | J69: 93502 | K69: 121353 | L69: -8039
D70: Accrued expenses and other liabilities | H70: 180338 | I70: -55513 | J70: 103565 | K70: 191899 | L70: 881218
D71: Deferred revenue | H71: 91350 | I71: 27356 | J71: 178708 | K71: 77844 | L71: 254917
D72: Other non-current assets and liabilities | H72: -289099 | I72: -217553 | J72: -310920 | K72: -446351 | L72: -793655
C73: Net cash provided by operating activities | H73: =SUM(H57,H59,H60,H61,H62,H63,H64,H65,H66,H68,H69,H70,H71,H72) -> 392610 | I73: =SUM(I57,I59,I60,I61,I62,I63,I64,I65,I66,I68,I69,I70,I71,I72) -> 2026257 | J73: =SUM(J57,J59,J60,J61,J62,J63,J64,J65,J66,J68,J69,J70,J71,J72) -> 7274301 | K73: =SUM(K57,K59,K60,K61,K62,K63,K64,K65,K66,K68,K69,K70,K71,K72) -> 7361364 | L73: =SUM(L57,L59,L60,L61,L62,L63,L64,L65,L66,L68,L69,L70,L71,L72) -> 10149273
B75: Cash flows from investing activities:
D76: Purchases of property and equipment | H76: -524585 | I76: -407729 | J76: -348552 | K76: -439538 | L76: -688220
D77: Change in other assets | H77: -26919 | I77: 0 | J77: 0 | K77: 0 | L77: 0
D78: Acquisitions | H78: -788349 | I78: -757387 | J78: 0 | K78: 0 | L78: -17194
D79: Purchases of investments | H79: 0 | I79: -911276 | J79: -504862 | K79: -1742246 | L79: -169965
D80: Proceeds from maturities and sales of investments | H80: 0 | I80: 0 | J80: 1395165 | K80: 0 | L80: 1917067
D81: Net cash provided by (used in) investing activities | H81: =SUM(H76:H80) -> -1339853 | I81: =SUM(I76:I80) -> -2076392 | J81: =SUM(J76:J80) -> 541751 | K81: =SUM(K76:K80) -> -2181784 | L81: =SUM(L76:L80) -> 1041688
B83: Cash flows from financing activities:
D84: Proceeds from issuance of debt | H84: 0 | I84: 0 | J84: 0 | K84: 1794460 | L84: 0
D85: Repayments of debt | H85: -500000 | I85: -700000 | J85: 0 | K85: -400000 | L85: -1833450
D86: Proceeds from issuance of common stock | H86: 174414 | I86: 35746 | J86: 169990 | K86: 832887 | L86: 666965
D87: Repurchases of common stock | H87: -600022 | I87: 0 | J87: -6045347 | K87: -6263746 | L87: -9127167
D88: Taxes paid related to net share settlement of equity awards | H88: -224168 | I88: 0 | J88: 0 | K88: -8285 | L88: -46165
D89: Other financing activities | H89: 0 | I89: 0 | J89: -75446 | K89: -29743 | L89: -5806
C90: Net cash used in financing activities | H90: =SUM(H84:H89) -> -1149776 | I90: =SUM(I84:I89) -> -664254 | J90: =SUM(J84:J89) -> -5950803 | K90: =SUM(K84:K89) -> -4074427 | L90: =SUM(L84:L89) -> -10345623
D92: Effect of exchange rate changes on cash, cash equivalents and restricted cash | H92: -86740 | I92: -170140 | J92: 82684 | K92: -416331 | L92: 386519
C93: Net increase (decrease) in cash, cash equivalents and restricted cash | H93: =H73+H81+H90+H92 -> -2183759 | I93: =I73+I81+I90+I92 -> -884529 | J93: =J73+J81+J90+J92 -> 1947933 | K93: =K73+K81+K90+K92 -> 688822 | L93: =L73+L81+L90+L92 -> 1231857
D94: Cash, cash equivalents and restricted cash, beginning of year | H94: 8238870 | I94: 6055111 | J94: 5170582 | K94: 7118515 | L94: 7807337
C95: Cash, cash equivalents and restricted cash, end of year | H95: =H93+H94 -> 6055111 | I95: =I93+I94 -> 5170582 | J95: =J93+J94 -> 7118515 | K95: =K93+K94 -> 7807337 | L95: =L93+L94 -> 9039194

Sheet Model
A1: NETFLIX, INC. | H1: Historical Data | M1: Forecasted Period
A2: Financial Statement Analysis & Valuation | H2: 2021 | I2: =H2+1 -> 2022 | J2: =I2+1 -> 2023 | K2: =J2+1 -> 2024 | L2: =K2+1 -> 2025 | M2: =L2+1 -> 2026 | N2: =M2+1 -> 2027 | O2: =N2+1 -> 2028 | P2: =O2+1 -> 2029 | Q2: =P2+1 -> 2030
A4: Ratios & Assumptions
C6: LIVE SCENARIO | E6: Base Case | G6: =IF(E6=Scenario!D6,1,IF(E6=Scenario!D7,2,3)) -> 1
C7: Revenue Growth % | I7: =(I22-H22)/H22 -> 0.064573913 | J7: =(J22-I22)/I22 -> 0.066668048 | K7: =(K22-J22)/J22 -> 0.1564992 | L7: =(L22-K22)/K22 -> 0.15851069 | M7: {=CHOOSE(G6,Scenario!H6:L6,Scenario!H7:L7,Scenario!H8:L8)} -> 0.11156296 | N7: 0.10435891 | O7: 0.097620043 | P7: 0.091316334 | Q7: 0.085419681
C8: COGS as % of Revenue | H8: =H23/-H22 -> 0.58363439 | I8: =I23/-I22 -> 0.60629295 | J8: =J23/-J22 -> 0.5846216 | K8: =K23/-K22 -> 0.53943443 | L8: =L23/-L22 -> 0.51513424 | M8: =AVERAGE(H8:L8) -> 0.56582352 | N8: =M8 -> 0.56582352 | O8: =N8 -> 0.56582352 | P8: =O8 -> 0.56582352 | Q8: =P8 -> 0.56582352
C9: Operating Expense as % of Revenue | H9: =H25/-H22 -> 0.20778114 | I9: =I25/-I22 -> 0.21554058 | J9: =J25/-J22 -> 0.20917071 | K9: =K25/-K22 -> 0.19345387 | L9: =L25/-L22 -> 0.18991871 | M9: =AVERAGE(H9:L9) -> 0.203173 | N9: =M9 -> 0.203173 | O9: =N9 -> 0.203173 | P9: =O9 -> 0.203173 | Q9: =P9 -> 0.203173
C10: Depreciation & Amortization as % PP&E | H10: =H27/-H45 -> 0.15747594 | I10: =I27/-I45 -> 0.24078692 | J10: =J27/-J45 -> 0.2393298 | K10: =K27/-K45 -> 0.20637663 | L10: =L27/-L45 -> 0.16633273 | M10: =AVERAGE(H10:L10) -> 0.2020604 | N10: =M10 -> 0.2020604 | O10: =N10 -> 0.2020604 | P10: =O10 -> 0.2020604 | Q10: =P10 -> 0.2020604
C11: Interest as % of Debt | H11: =H29/-H58 -> 0.049738532 | I11: =I29/-I58 -> 0.049202833 | J11: =J29/-J58 -> 0.048120294 | K11: =K29/-K58 -> 0.04612347 | L11: =L29/-L58 -> 0.053690023 | M11: =AVERAGE(H11:L11) -> 0.049375031 | N11: =M11 -> 0.049375031 | O11: =N11 -> 0.049375031 | P11: =O11 -> 0.049375031 | Q11: =P11 -> 0.049375031
C12: Other Revenue as % of Revenue | H12: =H30/H22 -> 0.013846594 | I12: =I30/I22 -> 0.010669117 | J12: =J30/J22 -> -0.0014462406 | K12: =K30/K22 -> 0.0068402408 | L12: =L30/L22 -> 0.0038168971 | M12: =AVERAGE(H12:L12) -> 0.0067453217 | N12: =M12 -> 0.0067453217 | O12: =N12 -> 0.0067453217 | P12: =O12 -> 0.0067453217 | Q12: =P12 -> 0.0067453217
C13: Dividend Payout Ratio | H13: =H90/H33 -> 0 | I13: =I90/I33 -> 0 | J13: =J90/J33 -> 0 | K13: =K90/K33 -> 0 | L13: =L90/L33 -> 0 | M13: =AVERAGE(H13:L13) -> 0 | N13: =M13 -> 0 | O13: =N13 -> 0 | P13: =O13 -> 0 | Q13: =P13 -> 0
C14: Day Sale's Oustanding | H14: 0 | I14: =H14 -> 0 | J14: =I14 -> 0 | K14: =J14 -> 0 | L14: =K14 -> 0 | M14: =L14 -> 0 | N14: =M14 -> 0 | O14: =N14 -> 0 | P14: =O14 -> 0 | Q14: =P14 -> 0
C15: Day Inventory Outstanding | H15: 0 | I15: =H15 -> 0 | J15: =I15 -> 0 | K15: =J15 -> 0 | L15: =K15 -> 0 | M15: =L15 -> 0 | N15: =M15 -> 0 | O15: =N15 -> 0 | P15: =O15 -> 0 | Q15: =P15 -> 0
C16: Day Payable Oustanding | H16: =H54/-H23*365 -> 17.636121 | I16: =I54/-I23*365 -> 12.786864 | J16: =J54/-J23*365 -> 13.837194 | K16: =K54/-K23*365 -> 15.612679 | L16: =L54/-L23*365 -> 14.123254 | M16: =AVERAGE(H16:L16) -> 14.799222 | N16: =M16 -> 14.799222 | O16: =N16 -> 14.799222 | P16: =O16 -> 14.799222 | Q16: =P16 -> 14.799222
C17: Capital Assets Turnover Ratio | H17: =H22/(H45) -> 22.439667 | I17: =I22/(I45) -> 22.610686 | J17: =J22/(J45) -> 22.611172 | K17: =K22/(K45) -> 24.471102 | L17: =L22/(L45) -> 22.542488 | M17: =AVERAGE(H17:L17) -> 22.935023 | N17: =M17 -> 22.935023 | O17: =N17 -> 22.935023 | P17: =O17 -> 22.935023 | Q17: =P17 -> 22.935023
C18: Tax Rate (% of PBT) | H18: =-H32/H31 -> 0.12853599 | I18: =-I32/I31 -> 0.1566808 | J18: =-J32/J31 -> 0.1363462 | K18: =-K32/K31 -> 0.13012965 | L18: =-L32/L31 -> 0.14055437 | M18: =AVERAGE(H18:L18) -> 0.1384494 | N18: =M18 -> 0.1384494 | O18: =N18 -> 0.1384494 | P18: =O18 -> 0.1384494 | Q18: =P18 -> 0.1384494
A20: INCOME STATEMENT
B22: Revenue | H22: ='Historical Data'!H5 -> 29697844 | I22: ='Historical Data'!I5 -> 31615550 | J22: ='Historical Data'!J5 -> 33723297 | K22: ='Historical Data'!K5 -> 39000966 | L22: ='Historical Data'!L5 -> 45183036 | M22: =L22*(1+M7) -> 50223789 | N22: =M22*(1+N7) -> 55465089 | O22: =N22*(1+O7) -> 60879593 | P22: =O22*(1+P7) -> 66438895 | Q22: =P22*(1+Q7) -> 72114084
B23: Less: Cost of Good Sold | H23: =-'Historical Data'!H6 -> -17332683 | I23: =-'Historical Data'!I6 -> -19168285 | J23: =-'Historical Data'!J6 -> -19715368 | K23: =-'Historical Data'!K6 -> -21038464 | L23: =-'Historical Data'!L6 -> -23275329 | M23: =M22*-M8 -> -28417801 | N23: =N22*-N8 -> -31383452 | O23: =O22*-O8 -> -34447106 | P23: =P22*-P8 -> -37592689 | Q23: =Q22*-Q8 -> -40803845
B24: Gross Profit | H24: =SUM(H22:H23) -> 12365161 | I24: =SUM(I22:I23) -> 12447265 | J24: =SUM(J22:J23) -> 14007929 | K24: =SUM(K22:K23) -> 17962502 | L24: =SUM(L22:L23) -> 21907707 | M24: =SUM(M22:M23) -> 21805988 | N24: =SUM(N22:N23) -> 24081637 | O24: =SUM(O22:O23) -> 26432487 | ... Q24: =SUM(Q22:Q23) -> 31310239
B25: Less: Operating Expense | H25: =-SUM('Historical Data'!H7:H9) -> -6170652 | I25: =-SUM('Historical Data'!I7:I9) -> -6814434 | J25: =-SUM('Historical Data'!J7:J9) -> -7053926 | K25: =-SUM('Historical Data'!K7:K9) -> -7544888 | L25: =-SUM('Historical Data'!L7:L9) -> -8581104 | M25: =M22*-M9 -> -10204118 | N25: =N22*-N9 -> -11269009 | O25: =O22*-O9 -> -12369090 | P25: =P22*-P9 -> -13498590 | Q25: =Q22*-Q9 -> -14651635
B26: EBITDA | H26: =SUM(H24:H25) -> 6194509 | I26: =SUM(I24:I25) -> 5632831 | J26: =SUM(J24:J25) -> 6954003 | K26: =SUM(K24:K25) -> 10417614 | L26: =SUM(L24:L25) -> 13326603 | M26: =SUM(M24:M25) -> 11601870 | N26: =SUM(N24:N25) -> 12812628 | O26: =SUM(O24:O25) -> 14063397 | ... Q26: =SUM(Q24:Q25) -> 16658604
B27: Less: Depreciation & Amortization | H27: =-'Historical Data'!H62 -> -208412 | I27: =-'Historical Data'!I62 -> -336682 | J27: =-'Historical Data'!J62 -> -356947 | K27: =-'Historical Data'!K62 -> -328914 | L27: =-'Historical Data'!L62 -> -333389 | M27: =M111 -> -404999.77 | N27: =N111 -> -367575.02 | O27: =O111 -> -339479.16 | P27: =P111 -> -318586.32 | Q27: =Q111 -> -303190.78
B28: EBIT | H28: =SUM(H26:H27) -> 5986097 | I28: =SUM(I26:I27) -> 5296149 | J28: =SUM(J26:J27) -> 6597056 | K28: =SUM(K26:K27) -> 10088700 | L28: =SUM(L26:L27) -> 12993214 | M28: =SUM(M26:M27) -> 11196870 | N28: =SUM(N26:N27) -> 12445053 | O28: =SUM(O26:O27) -> 13723918 | ... Q28: =SUM(Q26:Q27) -> 16355413
B29: Less: Interest | H29: ='Historical Data'!H13 -> -765620 | I29: ='Historical Data'!I13 -> -706212 | J29: ='Historical Data'!J13 -> -699826 | K29: ='Historical Data'!K13 -> -718733 | L29: ='Historical Data'!L13 -> -776510 | M29: =M118 -> -714102.97 | N29: =N118 -> -714017.03 | O29: =O118 -> -713931.1 | P29: =P118 -> -713845.16 | Q29: =Q118 -> -713759.22
B30: Other Income | H30: ='Historical Data'!H14 -> 411214 | I30: ='Historical Data'!I14 -> 337310 | J30: ='Historical Data'!J14 -> -48772 | K30: ='Historical Data'!K14 -> 266776 | L30: ='Historical Data'!L14 -> 172459 | M30: =M22*M12 -> 338775.62 | N30: =N22*N12 -> 374129.87 | O30: =O22*O12 -> 410652.44 | P30: =P22*P12 -> 448151.72 | Q30: =Q22*Q12 -> 486432.7
B31: Profit Before Tax | H31: =SUM(H28:H30) -> 5631691 | I31: =SUM(I28:I30) -> 4927247 | J31: =SUM(J28:J30) -> 5848458 | K31: =SUM(K28:K30) -> 9636743 | L31: =SUM(L28:L30) -> 12389163 | M31: =SUM(M28:M30) -> 10821543 | N31: =SUM(N28:N30) -> 12105166 | O31: =SUM(O28:O30) -> 13420640 | ... Q31: =SUM(Q28:Q30) -> 16128087
B32: Less: Tax | H32: ='Historical Data'!H16 -> -723875 | I32: ='Historical Data'!I16 -> -772005 | J32: ='Historical Data'!J16 -> -797415 | K32: ='Historical Data'!K16 -> -1254026 | L32: ='Historical Data'!L16 -> -1741351 | M32: =-M31*M18 -> -1498236.1 | N32: =-N31*N18 -> -1675953 | O32: =-O31*O18 -> -1858079.5 | P32: =-P31*P18 -> -2043975 | Q32: =-Q31*Q18 -> -2232923.9
B33: Profit After Tax | H33: =SUM(H31:H32) -> 4907816 | I33: =SUM(I31:I32) -> 4155242 | J33: =SUM(J31:J32) -> 5051043 | K33: =SUM(K31:K32) -> 8382717 | L33: =SUM(L31:L32) -> 10647812 | M33: =SUM(M31:M32) -> 9323306.5 | N33: =SUM(N31:N32) -> 10429213 | O33: =SUM(O31:O32) -> 11562560 | ... Q33: =SUM(Q31:Q32) -> 13895163
A35: BALANCE SHEET
A37: Assets
B38: Current Assets
C39: Cash & Bank | H39: ='Historical Data'!H22 -> 6027804 | I39: ='Historical Data'!I22 -> 5147176 | J39: ='Historical Data'!J22 -> 7116913 | K39: ='Historical Data'!K22 -> 7804733 | L39: ='Historical Data'!L22 -> 9033681 | M39: =M97 -> 18792074 | N39: =N97 -> 29478838 | O39: =O97 -> 41267275 | P39: =P97 -> 54188628 | Q39: =Q97 -> 68267993
C40: Trade Receivable | H40: 0 | I40: =H40 -> 0 | J40: =I40 -> 0 | K40: =J40 -> 0 | L40: =K40 -> 0 | M40: =L40 -> 0 | N40: =M40 -> 0 | O40: =N40 -> 0 | P40: =O40 -> 0 | Q40: =P40 -> 0
C41: Inventories | H41: 0 | I41: =H41 -> 0 | J41: =I41 -> 0 | K41: =J41 -> 0 | L41: =K41 -> 0 | M41: =L41 -> 0 | N41: =M41 -> 0 | O41: =N41 -> 0 | P41: =O41 -> 0 | Q41: =P41 -> 0
C42: Other Current Assets | H42: ='Historical Data'!H24+'Historical Data'!H23 -> 2042021 | I42: ='Historical Data'!I24+'Historical Data'!I23 -> 4119297 | J42: ='Historical Data'!J24+'Historical Data'!J23 -> 2801220 | K42: ='Historical Data'!K24+'Historical Data'!K23 -> 5295646 | L42: ='Historical Data'!L24+'Historical Data'!L23 -> 3986510 | M42: =L42 -> 3986510 | N42: =M42 -> 3986510 | O42: =N42 -> 3986510 | P42: =O42 -> 3986510 | Q42: =P42 -> 3986510
B44: Non-Current Assets
C45: Plant, Property & Equipment | H45: ='Historical Data'!H28 -> 1323453 | I45: ='Historical Data'!I28 -> 1398257 | J45: ='Historical Data'!J28 -> 1491444 | K45: ='Historical Data'!K28 -> 1593756 | L45: ='Historical Data'!L28 -> 2004350 | M45: =M112 -> 1819134.3 | N45: =N112 -> 1680087.5 | O45: =O112 -> 1576688.5 | P45: =P112 -> 1500495.7 | Q45: =Q112 -> 1444751.4
C46: Content Assets | H46: ='Historical Data'!H27 -> 30919539 | I46: ='Historical Data'!I27 -> 32736713 | J46: ='Historical Data'!J27 -> 31658056 | K46: ='Historical Data'!K27 -> 32452462 | L46: ='Historical Data'!L27 -> 32778392 | M46: =L46 -> 32778392 | N46: =M46 -> 32778392 | O46: =N46 -> 32778392 | P46: =O46 -> 32778392 | Q46: =P46 -> 32778392
C47: Goodwill | H47: 0 | I47: =H47 -> 0 | J47: =I47 -> 0 | K47: =J47 -> 0 | L47: =K47 -> 0 | M47: =L47 -> 0 | N47: =M47 -> 0 | O47: =N47 -> 0 | P47: =O47 -> 0 | Q47: =P47 -> 0
C48: Financial Assets | H48: 0 | I48: =H48 -> 0 | J48: =I48 -> 0 | K48: =J48 -> 0 | L48: =K48 -> 0 | M48: =L48 -> 0 | N48: =M48 -> 0 | O48: =N48 -> 0 | P48: =O48 -> 0 | Q48: =P48 -> 0
C49: Other Non-Current | H49: ='Historical Data'!H29 -> 4271846 | I49: ='Historical Data'!I29 -> 5193325 | J49: ='Historical Data'!J29 -> 5664359 | K49: ='Historical Data'!K29 -> 6483777 | L49: ='Historical Data'!L29 -> 7794060 | M49: =L49 -> 7794060 | N49: =M49 -> 7794060 | O49: =N49 -> 7794060 | P49: =O49 -> 7794060 | Q49: =P49 -> 7794060
C50: TOTAL ASSETS | H50: =SUM(H39:H42,H45:H49) -> 44584663 | I50: =SUM(I39:I42,I45:I49) -> 48594768 | J50: =SUM(J39:J42,J45:J49) -> 48731992 | K50: =SUM(K39:K42,K45:K49) -> 53630374 | L50: =SUM(L39:L42,L45:L49) -> 55596993 | M50: =SUM(M39:M42,M45:M49) -> 65170170 | N50: =SUM(N39:N42,N45:N49) -> 75717887 | O50: =SUM(O39:O42,O45:O49) -> 87402925 | ... Q50: =SUM(Q39:Q42,Q45:Q49) -> 1.1427171e+08
A52: Liabilities
B53: Current Liabilities
C54: Trade Payable | H54: ='Historical Data'!H35 -> 837483 | I54: ='Historical Data'!I35 -> 671513 | J54: ='Historical Data'!J35 -> 747412 | K54: ='Historical Data'!K35 -> 899909 | L54: ='Historical Data'!L35 -> 900612 | M54: =-M23/365*M16 -> 1152222.9 | N54: =-N23/365*N16 -> 1272467.6 | O54: =-O23/365*O16 -> 1396686 | P54: =-P23/365*P16 -> 1524226.2 | Q54: =-Q23/365*Q16 -> 1654425.1
C55: Other Current Liabilities | H55: =SUM('Historical Data'!H36:H37,'Historical Data'!H34) -> 6951660 | I55: =SUM('Historical Data'!I36:I37,'Historical Data'!I34) -> 7259461 | J55: =SUM('Historical Data'!J36:J37,'Historical Data'!J34) -> 7713399 | K55: =SUM('Historical Data'!K36:K37,'Historical Data'!K34) -> 8071038 | L55: =SUM('Historical Data'!L36:L37,'Historical Data'!L34) -> 9081453 | M55: =L55 -> 9081453 | N55: =M55 -> 9081453 | O55: =N55 -> 9081453 | P55: =O55 -> 9081453 | Q55: =P55 -> 9081453
B57: Non-Current Liabilities
C58: Borrowing | H58: ='Historical Data'!H42+'Historical Data'!H38 -> 15392895 | I58: ='Historical Data'!I42+'Historical Data'!I38 -> 14353076 | J58: ='Historical Data'!J42+'Historical Data'!J38 -> 14543261 | K58: ='Historical Data'!K42+'Historical Data'!K38 -> 15582804 | L58: ='Historical Data'!L42+'Historical Data'!L38 -> 14462836 | M58: =M117 -> 14461096 | N58: =N117 -> 14459355 | O58: =O117 -> 14457615 | P58: =P117 -> 14455874 | Q58: =Q117 -> 14454134
C59: Other Non-Current Liabilities | H59: =SUM('Historical Data'!H43,'Historical Data'!H41) -> 5553377 | I59: =SUM('Historical Data'!I43,'Historical Data'!I41) -> 5533317 | J59: =SUM('Historical Data'!J43,'Historical Data'!J41) -> 5139607 | K59: =SUM('Historical Data'!K43,'Historical Data'!K41) -> 4333056 | L59: =SUM('Historical Data'!L43,'Historical Data'!L41) -> 4536604 | M59: =L59 -> 4536604 | N59: =M59 -> 4536604 | O59: =N59 -> 4536604 | P59: =O59 -> 4536604 | Q59: =P59 -> 4536604
C60: TOTAL LABILITIES | H60: =SUM(H54:H55,H58:H59) -> 28735415 | I60: =SUM(I54:I55,I58:I59) -> 27817367 | J60: =SUM(J54:J55,J58:J59) -> 28143679 | K60: =SUM(K54:K55,K58:K59) -> 28886807 | L60: =SUM(L54:L55,L58:L59) -> 28981505 | M60: =SUM(M54:M55,M58:M59) -> 29231375 | N60: =SUM(N54:N55,N58:N59) -> 29349880 | O60: =SUM(O54:O55,O58:O59) -> 29472357 | ... Q60: =SUM(Q54:Q55,Q58:Q59) -> 29726616
B62: Equity | H62: ='Historical Data'!H48 -> 4024561 | I62: ='Historical Data'!I48 -> 4637601 | J62: ='Historical Data'!J48 -> 5145172 | K62: ='Historical Data'!K48 -> 6252126 | L62: ='Historical Data'!L48 -> 7286410 | M62: =L62+M22*M122 -> 7286410 | N62: =M62+N22*N122 -> 7286410 | O62: =N62+O22*O122 -> 7286410 | P62: =O62+P22*P122 -> 7286410 | Q62: =P62+Q22*Q122 -> 7286410
B63: Other Equity | H63: =SUM('Historical Data'!H49:H51) -> 11824687 | I63: =SUM('Historical Data'!I49:I51) -> 16139800 | J63: =SUM('Historical Data'!J49:J51) -> 15443141 | K63: =SUM('Historical Data'!K49:K51) -> 18491441 | L63: =SUM('Historical Data'!L49:L51) -> 19329078 | M63: =L63+M33 -> 28652385 | N63: =M63+N33 -> 39081598 | O63: =N63+O33 -> 50644158 | P63: =O63+P33 -> 63363518 | Q63: =P63+Q33 -> 77258681
B64: TOTAL SHAREHOLDER FUND | H64: =SUM(H62:H63) -> 15849248 | I64: =SUM(I62:I63) -> 20777401 | J64: =SUM(J62:J63) -> 20588313 | K64: =SUM(K62:K63) -> 24743567 | L64: =SUM(L62:L63) -> 26615488 | M64: =SUM(M62:M63) -> 35938795 | N64: =SUM(N62:N63) -> 46368008 | O64: =SUM(O62:O63) -> 57930568 | ... Q64: =SUM(Q62:Q63) -> 84545091
B65: Non-Controlling Interest | H65: 0 | I65: =H65 -> 0 | J65: =I65 -> 0 | K65: =J65 -> 0 | L65: =K65 -> 0 | M65: =L65 -> 0 | N65: =M65 -> 0 | O65: =N65 -> 0 | P65: =O65 -> 0 | Q65: =P65 -> 0
B66: Total Liabilities and Equity | H66: =SUM(H60,H64) -> 44584663 | I66: =SUM(I60,I64) -> 48594768 | J66: =SUM(J60,J64) -> 48731992 | K66: =SUM(K60,K64) -> 53630374 | L66: =SUM(L60,L64) -> 55596993 | M66: =SUM(M60,M64) -> 65170170 | N66: =SUM(N60,N64) -> 75717887 | O66: =SUM(O60,O64) -> 87402925 | ... Q66: =SUM(Q60,Q64) -> 1.1427171e+08
D68: CHECK | H68: =IF(ABS(H50-H66)<50000,"TALLIED","ERROR") -> TALLIED | I68: =IF(ABS(I50-I66)<50000,"TALLIED","ERROR") -> TALLIED | J68: =IF(ABS(J50-J66)<50000,"TALLIED","ERROR") -> TALLIED | K68: =IF(ABS(K50-K66)<50000,"TALLIED","ERROR") -> TALLIED | L68: =IF(ABS(L50-L66)<50000,"TALLIED","ERROR") -> TALLIED | M68: =IF(ABS(M50-M66)<50000,"TALLIED","ERROR") -> TALLIED | N68: =IF(ABS(N50-N66)<50000,"TALLIED","ERROR") -> TALLIED | O68: =IF(ABS(O50-O66)<50000,"TALLIED","ERROR") -> TALLIED | ... Q68: =IF(ABS(Q50-Q66)<50000,"TALLIED","ERROR") -> TALLIED
A70: CASH FlOW
A72: Cash Flow From Operation
B73: Profit After Tax | H73: ='Historical Data'!H57 -> 5116228 | I73: ='Historical Data'!I57 -> 4491924 | J73: ='Historical Data'!J57 -> 5407990 | K73: ='Historical Data'!K57 -> 8711631 | L73: ='Historical Data'!L57 -> 10981201 | M73: =M33 -> 9323306.5 | N73: =N33 -> 10429213 | O73: =O33 -> 11562560 | P73: =P33 -> 12719361 | Q73: =Q33 -> 13895163
C74: Add: Depreciation & Amortization | H74: ='Historical Data'!H62 -> 208412 | I74: ='Historical Data'!I62 -> 336682 | J74: ='Historical Data'!J62 -> 356947 | K74: ='Historical Data'!K62 -> 328914 | L74: ='Historical Data'!L62 -> 333389 | M74: =-M111 -> 404999.77 | N74: =-N111 -> 367575.02 | O74: =-O111 -> 339479.16 | P74: =-P111 -> 318586.32 | Q74: =-Q111 -> 303190.78
C75: Add/Less: Working capital | H75: =H106 -> -241977 | I75: =I106 -> -758087 | J75: =J106 -> -116148 | K75: =K106 -> -33075 | L75: =L106 -> -456220 | M75: =M106 -> 251610.91 | N75: =N106 -> 120244.72 | O75: =O106 -> 124218.34 | ... Q75: =Q106 -> 130198.92
C76: Add/Less: Other Adjustment | H76: =SUM('Historical Data'!H59:H61,'Historical Data'!H63:H66) -> -4690053 | I76: =SUM('Historical Data'!I59:I61,'Historical Data'!I63:I66) -> -2044262 | J76: =SUM('Historical Data'!J59:J61,'Historical Data'!J63:J66) -> 1625512 | K76: =SUM('Historical Data'!K59:K61,'Historical Data'!K63:K66) -> -1646106 | L76: =SUM('Historical Data'!L59:L61,'Historical Data'!L63:L66) -> -709097 | M76: =-SUM(M29:M30) -> 375327.35 | N76: =-SUM(N29:N30) -> 339887.16 | O76: =-SUM(O29:O30) -> 303278.65 | P76: =-SUM(P29:P30) -> 265693.44 | Q76: =-SUM(Q29:Q30) -> 227326.52
C77: Total | H77: =SUM(H73:H76) -> 392610 | I77: =SUM(I73:I76) -> 2026257 | J77: =SUM(J73:J76) -> 7274301 | K77: =SUM(K73:K76) -> 7361364 | L77: =SUM(L73:L76) -> 10149273 | M77: =SUM(M73:M76) -> 10355245 | N77: =SUM(N73:N76) -> 11256920 | O77: =SUM(O73:O76) -> 12329536 | ... Q77: =SUM(Q73:Q76) -> 14555879
A79: Cash Flow from Investing Activities
B80: Investment in PP&E | H80: ='Historical Data'!H76 -> -524585 | I80: ='Historical Data'!I76 -> -407729 | J80: ='Historical Data'!J76 -> -348552 | K80: ='Historical Data'!K76 -> -439538 | L80: ='Historical Data'!L76 -> -688220 | M80: =-M110 -> -219784.1 | N80: =-N110 -> -228528.21 | O80: =-O110 -> -236080.18 | P80: =-P110 -> -242393.54 | Q80: =-Q110 -> -247446.41
B81: Sale proceeds from sale of PP&E
B82: Purchase/sale of investments | H82: =SUM('Historical Data'!H77:H80) -> -815268 | I82: =SUM('Historical Data'!I77:I80) -> -1668663 | J82: =SUM('Historical Data'!J77:J80) -> 890303 | K82: =SUM('Historical Data'!K77:K80) -> -1742246 | L82: =SUM('Historical Data'!L77:L80) -> 1729908
B83: Dividend Income
B84: Interest income | M84: =M30 -> 338775.62 | N84: =N30 -> 374129.87 | O84: =O30 -> 410652.44 | P84: =P30 -> 448151.72 | Q84: =Q30 -> 486432.7
B85: Cash Flow from Investing Activities | H85: =SUM(H80:H84) -> -1339853 | I85: =SUM(I80:I84) -> -2076392 | J85: =SUM(J80:J84) -> 541751 | K85: =SUM(K80:K84) -> -2181784 | L85: =SUM(L80:L84) -> 1041688 | M85: =SUM(M80:M84) -> 118991.52 | N85: =SUM(N80:N84) -> 145601.66 | O85: =SUM(O80:O84) -> 174572.27 | ... Q85: =SUM(Q80:Q84) -> 238986.28
A87: Cash Flow from Financing Activities
B88: Issuance/repayment of debt | H88: =SUM('Historical Data'!H84:H85,'Historical Data'!H88:H89) -> -724168 | I88: =SUM('Historical Data'!I84:I85,'Historical Data'!I88:I89) -> -700000 | J88: =SUM('Historical Data'!J84:J85,'Historical Data'!J88:J89) -> -75446 | K88: =SUM('Historical Data'!K84:K85,'Historical Data'!K88:K89) -> 1356432 | L88: =SUM('Historical Data'!L84:L85,'Historical Data'!L88:L89) -> -1885421 | M88: =M116 -> -1740.4939 | N88: =N116 -> -1740.4939 | O88: =O116 -> -1740.4939 | P88: =P116 -> -1740.4939 | Q88: =Q116 -> -1740.4939
B89: Proceeds from issue of Common Shares | H89: ='Historical Data'!H86+'Historical Data'!H87 -> -425608 | I89: ='Historical Data'!I86+'Historical Data'!I87 -> 35746 | J89: ='Historical Data'!J86+'Historical Data'!J87 -> -5875357 | K89: ='Historical Data'!K86+'Historical Data'!K87 -> -5430859 | L89: ='Historical Data'!L86+'Historical Data'!L87 -> -8460202 | M89: 0 | N89: 0 | O89: 0 | P89: 0 | Q89: 0
B90: Dividend paid
B91: Interest paid | M91: =M118 -> -714102.97 | N91: =N118 -> -714017.03 | O91: =O118 -> -713931.1 | P91: =P118 -> -713845.16 | Q91: =Q118 -> -713759.22
B92: Cash Flow from Financing Activities | H92: =SUM(H88:H91) -> -1149776 | I92: =SUM(I88:I91) -> -664254 | J92: =SUM(J88:J91) -> -5950803 | K92: =SUM(K88:K91) -> -4074427 | L92: =SUM(L88:L91) -> -10345623 | M92: =SUM(M88:M91) -> -715843.46 | N92: =SUM(N88:N91) -> -715757.53 | O92: =SUM(O88:O91) -> -715671.59 | ... Q92: =SUM(Q88:Q91) -> -715499.72
B94: Effect of exchange rate changes on cash | H94: ='Historical Data'!H92 -> -86740 | I94: ='Historical Data'!I92 -> -170140 | J94: ='Historical Data'!J92 -> 82684 | K94: ='Historical Data'!K92 -> -416331 | L94: ='Historical Data'!L92 -> 386519 | M94: 0 | N94: 0 | O94: 0 | P94: 0 | Q94: 0
A95: Net decrease in Cash and Cash Equivalents | H95: =SUM(H77,H85,H94,H92) -> -2183759 | I95: =SUM(I77,I85,I94,I92) -> -884529 | J95: =SUM(J77,J85,J94,J92) -> 1947933 | K95: =SUM(K77,K85,K94,K92) -> 688822 | L95: =SUM(L77,L85,L94,L92) -> 1231857 | M95: =SUM(M77,M85,M94,M92) -> 9758392.6 | N95: =SUM(N77,N85,N94,N92) -> 10686764 | O95: =SUM(O77,O85,O94,O92) -> 11788437 | ... Q95: =SUM(Q77,Q85,Q94,Q92) -> 14079365
B96: Opening Cash Balance | H96: ='Historical Data'!H94 -> 8238870 | I96: =H97 -> 6055111 | J96: =I97 -> 5170582 | K96: =J97 -> 7118515 | L96: =K97 -> 7807337 | M96: =L39 -> 9033681 | N96: =M97 -> 18792074 | O96: =N97 -> 29478838 | P96: =O97 -> 41267275 | Q96: =P97 -> 54188628
B97: Closing Cash Balance | H97: =SUM(H95:H96) -> 6055111 | I97: =SUM(I95:I96) -> 5170582 | J97: =SUM(J95:J96) -> 7118515 | K97: =SUM(K95:K96) -> 7807337 | L97: =SUM(L95:L96) -> 9039194 | M97: =SUM(M95:M96) -> 18792074 | N97: =SUM(N95:N96) -> 29478838 | O97: =SUM(O95:O96) -> 41267275 | ... Q97: =SUM(Q95:Q96) -> 68267993
A99: Supporting Schedule
A101: Working Capital
B102: Trade Receivable | H102: =H40 -> 0 | I102: =I40 -> 0 | J102: =J40 -> 0 | K102: =K40 -> 0 | L102: =L40 -> 0 | M102: =L40-M40 -> 0 | N102: =M40-N40 -> 0 | O102: =N40-O40 -> 0 | P102: =O40-P40 -> 0 | Q102: =P40-Q40 -> 0
B103: Inventory | H103: =H41 -> 0 | I103: =I41 -> 0 | J103: =J41 -> 0 | K103: =K41 -> 0 | L103: =L41 -> 0 | M103: =L41-M41 -> 0 | N103: =M41-N41 -> 0 | O103: =N41-O41 -> 0 | P103: =O41-P41 -> 0 | Q103: =P41-Q41 -> 0
B104: Trade Payable | H104: ='Historical Data'!H69 -> 145115 | I104: ='Historical Data'!I69 -> -158543 | J104: ='Historical Data'!J69 -> 93502 | K104: ='Historical Data'!K69 -> 121353 | L104: ='Historical Data'!L69 -> -8039 | M104: =M54-L54 -> 251610.91 | N104: =N54-M54 -> 120244.72 | O104: =O54-N54 -> 124218.34 | P104: =P54-O54 -> 127540.24 | Q104: =Q54-P54 -> 130198.92
B105: Other | H105: =SUM('Historical Data'!H68,'Historical Data'!H70:H72) -> -387092 | I105: =SUM('Historical Data'!I68,'Historical Data'!I70:I72) -> -599544 | J105: =SUM('Historical Data'!J68,'Historical Data'!J70:J72) -> -209650 | K105: =SUM('Historical Data'!K68,'Historical Data'!K70:K72) -> -154428 | L105: =SUM('Historical Data'!L68,'Historical Data'!L70:L72) -> -448181
B106: Total | H106: =SUM(H102:H105) -> -241977 | I106: =SUM(I102:I105) -> -758087 | J106: =SUM(J102:J105) -> -116148 | K106: =SUM(K102:K105) -> -33075 | L106: =SUM(L102:L105) -> -456220 | M106: =SUM(M102:M105) -> 251610.91 | N106: =SUM(N102:N105) -> 120244.72 | O106: =SUM(O102:O105) -> 124218.34 | ... Q106: =SUM(Q102:Q105) -> 130198.92
A108: Depreciation & Amortization
B109: Opening Balance | I109: =H112 -> 1323453 | J109: =I112 -> 1398257 | K109: =J112 -> 1491444 | L109: =K112 -> 1593756 | M109: =L112 -> 2004350 | N109: =M112 -> 1819134.3 | O109: =N112 -> 1680087.5 | P109: =O112 -> 1576688.5 | Q109: =P112 -> 1500495.7
B110: Add/Less: Purchase/sale | I110: =I112-I111-I109 -> 411486 | J110: =J112-J111-J109 -> 450134 | K110: =K112-K111-K109 -> 431226 | L110: =L112-L111-L109 -> 743983 | M110: =(M22-L22)/M17 -> 219784.1 | N110: =(N22-M22)/N17 -> 228528.21 | O110: =(O22-N22)/O17 -> 236080.18 | P110: =(P22-O22)/P17 -> 242393.54 | Q110: =(Q22-P22)/Q17 -> 247446.41
B111: Less: Depreciation & Amortization | H111: =-'Historical Data'!H62 -> -208412 | I111: =-'Historical Data'!I62 -> -336682 | J111: =-'Historical Data'!J62 -> -356947 | K111: =-'Historical Data'!K62 -> -328914 | L111: =-'Historical Data'!L62 -> -333389 | M111: =-M109*M10 -> -404999.77 | N111: =-N109*N10 -> -367575.02 | O111: =-O109*O10 -> -339479.16 | P111: =-P109*P10 -> -318586.32 | Q111: =-Q109*Q10 -> -303190.78
B112: Closing Balance | H112: ='Historical Data'!H28 -> 1323453 | I112: ='Historical Data'!I28 -> 1398257 | J112: ='Historical Data'!J28 -> 1491444 | K112: ='Historical Data'!K28 -> 1593756 | L112: ='Historical Data'!L28 -> 2004350 | M112: =SUM(M109:M111) -> 1819134.3 | N112: =SUM(N109:N111) -> 1680087.5 | O112: =SUM(O109:O111) -> 1576688.5 | P112: =SUM(P109:P111) -> 1500495.7 | Q112: =SUM(Q109:Q111) -> 1444751.4
A114: Debt Schedule
B115: Opening Balance | I115: =H117 -> 15392895 | J115: =I117 -> 14353076 | K115: =J117 -> 14543261 | L115: =K117 -> 15582804 | M115: =L117 -> 14462836 | N115: =M117 -> 14461096 | O115: =N117 -> 14459355 | P115: =O117 -> 14457615 | Q115: =P117 -> 14455874
B116: Issuance/repayment | I116: =I117-I115 -> -1039819 | J116: =J117-J115 -> 190185 | K116: =K117-K115 -> 1039543 | L116: =L117-L115 -> -1119968 | M116: =-AVERAGE('Re-Payment'!H19:Q19) -> -1740.4939 | N116: =M116 -> -1740.4939 | O116: =N116 -> -1740.4939 | P116: =O116 -> -1740.4939 | Q116: =P116 -> -1740.4939
B117: Closing Balance | H117: =H58 -> 15392895 | I117: =I58 -> 14353076 | J117: =J58 -> 14543261 | K117: =K58 -> 15582804 | L117: =L58 -> 14462836 | M117: =SUM(M115:M116) -> 14461096 | N117: =SUM(N115:N116) -> 14459355 | O117: =SUM(O115:O116) -> 14457615 | P117: =SUM(P115:P116) -> 14455874 | Q117: =SUM(Q115:Q116) -> 14454134
B118: Interest Expense | H118: =H29 -> -765620 | I118: =I29 -> -706212 | J118: =J29 -> -699826 | K118: =K29 -> -718733 | L118: =L29 -> -776510 | M118: =-M115*M11 -> -714102.97 | N118: =-N115*N11 -> -714017.03 | O118: =-O115*O11 -> -713931.1 | P118: =-P115*P11 -> -713845.16 | Q118: =-Q115*Q11 -> -713759.22
A120: DCF VALUATION
D122: Assumption's
...

Sheet Re-Payment
A1: NETFLIX, INC.
A2: Loan Repayment
D4: UNSECURED — SENIOR NOTES (fixed rate, publicly registered) | H4: 2026 | I4: =H4+1 -> 2027 | J4: =I4+1 -> 2028 | K4: =J4+1 -> 2029 | L4: =K4+1 -> 2030 | M4: =L4+1 -> 2031 | N4: =M4+1 -> 2032 | O4: =N4+1 -> 2033 | P4: =O4+1 -> 2034 | Q4: =P4+1 -> 2035
D5: 4.375% Senior Notes (issued Oct 2016, matures Nov 2026) | H5: 1000 | I5: 0 | J5: 0 | K5: 0 | L5: 0 | M5: 0 | N5: 0 | O5: 0 | P5: 0 | Q5: 0
D6: 3.625% Senior Notes (issued May 2017, matures May 2027) | H6: 0 | I6: 1526 | J6: 0 | K6: 0 | L6: 0 | M6: 0 | N6: 0 | O6: 0 | P6: 0 | Q6: 0
D7: 4.875% Senior Notes (issued Oct 2017, matures Apr 2028) | H7: 0 | I7: 0 | J7: 1600 | K7: 0 | L7: 0 | M7: 0 | N7: 0 | O7: 0 | P7: 0 | Q7: 0
D8: 5.875% Senior Notes (issued Apr 2018, matures Nov 2028) | H8: 0 | I8: 0 | J8: 1900 | K8: 0 | L8: 0 | M8: 0 | N8: 0 | O8: 0 | P8: 0 | Q8: 0
D9: 4.625% Senior Notes (issued Oct 2018, matures May 2029) | H9: 0 | I9: 0 | J9: 0 | K9: 1292 | L9: 0 | M9: 0 | N9: 0 | O9: 0 | P9: 0 | Q9: 0
D10: 6.375% Senior Notes (issued Oct 2018, matures May 2029) | H10: 0 | I10: 0 | J10: 0 | K10: 800 | L10: 0 | M10: 0 | N10: 0 | O10: 0 | P10: 0 | Q10: 0
D11: 3.875% Senior Notes (issued Apr 2019, matures Nov 2029) | H11: 0 | I11: 0 | J11: 0 | K11: 1409 | L11: 0 | M11: 0 | N11: 0 | O11: 0 | P11: 0 | Q11: 0
D12: 5.375% Senior Notes (issued Apr 2019, matures Nov 2029) | H12: 0 | I12: 0 | J12: 0 | K12: 900 | L12: 0 | M12: 0 | N12: 0 | O12: 0 | P12: 0 | Q12: 0
D13: 3.625% Senior Notes (issued Oct 2019, matures June 2030) | H13: 0 | I13: 0 | J13: 0 | K13: 0 | L13: 1292 | M13: 0 | N13: 0 | O13: 0 | P13: 0 | Q13: 0
D14: 4.875% Senior Notes (issued Oct 2019, matures June 2030) | H14: 0 | I14: 0 | J14: 0 | K14: 0 | L14: 1000 | M14: 0 | N14: 0 | O14: 0 | P14: 0 | Q14: 0
D15: 4.900% Senior Notes (issued Aug 2024, matures Aug 2034) | H15: 0 | I15: 0 | J15: 0 | K15: 0 | L15: 0 | M15: 0 | N15: 0 | O15: 0 | P15: 1000 | Q15: 0
D16: 5.400% Senior Notes (issued Aug 2024, matures Aug 2054) | H16: 0 | I16: 0 | J16: 0 | K16: 0 | L16: 0 | M16: 0 | N16: 0 | O16: 0 | P16: 0 | Q16: 800
D17: OPERATING LEASE LIABILITIES (undiscounted future payments)
D18: Operating lease payments due | H18: 555.684 | I18: 481.542 | J18: 422.982 | K18: 351.107 | L18: 292.154 | M18: 0 | N18: 0 | O18: 0 | P18: 0 | Q18: 782.47
D19: TOTAL REPAYMENT | H19: =H5+H6+H7+H8+H9+H10+H11+H12+H13+H14+H15+H16+H18 -> 1555.684 | I19: =I5+I6+I7+I8+I9+I10+I11+I12+I13+I14+I15+I16+I18 -> 2007.542 | J19: =J5+J6+J7+J8+J9+J10+J11+J12+J13+J14+J15+J16+J18 -> 3922.982 | K19: =K5+K6+K7+K8+K9+K10+K11+K12+K13+K14+K15+K16+K18 -> 4752.107 | L19: =L5+L6+L7+L8+L9+L10+L11+L12+L13+L14+L15+L16+L18 -> 2584.154 | M19: =M5+M6+M7+M8+M9+M10+M11+M12+M13+M14+M15+M16+M18 -> 0 | N19: =N5+N6+N7+N8+N9+N10+N11+N12+N13+N14+N15+N16+N18 -> 0 | O19: =O5+O6+O7+O8+O9+O10+O11+O12+O13+O14+O15+O16+O18 -> 0 | ... Q19: =Q5+Q6+Q7+Q8+Q9+Q10+Q11+Q12+Q13+Q14+Q15+Q16+Q18 -> 1582.47

Sheet Scenario
A1: NETFLIX, INC.
A2: Live Scenario
D5: Scenarios | E5: Growth % | H5: =Model!M2 -> 2026 | I5: =Model!N2 -> 2027 | J5: =Model!O2 -> 2028 | K5: =Model!P2 -> 2029 | L5: =Model!Q2 -> 2030
D6: Base Case | E6: =AVERAGE(Model!I7:L7) -> 0.11156296 | H6: =E6 -> 0.11156296 | I6: =H6*(1-$E$8) -> 0.10435891 | J6: =I6*(1-$E$8) -> 0.097620043 | K6: =J6*(1-$E$8) -> 0.091316334 | L6: =K6*(1-$E$8) -> 0.085419681
D7: Bull Case | E7: =MAX(Model!I7:L7) -> 0.15851069 | H7: =E7 -> 0.15851069 | I7: =H7*(1-$E$8) -> 0.14827503 | J7: =I7*(1-$E$8) -> 0.13870033 | K7: =J7*(1-$E$8) -> 0.12974391 | L7: =K7*(1-$E$8) -> 0.12136584
D8: Bear Case | E8: =MIN(Model!I7:L7) -> 0.064573913 | H8: =E8 -> 0.064573913 | I8: =H8*(1-$E$8) -> 0.060404123 | J8: =I8*(1-$E$8) -> 0.056503592 | K8: =J8*(1-$E$8) -> 0.052854934 | L8: =K8*(1-$E$8) -> 0.049441884
D9: Annual growth tapering | E9: =10% -> 0.1

Sheet WACC
A1: NETFLIX, INC.
A2: Weighted-Average Cost of Capital (WACC)
A3: All Amounts in $ Millions Unless Otherwise Stated
A5: Comparable Companies Beta
H7: Equity | I7: Total | J7: Debt/ | K7: Debt/ | L7: Tax | M7: Levered | N7: Unlevered
D8: Company Name | H8: Value | I8: Debt | J8: Equity | K8: Capital | L8: Rate % | M8: Beta | N8: Beta
D9: The Walt Disney Company | H9: =Comps!K8 -> 194698.3 | I9: =Comps!L8 -> 42030 | J9: =I9/H9 -> 0.21587245 | K9: =I9/(H9+I9) -> 0.17754531 | L9: 0.21 | M9: 1.44 | N9: =M9/(1+J9*(1+K9)) -> 1.1481426
D10: Comcast Corporation | H10: =Comps!K9 -> 127688.4 | I10: =Comps!L9 -> 99090 | J10: =I10/H10 -> 0.77602977 | K10: =I10/(H10+I10) -> 0.43694638 | L10: =L9 -> 0.21 | M10: 1 | N10: =M10/(1+J10*(1+K10)) -> 0.47278794
D11: Paramount Skydance Corporation | H11: =Comps!K10 -> 17307.227 | I11: =Comps!L10 -> 14520 | J11: =I11/H11 -> 0.83895587 | K11: =I11/(H11+I11) -> 0.45621316 | L11: =L10 -> 0.21 | M11: 1.26 | N11: =M11/(1+J11*(1+K11)) -> 0.56713364
D12: Fox Corporation | H12: =Comps!K11 -> 32762.772 | I12: =Comps!L11 -> 6600 | J12: =I12/H12 -> 0.20144816 | K12: =I12/(H12+I12) -> 0.16767112 | L12: =L11 -> 0.21 | M12: 0.5 | N12: =M12/(1+J12*(1+K12)) -> 0.40478449
D13: Average | J13: =AVERAGE(J9:J12) -> 0.50807656 | K13: =AVERAGE(K9:K12) -> 0.30959399 | L13: =AVERAGE(L9:L12) -> 0.21 | M13: =AVERAGE(M9:M12) -> 1.05 | N13: =AVERAGE(N9:N12) -> 0.64821217
D14: Median | J14: =MEDIAN(J9:J12) -> 0.49595111 | K14: =MEDIAN(K9:K12) -> 0.30724584 | L14: =MEDIAN(L9:L12) -> 0.21 | M14: =MEDIAN(M9:M12) -> 1.13 | N14: =MEDIAN(N9:N12) -> 0.51996079
D16: Netflix, Inc. | H16: =Comps!K16 -> 324370.93 | I16: =Comps!L16 -> 14462.836
A18: WACC Calculation
C20: Target Capital Structure
D21: Proportion of Debt | I21: =Comps!L16/(Comps!K16+Comps!L16) -> 0.042684164
D22: Proportion of Equity | I22: =1-I21 -> 0.95731584
C24: Current Capital Structure
D25: Market Cap | I25: =H16 -> 324370.93
D26: Total Debt | I26: =I16 -> 14462.836
D27: Debt / Equity | I27: =I26/I25 -> 0.044587338
C29: Cost of Debt
D30: Pre-Tax Cost of Debt | I30: =-'Historical Data'!L13/('Historical Data'!L38+'Historical Data'!L42) -> 0.053690023
D31: Tax Rate | I31: =Model!M18 -> 0.1384494
D32: After-Tax Cost of Debt | I32: =I30*(1-I31) -> 0.046256672
C34: Cost of Equity
D35: Risk Free Rate | I35: 0.05
D36: Equity Risk Premium | I36: ='Market Data'!J9 -> 0.17353366
D37: Levered Equity Beta (relevered to NFLX capital structure) | I37: =N14*(1+I27)*(1-I31) -> 0.46794643
D38: Cost of Equity | I38: =I35+I37*I36 -> 0.13120446
D40: WACC | I40: =(I21*I32)+(I38*I22) -> 0.12757853

Sheet Market Data
A1: NETFLIX, INC.
A2: Market Data ( Nasdaq)
F5: Index (Nasdaq)
E6: DATE | F6: Closing Price
E7: 46280 | F7: 25981.57 | I7: Period (yrs) | J7: 10
E8: 46279 | F8: 26186.41
E9: 46276 | F9: 26333.04 | I9: Return's | J9: =_xlfn.RRI(J7,F2518,F7) -> 0.17353366
E10: 46275 | F10: 26081.72
E11: 46274 | F11: 26253.34
E12: 46273 | F12: 26421.41
E13: 46269 | F13: 26506.99
E14: 46268 | F14: 26584.06
E15: 46267 | F15: 26217.83
E16: 46266 | F16: 26099.77
E17: 46265 | F17: 26370.89
E18: 46262 | F18: 26402.42
E19: 46261 | F19: 26541.35
E20: 46260 | F20: 26130.2
E21: 46259 | F21: 26151.3
... E2518: 42629 | F2518: 5244.57

Sheet Comps Data
A1: NETFLIX, INC.
A2: Comps Data
D4: Company | H4: Ticker | I4: Price | J4: Shares | K4: Debt | L4: Cash | M4: Sales | N4: EBITDA | O4: Net Income
D5: Netflix, Inc. | H5: NFLX | I5: 77.9 | J5: 4163.94 | K5: =Model!L58/1000 -> 14462.836 | L5: =Model!L39/1000 -> 9033.681 | M5: =Model!L22/1000 -> 45183.036 | N5: =Model!L26/1000 -> 13326.603 | O5: =Model!L33/1000 -> 10647.812
D7: The Walt Disney Company | H7: DIS | I7: 108.77 | J7: 1790 | K7: 42030 | L7: 5700 | M7: 94420 | N7: 19210 | O7: 12400
D8: Comcast Corporation | H8: CMCSA | I8: 33.78 | J8: 3780 | K8: 99090 | L8: 7320 | M8: 123730 | N8: 38100 | O8: 16190
D9: Paramount Skydance Corporation | H9: PSKY | I9: 25.67 | J9: 674.22 | K9: 14520 | L9: 2740 | M9: 28760 | N9: 15670 | O9: -14
D10: Fox Corporation | H10: FOXA | I10: 73.8 | J10: 443.94 | K10: 6600 | L10: 4370 | M10: 16470 | N10: 3650 | O10: 2040
D12: (marketscreener.com)

Sheet Comps
A1: NETFLIX, INC.
A2: Comps Valuation
I5: Market Data | P5: Financial Data | T5: Valuation
I6: Price | J6: Shares | K6: Market Cap | L6: Debt | M6: Cash | N6: EV | P6: Sales | Q6: EBITDA | R6: Earnings | T6: EV/Sales | U6: EV/EBITDA | V6: PE
D7: Company Name | G7: Ticker | I7: ($/share) | J7: M | K7: $M | M7: & Equivalents | N7: $M | P7: $M | Q7: $M | R7: $M | T7: x | U7: x | V7: x
D8: The Walt Disney Company | G8: DIS | I8: ='Comps Data'!I7 -> 108.77 | J8: ='Comps Data'!J7 -> 1790 | K8: =I8*J8 -> 194698.3 | L8: ='Comps Data'!K7 -> 42030 | M8: ='Comps Data'!L7 -> 5700 | N8: =K8+L8-M8 -> 231028.3 | P8: ='Comps Data'!M7 -> 94420 | Q8: ='Comps Data'!N7 -> 19210 | R8: ='Comps Data'!O7 -> 12400 | T8: =N8/P8 -> 2.4468153 | U8: =N8/Q8 -> 12.02646 | V8: =K8/R8 -> 15.701476
D9: Comcast Corporation | G9: CMCSA | I9: ='Comps Data'!I8 -> 33.78 | J9: ='Comps Data'!J8 -> 3780 | K9: =I9*J9 -> 127688.4 | L9: ='Comps Data'!K8 -> 99090 | M9: ='Comps Data'!L8 -> 7320 | N9: =K9+L9-M9 -> 219458.4 | P9: ='Comps Data'!M8 -> 123730 | Q9: ='Comps Data'!N8 -> 38100 | R9: ='Comps Data'!O8 -> 16190 | T9: =N9/P9 -> 1.7736879 | U9: =N9/Q9 -> 5.760063 | V9: =K9/R9 -> 7.8868684
D10: Paramount Skydance Corporation | G10: PSKY | I10: ='Comps Data'!I9 -> 25.67 | J10: ='Comps Data'!J9 -> 674.22 | K10: =I10*J10 -> 17307.227 | L10: ='Comps Data'!K9 -> 14520 | M10: ='Comps Data'!L9 -> 2740 | N10: =K10+L10-M10 -> 29087.227 | P10: ='Comps Data'!M9 -> 28760 | Q10: ='Comps Data'!N9 -> 15670 | R10: ='Comps Data'!O9 -> -14 | T10: =N10/P10 -> 1.0113779 | U10: =N10/Q10 -> 1.8562366 | V10: =K10/R10 -> -1236.2305
D11: Fox Corporation | G11: FOXA | I11: ='Comps Data'!I10 -> 73.8 | J11: ='Comps Data'!J10 -> 443.94 | K11: =I11*J11 -> 32762.772 | L11: ='Comps Data'!K10 -> 6600 | M11: ='Comps Data'!L10 -> 4370 | N11: =K11+L11-M11 -> 34992.772 | P11: ='Comps Data'!M10 -> 16470 | Q11: ='Comps Data'!N10 -> 3650 | R11: ='Comps Data'!O10 -> 2040 | T11: =N11/P11 -> 2.124637 | U11: =N11/Q11 -> 9.5870608 | V11: =K11/R11 -> 16.060182
D13: Average | T13: =AVERAGE(T8:T11) -> 1.8391295 | U13: =AVERAGE(U8:U11) -> 7.3074551 | V13: =AVERAGE(V8:V11) -> -299.1455
D14: Median | T14: =MEDIAN(T8:T11) -> 1.9491625 | U14: =MEDIAN(U8:U11) -> 7.6735619 | V14: =MEDIAN(V8:V11) -> 11.794172
D16: Netflix, Inc. | G16: NFLX | I16: ='Comps Data'!I5 -> 77.9 | J16: ='Comps Data'!J5 -> 4163.94 | K16: =I16*J16 -> 324370.93 | L16: ='Comps Data'!K5 -> 14462.836 | M16: ='Comps Data'!L5 -> 9033.681 | N16: =K16+L16-M16 -> 329800.08 | P16: ='Comps Data'!M5 -> 45183.036 | Q16: ='Comps Data'!N5 -> 13326.603 | R16: ='Comps Data'!O5 -> 10647.812
D18: Metric | E18: Comps | H18: EV | I18: Net Debt | J18: Equity Value | K18: Shares | L18: Share Price
D19: EV/Sales | E19: =T14 -> 1.9491625 | H19: =E19*P16 -> 88069.077 | I19: =$L$16-$M$16 -> 5429.155 | J19: =H19-I19 -> 82639.922 | K19: =J16 -> 4163.94 | L19: =J19/K19 -> 19.846569
D20: EV/EBITDA | E20: =U14 -> 7.6735619 | H20: =E20*Q16 -> 102262.51 | I20: =$L$16-$M$16 -> 5429.155 | J20: =H20-I20 -> 96833.358 | K20: =K19 -> 4163.94 | L20: =J20/K20 -> 23.255224
D21: P/E | E21: =V14 -> 11.794172 | H21: =E21*R16 -> 125582.13 | I21: =$L$16-$M$16 -> 5429.155 | J21: =H21-I21 -> 120152.97 | K21: =K20 -> 4163.94 | L21: =J21/K21 -> 28.855596

Sheet Foot Ball Field
A1: NETFLIX, INC.
A2: Valuation Summary — Football Field ($ per share)
A4: Football Field Data
E6: Comps | F6: DCF | G6: 52-week high/low | H6: Market Consensus
D7: High
D8: High
D9: Low
D10: Low
A12: Valuation Summary
